Workbook

Sheet 最高报价汇总 
B2: 新元促销利率 | F2: 46099 | G2: =F2-7 -> 46092
B3: Bank | C3: 1M | D3: 3M | E3: 6M | F3: 9M | G3: 12M | H3: 18M | I3: 24M | J3: Minimum Amount | K3: Others | L3: 代表本周有调整
B4: BOC | C4: =SGD促销!C11 -> 0.011 | D4: =SGD促销!C29 -> 0.013 | E4: =SGD促销!C47 -> 0.0135 | F4: =SGD促销!C76 -> 0.012 | G4: =SGD促销!C102 -> 0.014 | H4: =[1]SGD促销!C124 -> - | I4: =[1]SGD促销!Q133 -> - | J4: 500 | K4: 手机银行
B5: BEA | C5: =SGD促销!C7 -> - | D5: =SGD促销!C27 -> 0.0135 | E5: - | F5: - | G5: =SGD促销!C109 -> 0.013 | H5: - | I5: - | J5: =SGD促销!EZ7 -> 100,000 < 2,000,000 | K5: 新资金（有网银和手机银行）
B6: CIMB | C6: - | D6: =SGD促销!C18 -> 0.0125 | E6: =SGD促销!C51 -> 0.013 | F6: =SGD促销!C78 -> 0.011 | G6: =SGD促销!C96 -> 0.013 | I6: - | J6: 10,000-1,000,000 | K6: 电子银行,Preferrec Banking personal banking -0.05% 按促销/挂牌利率续存
B7: ICBC | C7: =SGD促销!C9 -> 0.0115 | D7: =SGD促销!C25 -> 0.0135 | E7: =SGD促销!C45 -> 0.0115 | F7: =SGD促销!C74 -> 0.0105 | G7: =SGD促销!C104 -> 0.0105 | H7: - | I7: - | J7: 500 | K7: 柜面2万起存，利率-0.10%，电子银行500起存 按挂牌利率续存
B8: SingFinance | C8: =SGD促销!C13 -> 0.0105 | D8: =SGD促销!C31 -> 0.0125 | E8: =SGD促销!C54 -> 0.0125 | F8: - | G8: =SGD促销!C108 -> - | H8: - | I8: - | J8: 10000 | K8: Fresh FunCs, Online Placement
B9: CITI | C9: - | D9: =SGD促销!C22 -> 0.0125 | E9: =SGD促销!C64 -> 0.0115 | F9: - | G9: - | H9: - | I9: - | J9: 10,000-5,000,000 | K9: 新资金,citi banking customer，counter only 按挂牌利率续存
B10: SCB | C10: - | D10: - | E10: - | F10: =SGD促销!C85 -> 0.011 | G10: - | H10: - | I10: - | J10: 25000 | K10: 新资金&电子银行（网银/手机） 按挂牌利率续存
B11: SBI | C11: - | D11: - | E11: =SGD促销!C43 -> 0.0115 | F11: - | G11: =SGD促销!C100 -> 0.008 | H11: - | I11: - | J11: $50,000-1,000,000 | K11: 按挂牌利率续存 $5k - 1mil
B12: HSBC | C12: =SGD促销!C8 -> 0.006 | D12: =SGD促销!C28 -> 0.014 | E12: =SGD促销!C63 -> 0.0075 | F12: - | G12: =SGD促销!C113 -> 0.0085 | H12: - | I12: - | J12: 30000 | K12: PERSONAL CUSTOMER FRESH FUNc Mobile only
B13: RHB | C13: - | D13: =SGD促销!C23 -> 0.012 | E13: =SGD促销!C49 -> 0.012 | F13: - | G13: =SGD促销!C94 -> 0.0125 | H13: =[1]SGD促销!C128 -> - | I13: - | J13: 20000 | K13: 以上利率适用于PREMIER BANKING（AUM 20万） PERSONAL BANKING利率-0.10% APP 按促销利率续存
B14: Maybank | E14: =SGD促销!C56 -> 0.013 | F14: =SGD促销!C83 -> 0.0132 | G14: =SGD促销!C98 -> 0.0132 | H14: =[1]SGD促销!C126 -> - | I14: =[1]SGD促销!Q135 -> - | J14: 20000 | K14: savings Buncle，要求每存入1k新元活期存款，可有10k定期存款享有以上优惠利率（活期资金会被冻结） 普通定期：6M-2.45%，9M-2.40%,12M-2.35% 按挂牌利率续存
B15: HLB | D15: =SGD促销!C35 -> - | E15: =SGD促销!C70 -> 0.015 | F15: =SGD促销!C82 -> - | G15: =SGD促销!C93 -> 0.013 | H15: - | I15: - | J15: S100,000 | K15: 按挂牌利率续存
B16: HLF | D16: =SGD促销!C20 -> - | E16: =SGD促销!C57 -> 0.0125 | F16: =SGD促销!C80 -> 0.012 | G16: =SGD促销!C110 -> 0.012 | H16: - | I16: - | J16: 50000 | K16: Fresh FunCs, 手机银行
B17: OCBC | C17: - | D17: =SGD促销!C33 -> 0.014 | E17: =SGD促销!C68 -> - | F17: =SGD促销!C88 -> - | G17: =SGD促销!C115 -> 0.011 | H17: =SGD促销!C134 -> 0.0115 | I17: - | J17: 20000 | K17: internet banking over the counter -0.05%
B18: UOB | C18: - | D18: - | E18: =SGD促销!C53 -> 0.012 | F18: =SGD促销!C84 -> 0.01 | G18: =SGD促销!C112 -> - | H18: - | I18: - | J18: $10,000 | K18: 新资金 按挂牌利率续存
B19: DBS/POSB | C19: =SGD挂牌!C3 -> - | D19: =SGD挂牌!F3 -> 0.0015 | E19: =SGD挂牌!I3 -> 0.008 | F19: =SGD挂牌!L3 -> 0.01 | G19: =SGD挂牌!O3 -> 0.01 | H19: =SGD挂牌!P3 -> 0.01 | I19: =[1]SGD挂牌!Q3 -> 0.01 | J19: - | K19: 挂牌利率
B20: TrustBank | C20: 活期账户：最高2.00%（基础利息0.50%+银行卡消费至少5次，每次30新元0.50%+月均余额100k及以上0.50%+薪水入账0.50%）（cap 1.2M）
B21: GXS | C21: 活期账户：最高1.58%（SG60最多额外1.2%）(cap 60k）
B22: Maribank | C22: 活期账户：最高1.88%，基础利率1.88%（无cap）
B26: 美元促销利率市场调研 | E26: =F2 -> 46099
B27: Bank | C27: 1M | D27: 3M | E27: 6M | F27: 9M | G27: 12M | H27: Minimum Amount | I27: OTHERS
B28: BOC | C28: =USD促销!D6 -> 0.036 | D28: =USD促销!D15 -> 0.036 | E28: =USD促销!D35 -> 0.036 | F28: - | G28: =USD促销!D64 -> 0.0355 | H28: 10000 | I28: ONLINE
B29: ICBC | C29: =USD促销!D5 -> 0.036 | D29: =USD促销!D18 -> 0.0365 | E29: =USD促销!D41 -> 0.036 | F29: - | G29: =USD促销!D60 -> 0.0335 | H29: 500 | I29: ONLINE
B30: CIMB | C30: =USD促销!D7 -> 0.035 | D30: =USD促销!D16 -> 0.036 | E30: =USD促销!D39 -> 0.035 | F30: - | G30: =USD促销!D56 -> 0.034 | H30: 10000 | I30: ONLINE
B31: SCB | C31: =USD促销!D10 -> - | D31: =USD促销!G10 -> - | E31: =USD促销!H10 -> - | F31: =USD促销!D49 -> 0.036 | G31: =USD促销!I10 -> - | H31: 25000 | I31: priority private fresh fund 4.00% personal banking
B32: SBI | C32: - | D32: =USD促销!D25 -> 0 | E32: =USD促销!D43 -> 0.038 | F32: - | G32: =USD促销!D63 -> 0 | H32: 25000 | I32: over the counter
B33: CITI | C33: =USD促销!D8 -> 0.0325 | F33: - | H33: $50,000 | I33: 外币兑换+柜台
B34: RHB | C34: - | D34: - | E34: =USD促销!D42 -> 0.034 | F34: - | G34: =USD促销!D62 -> 0.034 | H34: USD$5,000 | I34: Mobile banking
B35: BEA | C35: =USD促销!D9 -> 0.0325 | D35: =USD促销!D26 -> 0.0345 | E35: =USD促销!D46 -> 0.034 | F35: - | G35: =USD促销!D55 -> 0.0335 | H35: USD$100,000 | I35: personal
B36: HSBC | C36: - | D36: =USD促销!D24 -> 0.03 | E36: =USD促销!D44 -> 0.0285 | F36: - | G36: =USD促销!D58 -> 0.0215 | H36: 30000 | I36: personal
B40: 美元挂牌利率市场调研 | H40: =F2 -> 46099
B41: Bank | C41: 7D | D41: 1M | E41: 3M | F41: 6M | G41: 9M | H41: 12M | I41: 18M | J41: 24M | K41: Minimum Amount | L41: OTHERS | M41: =L3 -> 代表本周有调整
B42: BOC | C42: =USD挂牌!D10 -> 0.027 | D42: =USD挂牌!D38 -> 0.033 | E42: =USD挂牌!D85 -> 0.033 | F42: =USD挂牌!D132 -> 0.0305 | G42: =USD挂牌!D173 -> 0.03 | H42: =USD挂牌!D193 -> 0.029 | I42: =USD挂牌!D234 -> 0.025 | J42: =USD挂牌!D241 -> 0.02 | K42: 500000
B43: ICBC | C43: - | D43: =USD挂牌!D50 -> 0.036 | E43: =USD挂牌!D97 -> 0.0365 | F43: =USD挂牌!D144 -> 0.036 | G43: - | H43: =USD挂牌!D205 -> 0.033 | I43: - | J43: - | K43: 500 | L43: 柜台2万起存，电子银行500起存
B44: DBS/POSB | C44: =USD挂牌!D16 -> 0 | D44: =USD挂牌!D56 -> 0.0348 | E44: =USD挂牌!D103 -> 0.0342 | F44: =USD挂牌!D150 -> 0.0308 | G44: - | H44: =USD挂牌!D211 -> 0.0299 | I44: - | J44: - | K44: 250000
B45: UOB | C45: =USD挂牌!D7 -> 0.0255 | D45: =USD挂牌!D35 -> 0.0324 | E45: =USD挂牌!D82 -> 0.0326 | F45: =USD挂牌!D129 -> 0.0306 | G45: - | H45: =USD挂牌!D190 -> 0.029 | I45: - | J45: - | K45: $250,000-$500,000
B46: Maybank | C46: - | D46: =USD挂牌!D31 -> 0.0315 | E46: =USD挂牌!D78 -> 0.0315 | F46: =USD挂牌!D125 -> 0.0315 | G46: - | H46: - | I46: - | J46: - | K46: 100000
B47: OCBC | C47: - | D47: =USD挂牌!D61 -> 0.0325 | E47: =USD挂牌!D108 -> 0.0325 | F47: =USD挂牌!D155 -> 0.03 | G47: =USD挂牌!D178 -> 0.0293 | H47: =USD挂牌!D216 -> 0.0282 | I47: - | J47: - | K47: 500000
B48: RHB | C48: =USD挂牌!D24 -> 0.0005 | D48: =USD挂牌!D69 -> 0.032 | E48: =USD挂牌!D116 -> 0.033 | F48: =USD挂牌!D163 -> 0.0325 | G48: =USD挂牌!D182 -> 0.0305 | H48: =USD挂牌!D224 -> 0.0285 | I48: - | J48: =USD挂牌!D245 -> 0.0285 | K48: 500000
B49: SBI | C49: - | D49: =USD挂牌!D72 -> 0.0275 | E49: =USD挂牌!D119 -> 0.0325 | F49: =USD挂牌!D166 -> 0.0325 | G49: - | H49: =USD挂牌!D227 -> 0.03 | I49: =USD挂牌!D235 -> 0.01 | J49: =USD挂牌!D246 -> 0.005 | K49: 25000
B50: BEA | C50: =USD挂牌!D25 -> 0.0277 | D50: =USD挂牌!D70 -> 0.0312 | E50: =USD挂牌!D117 -> 0.0332 | F50: =USD挂牌!D164 -> 0.0327 | G50: - | H50: =USD挂牌!D225 -> 0.0322 | I50: - | J50: - | K50: =USD挂牌!C225 -> 10,000以上
B51: HLB | C51: - | D51: =USD挂牌!D71 -> 0.029407 | E51: =USD挂牌!D118 -> 0.029966 | F51: =USD挂牌!D165 -> 0.029657 | G51: - | H51: =USD挂牌!D226 -> 0.028903 | K51: =USD挂牌!C226 -> ≥50,000
B52: CIMB | C52: - | D52: =USD挂牌!D42 -> 0.026 | E52: =USD挂牌!D89 -> 0.0275 | F52: =USD挂牌!D136 -> 0.0265 | G52: - | H52: =USD挂牌!D197 -> 0.026 | I52: - | J52: - | K52: 250000
B53: SCB | C53: =USD挂牌!D20 -> 0.025 | D53: =USD挂牌!D65 -> 0.024765 | E53: =USD挂牌!D112 -> 0.025248 | F53: =USD挂牌!D159 -> 0.026882 | G53: - | H53: =USD挂牌!D220 -> 0.027476 | I53: - | J53: - | K53: 500000
B54: HSBC | C54: - | D54: =USD挂牌!D48 -> 0.0305 | E54: =USD挂牌!D95 -> 0.029 | F54: =USD挂牌!D142 -> 0.0275 | G54: - | H54: =USD挂牌!D203 -> 0.0205 | I54: - | J54: - | K54: $100,000
B57: 人民币挂牌利率 | H57: =F2 -> 46099
B58: Bank | C58: 1M | D58: 3M | E58: 6M | F58: 9M | G58: 12M | H58: 18M | I58: 24M | J58: Minimum Amount | K58: others | L58: =L3 -> 代表本周有调整
B59: BOC | C59: =CNY挂牌!Q12 -> 0.0125 | D59: =CNY挂牌!Q35 -> 0.0135 | E59: =CNY挂牌!Q58 -> 0.014 | F59: =CNY挂牌!Q81 -> 0.015 | G59: =CNY挂牌!Q93 -> 0.0145 | H59: 0.0155 | I59: 0.0155 | J59: 200000
B60: ICBC | C60: =CNY挂牌!Q9 -> 0.012 | D60: =CNY挂牌!Q32 -> 0.013 | E60: =CNY挂牌!Q55 -> 0.0135 | F60: =CNY挂牌!Q78 -> 0.014 | G60: =CNY挂牌!Q90 -> 0.014 | H60: - | I60: - | J60: 50000 | K60: online banking
B61: UOB | C61: =CNY挂牌!Q19 -> 0.0115 | D61: =CNY挂牌!Q42 -> 0.0125 | E61: =CNY挂牌!Q65 -> 0.0135 | F61: - | G61: =CNY挂牌!Q100 -> 0.0145 | J61: $250,000-$500,000
B62: CIMB | C62: =CNY挂牌!Q7 -> 0.0083 | D62: =CNY挂牌!Q30 -> 0.0083 | E62: =CNY挂牌!Q53 -> 0.0108 | F62: - | G62: =CNY挂牌!Q88 -> 0.0128 | H62: - | I62: - | J62: 250000
B63: BEA | C63: =CNY挂牌!Q13 -> 0.006 | D63: =CNY挂牌!Q36 -> 0.008 | E63: =CNY挂牌!Q59 -> 0.0085 | F63: - | G63: =CNY挂牌!Q94 -> 0.009 | J63: ≥10,000USD
B66: Bank | C66: 澳元利率 | F66: 新西兰元利率 | I66: 欧元利率 | L66: 英镑利率
C67: 1M | D67: 3M | E67: 6M | F67: 1M | G67: 3M | H67: 6M | I67: 1M | J67: 3M | K67: 6M | L67: 1M | M67: 3M | N67: 6M | O67: 促销金额 | P67: 要求
B68: BOC | C68: =其他外币促销利率!D6 -> 0.0335 | D68: =其他外币促销利率!D13 -> 0.034 | E68: =其他外币促销利率!D21 -> 0.0345 | F68: =其他外币促销利率!D80 -> 0.02 | G68: =其他外币促销利率!D88 -> 0.02 | H68: =其他外币促销利率!D95 -> 0.0205 | I68: =其他外币促销利率!D30 -> 0.018 | J68: =其他外币促销利率!D37 -> 0.018 | K68: =其他外币促销利率!D43 -> 0.0185 | L68: =其他外币促销利率!D51 -> 0.0345 | M68: =其他外币促销利率!D58 -> 0.0345 | N68: =其他外币促销利率!D65 -> 0.034 | O68: 10000 | P68: 手机银行
B69: CIMB | C69: =其他外币促销利率!D7 -> 0.035 | D69: =其他外币促销利率!D14 -> 0.036 | E69: =其他外币促销利率!D22 -> 0.037 | F69: =其他外币促销利率!D81 -> 0 | G69: =其他外币促销利率!D89 -> 0 | H69: =其他外币促销利率!D96 -> 0 | I69: =其他外币促销利率!D31 -> 0 | J69: =其他外币促销利率!D38 -> 0 | K69: =其他外币促销利率!D44 -> 0 | L69: =其他外币促销利率!D52 -> 0.034 | M69: =其他外币促销利率!D59 -> 0.0345 | N69: =其他外币促销利率!D66 -> 0.0325 | O69: 本币250,000 | P69: 电子银行
B70: RHB | C70: - | D70: - | E70: =其他外币促销利率!D24 -> 0.038 | F70: =其他外币促销利率!D84 -> 0.016 | G70: =其他外币促销利率!D91 -> 0.016 | H70: =其他外币促销利率!D98 -> 0.0155 | I70: - | J70: - | K70: - | L70: - | M70: - | N70: =其他外币促销利率!D68 -> 0.034 | O70: 5,000-100,000
B71: CITI | C71: =其他外币促销利率!D8 -> 0.0325 | D71: - | E71: - | F71: =其他外币促销利率!D82 -> 0.02 | G71: - | H71: - | I71: =其他外币促销利率!D32 -> 0.0175 | J71: - | K71: - | L71: =其他外币促销利率!D53 -> 0.0325 | M71: - | O71: USD50,000 | P71: 外币兑换+柜台
B72: BEA | C72: =其他外币促销利率!D5 -> 0.0335 | D72: =其他外币促销利率!D12 -> 0.035 | E72: =其他外币促销利率!D20 -> 0.0365 | F72: =其他外币促销利率!D83 -> 0.018 | G72: =其他外币促销利率!D90 -> 0.0185 | H72: =其他外币促销利率!D97 -> 0.019 | I72: =其他外币促销利率!D33 -> 0.0155 | J72: =其他外币促销利率!D39 -> 0.0165 | K72: =其他外币促销利率!D45 -> 0.0175 | L72: =其他外币促销利率!D54 -> 0.034 | M72: =其他外币促销利率!D60 -> 0.034 | N72: =其他外币促销利率!D68 -> 0.034
F73: note：CIMB和 RHB仅有挂牌利率报价 | I73: note：CIMB为挂牌利率报价

Sheet SGD促销
A1: 新元促销利率市场调研
A2: 1 Month
A3: 日期 | C3: ='最高报价汇总 '!F2 -> 46099 | D3: ='最高报价汇总 '!G2 -> 46092 | E3: 46085 | F3: 46078 | G3: 46071 | H3: 46064 | I3: 46057 | J3: 46050 | K3: 46043 | L3: 46036 | M3: 46029 | N3: 46022 | O3: 46015 | P3: 46008 | Q3: 46001 | R3: 45994 | S3: ='最高报价汇总 '!G2 -> 46092 | T3: 45980 | U3: 45973 | V3: 45966 | W3: 45959 | X3: 45952 | Y3: 45945 | Z3: 45938 | AA3: 45931 | AB3: 45924 | AC3: 45917 | AD3: 45910 | AE3: ='最高报价汇总 '!G2 -> 46092 | AF3: 45896 | AG3: 45889 | AH3: 45882 | AI3: 45875 | AJ3: 45868 | AK3: 45861 | AL3: 45854 | AM3: 45847 | AN3: 45840 | AO3: 45833 | AP3: 45826 | AQ3: 45819 | AR3: 45812 | AS3: 45805 | AT3: 45798 | AU3: 45792 | AV3: 45785 | AW3: 45777 | AX3: 45771 | AY3: 45763 | AZ3: 45757 | BA3: 45750 | BB3: 45742 | BC3: ='[2]最高报价汇总 '!H2 -> #REF! | BD3: 45729 | BE3: 45722 | BF3: 45715 | BG3: 45708 | BH3: 45701 | BI3: 45694 | BJ3: 45688 | BK3: 45315 | BL3: 45673 | BM3: 45666 | BN3: 45659 | BO3: 45652 | BP3: 45645 | BQ3: 45638 | BR3: 45631 | BS3: 45625 | BT3: 45617 | BU3: 45610 | BV3: 45603 | BW3: 45595 | BX3: 45591 | BY3: 45582 | BZ3: 45575 | CA3: 45568 | CB3: 45561 | CC3: 45554 | CD3: 45547 | CE3: 45540 | CF3: 45533 | CG3: 45526 | CH3: 45519 | CI3: 45511 | CJ3: 45505 | CK3: 45498 | CL3: 45492 | CM3: 11/7/224 | CN3: 45477 | CO3: 45464 | CP3: 45456 | CQ3: 45449 | CR3: 45442 | CS3: 45435 | CT3: 45428 | CU3: 45421 | CV3: 45414 | CW3: 45407 | CX3: 45400 | CY3: 45393 | CZ3: 45386 | DA3: 45378 | DB3: 45372 | DC3: 45365 | DD3: 45358 | DE3: 45351 | DF3: 45343 | DG3: 45336 | DH3: 45329 | DI3: 45323 | DJ3: 45316 | DK3: 45309 | DL3: 45302 | DM3: 45295 | DN3: 45288 | DO3: 45281 | DP3: 14/21/2023 | DQ3: 45267 | DR3: 45260 | DS3: 45253 | DT3: 45246 | DU3: 45239 | DV3: 45232 | DW3: 45225 | DX3: 45218 | DY3: 45211 | DZ3: 45204 | EA3: 45197 | EB3: 45190 | EC3: 45183 | ED3: 45176 | EE3: 45168 | EF3: 45162 | EG3: 45155 | EH3: 45148 | EI3: 45141 | EJ3: 45134 | EK3: 45127 | EL3: 45120 | EM3: 45113 | EN3: 45105 | EO3: 45099 | EP3: 45092 | EQ3: 45085 | ER3: 45076 | ES3: 45070 | ET3: 45063 | EU3: 45056 | EV3: 45049 | EW3: 45042 | EX3: 45035 | EY3: 45028 | FA3: 44803 | FD3: 44706 | FI3: 44685 | FJ3: 44699 | FK3: 44690 | FL3: 44713 | FM3: 44720 | FN3: 44727 | FO3: 44733 | FP3: 44741 | FQ3: 44755 | FR3: 44748 | FS3: 44769 | FT3: 44762 | FU3: 44783 | FV3: 44776 | FW3: 44797 | FX3: 44790 | FY3: 44805 | FZ3: 45000 | GA3: 44993 | GB3: 44986 | GC3: 44979 | GD3: 44972 | GE3: 44965 | GF3: 44958 | GG3: 44951 | GH3: 44944 | GI3: 44937 | GJ3: 44930 | GK3: 44923 | GL3: 44916 | GM3: 44910 | GN3: 44902 | GO3: 44896 | GP3: 44888 | GQ3: 44881 | GR3: 44874 | GS3: 44868 | GT3: 44860 | GU3: 44853 | GV3: 44846 | GW3: 44839 | GX3: 44831 | GY3: 44825 | GZ3: 44818 | HA3: 44811 | HB3: 45002 | HC3: 45020 | HD3: 45014 | HE3: 45008
B4: 全部公开报价 | C4: 当日最高报价 | D4: 当日最高报价 | E4: 当日最高报价 | F4: 当日最高报价 | G4: 当日最高报价 | H4: 当日最高报价 | I4: 当日最高报价 | J4: 当日最高报价 | K4: 当日最高报价 | L4: 当日最高报价 | M4: 当日最高报价 | N4: 当日最高报价 | O4: 当日最高报价 | P4: 当日最高报价 | Q4: 当日最高报价 | R4: 当日最高报价 | S4: 当日最高报价 | T4: 当日最高报价 | U4: 当日最高报价 | V4: 当日最高报价 | W4: 当日最高报价 | X4: 当日最高报价 | Y4: 当日最高报价 | Z4: 当日最高报价 | AA4: 当日最高报价 | AB4: 当日最高报价 | AC4: 当日最高报价 | AD4: 当日最高报价 | AE4: 当日最高报价 | AF4: 当日最高报价 | AG4: 当日最高报价 | AH4: 当日最高报价 | AI4: 当日最高报价 | AJ4: 当日最高报价 | AK4: 当日最高报价 | AL4: 当日最高报价 | AM4: 当日最高报价 | AN4: 当日最高报价 | AO4: 当日最高报价 | AP4: 当日最高报价 | AQ4: 当日最高报价 | AR4: 当日最高报价 | AS4: 当日最高报价 | AT4: 当日最高报价 | AU4: 当日最高报价 | AV4: 当日最高报价 | AW4: 当日最高报价 | AX4: 当日最高报价 | AY4: 当日最高报价 | AZ4: 当日最高报价 | BA4: 当日最高报价 | BB4: 当日最高报价 | BC4: 当日最高报价 | BD4: 当日最高报价 | BE4: 当日最高报价 | BF4: 当日最高报价 | BG4: 当日最高报价 | BH4: 当日最高报价 | BI4: 当日最高报价 | BJ4: 当日最高报价 | BK4: 当日最高报价 | BL4: 当日最高报价 | BM4: 当日最高报价 | BN4: 当日最高报价 | BO4: 当日最高报价 | BP4: 当日最高报价 | BQ4: 当日最高报价 | BR4: 当日最高报价 | BS4: 当日最高报价 | BT4: 当日最高报价 | BU4: 当日最高报价 | BV4: 当日最高报价 | BW4: 当日最高报价 | BX4: 当日最高报价 | BY4: 当日最高报价 | BZ4: 当日最高报价 | CA4: 当日最高报价 | CB4: 当日最高报价 | CC4: 当日最高报价 | CD4: 当日最高报价 | CE4: 当日最高报价 | CF4: 当日最高报价 | CG4: 当日最高报价 | CH4: 当日最高报价 | CI4: 当日最高报价 | CJ4: 当日最高报价 | CK4: 当日最高报价 | CL4: 当日最高报价 | CM4: 当日最高报价 | CN4: 当日最高报价 | CO4: 当日最高报价 | CP4: 当日最高报价 | CQ4: 当日最高报价 | CR4: 当日最高报价 | CS4: 当日最高报价 | CT4: 当日最高报价 | CU4: 当日最高报价 | CV4: 当日最高报价 | CW4: 当日最高报价 | CX4: 当日最高报价 | CY4: 当日最高报价 | CZ4: 当日最高报价 | DA4: 当日最高报价 | DB4: 当日最高报价 | DC4: 当日最高报价 | DD4: 当日最高报价 | DE4: 当日最高报价 | DF4: 当日最高报价 | DG4: 当日最高报价 | DH4: 当日最高报价 | DI4: 当日最高报价 | DJ4: 当日最高报价 | DK4: 当日最高报价 | DL4: 当日最高报价 | DM4: 当日最高报价 | DN4: 当日最高报价 | DO4: 当日最高报价 | DP4: 当日最高报价 | DQ4: 当日最高报价 | DR4: 当日最高报价 | DS4: 当日最高报价 | DT4: 当日最高报价 | DU4: 当日最高报价 | DV4: 当日最高报价 | DW4: 当日最高报价 | DX4: 当日最高报价 | DY4: 当日最高报价 | DZ4: 当日最高报价 | EA4: 当日最高报价 | EB4: 当日最高报价 | EC4: 当日最高报价 | ED4: 当日最高报价 | EE4: 当日最高报价 | EF4: 当日最高报价 | EG4: 当日最高报价 | EH4: 当日最高报价 | EI4: 当日最高报价 | EJ4: 当日最高报价 | EK4: 当日最高报价 | EL4: 当日最高报价 | EM4: 当日最高报价 | EN4: 当日最高报价 | EO4: 当日最高报价 | EP4: 当日最高报价 | EQ4: 当日最高报价 | ER4: 当日最高报价 | ES4: 当日最高报价 | ET4: 当日最高报价 | EU4: 当日最高报价 | EV4: 当日最高报价 | EW4: 当日最高报价 | EX4: 当日最高报价 | EY4: 当日最高报价 | EZ4: 金额 | FA4: 当日最高报价 | FB4: 全部公开报价 | FC4: 金额 | FD4: 当日最高报价 | FE4: 全部公开报价 | FF4: 金额 | FG4: 挂牌利率/促销利率 | FH4: 当日最高报价 | FI4: 当日最高报价 | FJ4: 当日最高报价 | FK4: 当日最高报价 | FL4: 当日最高报价 | FM4: 当日最高报价 | FN4: 当日最高报价 | FO4: 当日最高报价 | FP4: 当日最高报价 | FQ4: 当日最高报价 | FR4: 当日最高报价 | FS4: 当日最高报价 | FT4: 当日最高报价 | FU4: 当日最高报价 | FV4: 当日最高报价 | FW4: 当日最高报价 | FX4: 当日最高报价 | FY4: 当日最高报价 | FZ4: 当日最高报价 | GA4: 当日最高报价 | GB4: 当日最高报价 | GC4: 当日最高报价 | GD4: 当日最高报价 | GE4: 当日最高报价 | GF4: 当日最高报价 | GG4: 当日最高报价 | GH4: 当日最高报价 | GI4: 当日最高报价 | GJ4: 当日最高报价 | GK4: 当日最高报价 | GL4: 当日最高报价 | GM4: 当日最高报价 | GN4: 当日最高报价 | GO4: 当日最高报价 | GP4: 当日最高报价 | GQ4: 当日最高报价 | GR4: 当日最高报价 | GS4: 当日最高报价 | GT4: 当日最高报价 | GU4: 当日最高报价 | GV4: 当日最高报价 | GW4: 当日最高报价 | GX4: 当日最高报价 | GY4: 当日最高报价 | GZ4: 当日最高报价 | HA4: 当日最高报价 | HB4: 当日最高报价 | HC4: 当日最高报价 | HD4: 当日最高报价 | HE4: 当日最高报价 | HF4: 当日最高报价变动
A5: SCB | B5: >200K | O5: 0.0188 | P5: 0.0188 | Q5: 0.0188 | S5: - | T5: - | U5: - | V5: - | W5: - | X5: - | Y5: - | Z5: - | AA5: - | AB5: - | AC5: - | AD5: - | AE5: - | AF5: - | AG5: - | AH5: - | AI5: - | AJ5: - | AK5: - | AL5: - | AM5: - | AN5: - | AO5: - | AP5: - | AQ5: - | AR5: - | AS5: - | AT5: - | AU5: - | AV5: - | AW5: - | AX5: - | AY5: - | AZ5: - | BA5: - | BB5: - | BC5: - | BD5: - | BE5: - | BF5: - | BG5: - | BH5: - | BI5: - | BJ5: - | BK5: - | BL5: - | BM5: - | BN5: - | BO5: - | BP5: - | BQ5: - | BR5: - | BS5: - | BT5: - | BU5: - | BV5: - | BW5: - | BX5: - | BY5: - | BZ5: - | CA5: - | CB5: - | CC5: - | CD5: - | CE5: - | CF5: - | CG5: - | CH5: - | CI5: - | CJ5: - | CK5: - | CL5: - | CM5: - | CN5: - | CO5: - | CP5: - | CQ5: - | CR5: - | CS5: - | CT5: - | CU5: - | CV5: - | CW5: - | CX5: - | CY5: - | CZ5: - | DA5: - | DB5: - | DC5: - | DD5: - | DE5: - | DF5: - | DG5: - | DH5: - | DI5: - | DJ5: - | DK5: - | DL5: - | DM5: - | DN5: - | DO5: - | DP5: - | DQ5: - | DR5: - | DS5: - | DT5: - | DU5: - | DV5: - | DW5: - | DX5: - | DY5: - | DZ5: - | EA5: - | EB5: - | EC5: - | ED5: - | EE5: - | EF5: - | EG5: - | EH5: - | EI5: - | EJ5: - | EK5: - | EL5: - | EM5: 0.0298 | EN5: 0.0298 | EO5: 0.0298 | EP5: 0.0298 | EQ5: 0.0298 | EZ5: 20,000 < 50,000 | HF5: =C5-D5 -> 0 | HG5: Fresh Fund
EZ6: ≥50,000
A7: BEA | B7: 3.00%fresh fund | C7: - | D7: - | E7: - | F7: - | G7: - | H7: - | I7: - | J7: - | K7: - | L7: - | M7: - | N7: - | O7: - | P7: - | Q7: - | R7: - | S7: - | T7: - | U7: - | V7: - | W7: - | X7: - | Y7: - | Z7: - | AA7: - | AB7: - | AC7: - | AD7: - | AE7: - | AF7: - | AG7: - | AH7: - | AI7: - | AJ7: - | AK7: - | AL7: - | AM7: - | AN7: - | AO7: - | AP7: - | AQ7: - | AR7: - | AS7: - | AT7: - | AU7: - | AV7: - | AW7: - | AX7: - | AY7: - | AZ7: - | BA7: - | BB7: - | BC7: - | BD7: - | BE7: - | BF7: - | BG7: - | BH7: - | BI7: - | BJ7: - | BK7: - | BL7: - | BM7: - | BN7: - | BO7: - | BP7: - | BQ7: - | BR7: - | BS7: - | BT7: - | BU7: - | BV7: - | BW7: - | BX7: - | BY7: - | BZ7: - | CA7: - | CB7: - | CC7: - | CD7: - | CE7: - | CF7: 0.03 | CG7: 0.03 | CH7: 0.03 | CI7: - | CJ7: - | CK7: - | CL7: - | CM7: - | CN7: - | CO7: - | CP7: - | CQ7: - | CR7: - | CS7: - | CT7: - | CU7: - | CV7: - | CW7: - | CX7: - | CY7: - | CZ7: - | DA7: - | DB7: - | DC7: - | DD7: - | DE7: - | DF7: - | DG7: - | DH7: - | DI7: - | DJ7: - | DK7: - | DL7: - | DM7: - | DN7: - | DO7: - | DP7: - | DQ7: - | DR7: - | DS7: - | DT7: - | DU7: - | DV7: - | DW7: - | DX7: - | DY7: 0.028 | DZ7: 0.028 | EA7: 0.028 | EB7: 0.028 | EC7: 0.028 | ED7: 0.028 | EE7: 0.028 | EF7: 0.028 | EG7: 0.028 | EH7: 0.028 | EI7: 0.028 | EJ7: 0.028 | EK7: 0.028 | EL7: 0.028 | EM7: 0.028 | EN7: 0.028 | EO7: 0.028 | EP7: 0.028 | EQ7: 0.028 | ER7: 0.028 | EZ7: 100,000 < 2,000,000 | HF7: -
A8: HSBC | B8: 0.60% personal (counter) 0.65% premier w/o wealth products (counter) 0.9% premier w wealth holdings or FX Engaged (Mobile App only+$30K fresh funds) | C8: 0.006 | D8: 0.006 | E8: 0.006 | F8: 0.0065 | G8: 0.0065 | H8: 0.0065 | I8: 0.0065 | J8: 0.007 | K8: 0.007 | L8: 0.007 | M8: 0.007 | N8: 0.007 | O8: 0.007 | P8: 0.007 | Q8: 0.007 | R8: 0.007 | S8: 0.0085 | T8: 0.0085 | U8: 0.0085 | V8: 0.0085 | W8: 0.0085 | X8: 0.0085 | Y8: 0.0085 | Z8: 0.0085 | AA8: 0.0085 | AB8: 0.0085 | AC8: 0.0085 | AD8: 0.0085 | AE8: 0.01 | AF8: 0.011 | AG8: 0.0115 | AH8: 0.012 | AI8: 0.012 | AJ8: 0.012 | AK8: 0.0095 | AL8: 0.0095 | AM8: 0.0095 | AN8: 0.0095 | HF8: =C8-D8 -> 0
A9: ICBC | B9: 1.10%（online） | C9: 0.0115 | D9: 0.0115 | E9: 0.0115 | F9: 0.0115 | G9: 0.0115 | H9: 0.0115 | I9: 0.0115 | J9: 0.0115 | K9: 0.0115 | L9: 0.0115 | M9: 0.012 | N9: 0.012 | O9: 0.012 | P9: 0.012 | Q9: 0.012 | R9: 0.012 | S9: 0.012 | T9: 0.012 | U9: 0.012 | V9: 0.012 | W9: 0.012 | X9: 0.012 | Y9: 0.012 | Z9: 0.012 | AA9: 0.012 | AB9: 0.012 | AC9: 0.012 | AD9: 0.013 | AE9: 0.013 | AF9: 0.0145 | AG9: 0.0145 | AH9: 0.015 | AI9: 0.015 | AJ9: 0.015 | AK9: 0.015 | AL9: 0.015 | AM9: 0.018 | AN9: 0.018 | AO9: 0.018 | AP9: 0.018 | AQ9: 0.019 | AR9: 0.0205 | AS9: 0.0205 | AT9: 0.0205 | AU9: 2.2%（电子银行） | AV9: 2.2%（电子银行） | AW9: 2.2%（电子银行） | AX9: 2.2%（电子银行） | AY9: 2.2%（电子银行） | AZ9: 2.35%电子/2.35%柜台 | BA9: 2.35%电子/2.35%柜台 | BB9: =BC9 -> 2.8% （电子银行） | BC9: =BD9 -> 2.8% （电子银行） | BD9: =BE9 -> 2.8% （电子银行） | BE9: =BF9 -> 2.8% （电子银行） | BF9: =BG9 -> 2.8% （电子银行） | BG9: =BH9 -> 2.8% （电子银行） | BH9: =BI9 -> 2.8% （电子银行） | BI9: =BJ9 -> 2.8% （电子银行） | ... CB9: =CC9 -> 2.8% （电子银行） | CC9: 2.8% （电子银行） | CD9: 0.029 | CE9: 0.029 | CF9: 0.029 | CG9: 0.029 | CH9: 0.029 | CI9: 0.029 | CJ9: 0.029 | CK9: 0.029 | CL9: 0.029 | CM9: 0.029 | CN9: 0.029 | CO9: 0.029 | CP9: 0.029 | CQ9: 0.029 | CR9: 0.029 | CS9: 0.029 | CT9: 0.029 | CU9: 0.029 | CV9: 0.029 | CW9: 0.029 | CX9: 0.029 | CY9: 0.029 | CZ9: 0.029 | DA9: 0.029 | DB9: 0.029 | DC9: 0.029 | DD9: 0.029 | DE9: 0.029 | DF9: 0.029 | DG9: 0.029 | DH9: 0.029 | DI9: 0.029 | DJ9: 0.029 | DK9: 0.029 | DL9: 0.029 | DM9: 0.029 | DN9: 0.029 | DO9: 0.029 | DP9: 0.029 | DQ9: 0.029 | DR9: 0.029 | DS9: 0.029 | DT9: 0.029 | DU9: 0.029 | DV9: 0.029 | DW9: 0.029 | DX9: 0.029 | DY9: 0.029 | DZ9: 0.029 | EA9: 0.029 | EB9: 0.029 | EC9: 0.029 | ED9: 0.029 | EE9: 0.029 | EF9: 0.029 | EG9: 0.029 | EH9: 0.029 | EI9: 0.029 | EJ9: 0.029 | EK9: 0.029 | EL9: 0.029 | EM9: 0.029 | EN9: 0.029 | EO9: 0.029 | EP9: 0.029 | EQ9: 0.029 | ER9: 0.029 | ES9: 0.029 | ET9: 0.029 | EU9: 0.029 | EV9: 0.029 | EW9: 0.0295 | EX9: 0.031 | EY9: 0.031 | EZ9: ≥20,000 | FA9: 0.006 | FB9: 0.55% 柜面 | FC9: ≥500 | FD9: 0.006 | FE9: 0.55% 柜面 | FF9: ≥500 | FG9: 促销 | FH9: 0.0045 | FI9: 0.0045 | FJ9: 0.0045 | FK9: 0.0045 | FL9: 0.006 | FM9: 0.006 | FN9: 0.006 | FO9: 0.006 | FP9: 0.006 | FQ9: 0.006 | FR9: 0.006 | FS9: 0.006 | FT9: 0.006 | FU9: 0.006 | FV9: 0.006 | FW9: 0.006 | FX9: 0.006 | FY9: 0.0015 | FZ9: 0.031 | GA9: 0.031 | GB9: 0.031 | GC9: 0.036 | GD9: 0.036 | GE9: 0.036 | GF9: 0.036 | GG9: 0.036 | GH9: 0.023 | GI9: 0.023 | GJ9: 0.023 | GK9: 0.023 | GL9: 0.023 | GM9: 0.023 | GN9: 0.023 | GO9: 0.023 | GP9: 0.023 | GQ9: 0.023 | GR9: 0.023 | GS9: 0.0195 | GT9: 0.0195 | GU9: 0.0195 | GV9: 0.0165 | GW9: 0.0165 | GX9: 0.0165 | GY9: 0.0015 | GZ9: 0.0015 | HA9: 0.0015 | HB9: 0.031 | HC9: 0.031 | HD9: 0.031 | HE9: 0.031 | HF9: =C9-D9 -> 0 | HG9: 500-20k
B10: 1.15%（online）>200k | HG10: >200k
A11: BOC | B11: 1.15% (counter) | C11: 0.011 | D11: 0.011 | E11: 0.0115 | F11: 0.0115 | G11: 0.0115 | H11: 0.0115 | I11: 0.0115 | J11: 0.0115 | K11: 0.012 | L11: 0.012 | M11: 0.012 | N11: 0.012 | O11: 0.012 | P11: 0.012 | Q11: 0.012 | R11: 0.012 | S11: 0.012 | T11: 0.012 | U11: 0.012 | V11: 0.012 | W11: 0.012 | X11: 0.012 | Y11: 0.012 | Z11: 0.012 | AA11: 0.012 | AB11: 0.012 | AC11: 0.0125 | AD11: 0.0125 | AE11: 0.0145 | AF11: 0.015 | AG11: 0.0155 | AH11: 0.0155 | AI11: 0.0155 | AJ11: 0.0155 | AK11: 0.017 | AL11: 0.018 | AM11: 0.018 | AN11: 0.018 | AO11: 0.0185 | AP11: 0.02 | AQ11: 0.0205 | AR11: 0.0205 | AS11: 0.021 | AT11: 0.022 | AU11: 0.0225 | AV11: 0.0235 | AW11: 0.0235 | AX11: 0.024 | AY11: 0.024 | AZ11: 0.024 | BA11: 0.024 | BB11: 0.024 | BC11: 0.024 | BD11: 0.025 | BE11: 0.026 | BF11: 0.026 | BG11: 0.026 | BH11: 0.026 | BI11: 0.026 | BJ11: 0.026 | BK11: 0.026 | BL11: 2.6%↓ | BM11: 0.027 | BN11: 0.027 | BO11: 0.027 | BP11: 0.027 | BQ11: 0.027 | BR11: 0.027 | BS11: 0.027 | BT11: 0.027 | BU11: 0.027 | BV11: 0.027 | BW11: 0.027 | BX11: 0.027 | BY11: 0.027 | BZ11: 0.027 | CA11: 0.027 | CB11: 0.0285 | CC11: 0.0295 | CD11: 0.0295 | CE11: 0.0295 | CF11: 0.0295 | CG11: 0.0295 | CH11: 0.0295 | CI11: 0.0295 | CJ11: 0.0295 | CK11: 0.03 | CL11: 0.03 | CM11: 0.03 | CN11: 0.03 | CO11: 0.03 | CP11: 0.03 | CQ11: 0.03 | CR11: 0.03 | CS11: 0.03 | CT11: 0.029 | CU11: 0.029 | CV11: 0.029 | CW11: 0.029 | CX11: 0.029 | CY11: 0.029 | CZ11: 0.029 | DA11: 0.029 | DB11: 0.029 | DC11: 0.029 | DD11: 0.029 | DE11: 0.029 | DF11: 0.029 | DG11: 0.029 | DH11: 0.029 | DI11: 0.029 | DJ11: 0.029 | DK11: 0.029 | DL11: 0.029 | DM11: 0.029 | DN11: 0.029 | DO11: 0.029 | DP11: 0.029 | DQ11: 0.029 | DR11: 0.029 | DS11: 0.029 | DT11: 0.029 | DU11: 0.029 | DV11: 0.029 | DW11: 0.029 | DX11: 0.029 | DY11: 0.029 | DZ11: 0.03 | EA11: 0.03 | EB11: 0.03 | EC11: 0.03 | ED11: 0.03 | EE11: 0.03 | EF11: 0.03 | EG11: 0.03 | EH11: 0.03 | EI11: 0.03 | EJ11: 0.03 | EK11: 0.03 | EL11: 0.03 | EM11: 0.03 | EN11: 0.03 | EO11: 0.03 | EP11: 0.029 | EQ11: 0.029 | ER11: 0.029 | ES11: 0.029 | ET11: 0.029 | EU11: 0.029 | EV11: 0.029 | EW11: 0.029 | EX11: 0.029 | EY11: 0.029 | EZ11: ≥10,000 | FA11: 0.018 | FB11: 0.018 | FC11: ≥5,000 | FD11: 0.006 | FE11: 0.006 | FF11: ≥5千 | FG11: 促销 | FH11: 0.0045 | FI11: 0.0045 | FJ11: 0.006 | FK11: 0.0045 | FL11: 0.006 | FM11: 0.006 | FN11: 0.006 | FO11: 0.006 | FP11: 0.008 | FQ11: 0.01 | FR11: 0.01 | FS11: 0.01 | FT11: 0.01 | FU11: 0.014 | FV11: 0.014 | FW11: 0.016 | FX11: 0.016 | FY11: 0.0145 | FZ11: 0.029 | GA11: 0.029 | GB11: 0.029 | GC11: 0.029 | GD11: 0.029 | GE11: 0.029 | GF11: 0.029 | GG11: 0.0285 | GH11: 0.0285 | GI11: 0.0285 | GJ11: 0.0285 | GK11: 0.0285 | GL11: 0.0285 | GM11: 0.0285 | GN11: 0.0285 | GO11: 0.028 | GP11: 0.027 | GQ11: 0.026 | GR11: 0.023 | GS11: 0.023 | GT11: 0.021 | GU11: 0.021 | GV11: 0.019 | GW11: 0.018 | GX11: 0.0175 | GY11: 0.0165 | GZ11: 0.0165 | HA11: 0.0165 | HB11: 0.029 | HC11: 0.029 | HD11: 0.029 | HE11: 0.029 | HF11: =C11-D11 -> 0
B12: 1.15% (手机银行) | EZ12: ≥500
A13: SingFinance | B13: 1.05%(NewFund 10k) | C13: 0.0105 | D13: 0.0105 | E13: 0.0105 | F13: 0.012 | G13: 0.012 | H13: 0.012 | I13: 0.012 | J13: 0.012 | K13: 0.012 | L13: 0.012 | M13: 0.012 | N13: 0.012 | O13: 0.012 | P13: 0.013 | Q13: 0.013 | R13: 0.013 | S13: 0.013 | T13: 0.013 | U13: 0.013 | V13: 0.013 | W13: - | X13: 0.012 | Y13: 0.012 | Z13: 0.012 | AA13: 0.012 | AB13: 0.012 | AC13: 0.0125 | AD13: 0.0125 | AE13: 0.0145 | AF13: 0.015 | AG13: 0.0155 | AH13: 0.0155 | AI13: 0.0155 | AJ13: 0.0155 | AK13: 0.017 | AL13: 0.018 | AM13: 0.018 | AN13: 0.018 | AO13: 0.0185 | AP13: 0.02 | AQ13: 0.0205 | AR13: 0.0205 | AS13: 0.021 | AT13: 0.022 | AU13: 0.0225 | AV13: 0.0235 | AW13: 0.0235 | AX13: 0.024 | AY13: 0.024 | AZ13: 0.024 | BA13: 0.024 | BB13: 0.024 | BC13: 0.024 | BD13: 0.025 | BE13: 0.026 | BF13: 0.026 | BG13: 0.026 | BH13: 0.026 | BI13: 0.026 | BJ13: 0.026 | BK13: 0.026 | BL13: 2.6%↓ | BM13: 0.027 | BN13: 0.027 | BO13: 0.027 | BP13: 0.027 | BQ13: 0.027 | BR13: 0.027 | BS13: 0.027 | BT13: 0.027 | BU13: 0.027 | BV13: 0.027 | BW13: 0.027 | BX13: 0.027 | BY13: 0.027 | BZ13: 0.027 | CA13: 0.027 | CB13: 0.0285 | CC13: 0.0295 | CD13: 0.0295 | CE13: 0.0295 | CF13: 0.0295 | CG13: 0.0295 | CH13: 0.0295 | CI13: 0.0295 | CJ13: 0.0295 | CK13: 0.03 | CL13: 0.03 | CM13: 0.03 | CN13: 0.03 | CO13: 0.03 | CP13: 0.03 | CQ13: 0.03 | CR13: 0.03 | CS13: 0.03 | CT13: 0.029 | CU13: 0.029 | CV13: 0.029 | CW13: 0.029 | CX13: 0.029 | CY13: 0.029 | CZ13: 0.029 | DA13: 0.029 | DB13: 0.029 | DC13: 0.029 | DD13: 0.029 | DE13: 0.029 | DF13: 0.029 | DG13: 0.029 | DH13: 0.029 | DI13: 0.029 | DJ13: 0.029 | DK13: 0.029 | DL13: 0.029 | DM13: 0.029 | DN13: 0.029 | DO13: 0.029 | DP13: 0.029 | DQ13: 0.029 | DR13: 0.029 | DS13: 0.029 | DT13: 0.029 | DU13: 0.029 | DV13: 0.029 | DW13: 0.029 | DX13: 0.029 | DY13: 0.029 | DZ13: 0.03 | EA13: 0.03 | EB13: 0.03 | EC13: 0.03 | ED13: 0.03 | EE13: 0.03 | EF13: 0.03 | EG13: 0.03 | EH13: 0.03 | EI13: 0.03 | EJ13: 0.03 | EK13: 0.03 | EL13: 0.03 | EM13: 0.03 | EN13: 0.03 | EO13: 0.03 | EP13: 0.029 | EQ13: 0.029 | ER13: 0.029 | ES13: 0.029 | ET13: 0.029 | EU13: 0.029 | EV13: 0.029 | EW13: 0.029 | EX13: 0.029 | EY13: 0.029 | EZ13: ≥10,000 | FA13: 0.018 | FB13: 0.018 | FC13: ≥5,000 | FD13: 0.006 | FE13: 0.006 | FF13: ≥5千 | FG13: 促销 | FH13: 0.0045 | FI13: 0.0045 | FJ13: 0.006 | FK13: 0.0045 | FL13: 0.006 | FM13: 0.006 | FN13: 0.006 | FO13: 0.006 | FP13: 0.008 | FQ13: 0.01 | FR13: 0.01 | FS13: 0.01 | FT13: 0.01 | FU13: 0.014 | FV13: 0.014 | FW13: 0.016 | FX13: 0.016 | FY13: 0.0145 | FZ13: 0.029 | GA13: 0.029 | GB13: 0.029 | GC13: 0.029 | GD13: 0.029 | GE13: 0.029 | GF13: 0.029 | GG13: 0.0285 | GH13: 0.0285 | GI13: 0.0285 | GJ13: 0.0285 | GK13: 0.0285 | GL13: 0.0285 | GM13: 0.0285 | GN13: 0.0285 | GO13: 0.028 | GP13: 0.027 | GQ13: 0.026 | GR13: 0.023 | GS13: 0.023 | GT13: 0.021 | GU13: 0.021 | GV13: 0.019 | GW13: 0.018 | GX13: 0.0175 | GY13: 0.0165 | GZ13: 0.0165 | HA13: 0.0165 | HB13: 0.029 | HC13: 0.029 | HD13: 0.029 | HE13: 0.029 | HF13: =C13-D13 -> 0
B14: 1.0%(NewFund 1k) | EZ14: ≥500
A15: 3 Months
A16: 日期 | C16: =C3 -> 46099 | D16: =D3 -> 46092 | E16: =E3 -> 46085 | F16: =F3 -> 46078 | G16: =G3 -> 46071 | H16: =H3 -> 46064 | I16: =I3 -> 46057 | J16: =J3 -> 46050 | ... AF16: =AF3 -> 45896 | AG16: 45889 | AH16: 45882 | AI16: 45875 | AJ16: 45868 | AK16: 45861 | AL16: 45854 | AM16: 45847 | AN16: 45840 | AO16: =AO3 -> 45833 | AP16: 45826 | AQ16: =AQ3 -> 45819 | AR16: =AR3 -> 45812 | AS16: =AS3 -> 45805 | AT16: =AT3 -> 45798 | AU16: =AU3 -> 45792 | AV16: =AV3 -> 45785 | AW16: =AW3 -> 45777 | AX16: =AX3 -> 45771 | ... EH16: =EH3 -> 45148 | EI16: 45141 | EJ16: 45134 | EK16: 45127 | EL16: 45120 | EM16: 45113 | EN16: 45105 | EO16: 45099 | EP16: 45092 | EQ16: 45085 | ER16: 45076 | ES16: 45070 | ET16: 45063 | EU16: 45056 | EV16: 45049 | EW16: 45042 | EX16: 45035 | EY16: 45028 | FA16: 44803 | FD16: 44706 | FH16: 5月6日 | FI16: 44685 | FJ16: 44699 | FK16: 44690 | FL16: 44713 | FM16: 44720 | FN16: 44727 | FO16: 44733 | FP16: 44741 | FQ16: 44755 | FR16: 44748 | FS16: 44769 | FT16: 44762 | FU16: 44783 | FV16: 44776 | FW16: 44797 | FX16: 44790 | FY16: 44805 | FZ16: 45000 | GA16: 44993 | GB16: 44986 | GC16: 44979 | GD16: 44972 | GE16: 44965 | GF16: 44958 | GG16: 44951 | GH16: 44944 | GI16: 44937 | GJ16: 44930 | GK16: 44923 | GL16: 44916 | GM16: 44910 | GN16: 44902 | GO16: 44896 | GP16: 44888 | GQ16: 44881 | GR16: 44874 | GS16: 44868 | GT16: 44860 | GU16: 44853 | GV16: 44846 | GW16: 44839 | GX16: 44831 | GY16: 44825 | GZ16: 44818 | HA16: 44811 | HB16: 45002 | HC16: 45020 | HD16: 45014 | HE16: 45008
B17: 全部公开报价 | C17: 当日最高报价 | D17: 当日最高报价 | E17: 当日最高报价 | F17: 当日最高报价 | G17: 当日最高报价 | H17: 当日最高报价 | I17: 当日最高报价 | J17: 当日最高报价 | K17: 当日最高报价 | L17: 当日最高报价 | M17: 当日最高报价 | N17: 当日最高报价 | O17: 当日最高报价 | P17: 当日最高报价 | Q17: 当日最高报价 | R17: 当日最高报价 | S17: 当日最高报价 | T17: 当日最高报价 | U17: 当日最高报价 | V17: 当日最高报价 | W17: 当日最高报价 | X17: 当日最高报价 | Y17: 当日最高报价 | Z17: 当日最高报价 | AA17: 当日最高报价 | AB17: 当日最高报价 | AC17: 当日最高报价 | AD17: 当日最高报价 | AE17: 当日最高报价 | AF17: 当日最高报价 | AG17: 当日最高报价 | AH17: 当日最高报价 | AI17: 当日最高报价 | AJ17: 当日最高报价 | AK17: 当日最高报价 | AL17: 当日最高报价 | AM17: 当日最高报价 | AN17: 当日最高报价 | AO17: 当日最高报价 | AP17: 当日最高报价 | AQ17: 当日最高报价 | AR17: 当日最高报价 | AS17: 当日最高报价 | AT17: 当日最高报价 | AU17: 当日最高报价 | AV17: 当日最高报价 | AW17: 当日最高报价 | AX17: 当日最高报价 | AY17: 当日最高报价 | AZ17: 当日最高报价 | BA17: 当日最高报价 | BB17: 当日最高报价 | BC17: 当日最高报价 | BD17: 当日最高报价 | BE17: 当日最高报价 | BF17: 当日最高报价 | BG17: 当日最高报价 | BH17: 当日最高报价 | BI17: 当日最高报价 | BJ17: 当日最高报价 | BK17: 当日最高报价 | BL17: 当日最高报价 | BM17: 当日最高报价 | BN17: 当日最高报价 | BO17: 当日最高报价 | BP17: 当日最高报价 | BQ17: 当日最高报价 | BR17: 当日最高报价 | BS17: 当日最高报价 | BT17: 当日最高报价 | BU17: 当日最高报价 | BV17: 当日最高报价 | BW17: 当日最高报价 | BX17: 当日最高报价 | BY17: 当日最高报价 | BZ17: 当日最高报价 | CA17: 当日最高报价 | CB17: 当日最高报价 | CC17: 当日最高报价 | CD17: 当日最高报价 | CE17: 当日最高报价 | CF17: 当日最高报价 | CG17: 当日最高报价 | CH17: 当日最高报价 | CI17: 当日最高报价 | CJ17: 当日最高报价 | CK17: 当日最高报价 | CL17: 当日最高报价 | CM17: 当日最高报价 | CN17: 当日最高报价 | CO17: 当日最高报价 | CP17: 当日最高报价 | CQ17: 当日最高报价 | CR17: 当日最高报价 | CS17: 当日最高报价 | CT17: 当日最高报价 | CU17: 当日最高报价 | CV17: 当日最高报价 | CW17: 当日最高报价 | CX17: 当日最高报价 | CY17: 当日最高报价 | CZ17: 当日最高报价 | DA17: 当日最高报价 | DB17: 当日最高报价 | DC17: 当日最高报价 | DD17: 当日最高报价 | DE17: 当日最高报价 | DF17: 当日最高报价 | DG17: 当日最高报价 | DH17: 当日最高报价 | DI17: 当日最高报价 | DJ17: 当日最高报价 | DK17: 当日最高报价 | DL17: 当日最高报价 | DM17: 当日最高报价 | DN17: 当日最高报价 | DO17: 当日最高报价 | DP17: 当日最高报价 | DQ17: 当日最高报价 | DR17: 当日最高报价 | DS17: 当日最高报价 | DT17: 当日最高报价 | DU17: 当日最高报价 | DV17: 当日最高报价 | DW17: 当日最高报价 | DX17: 当日最高报价 | DY17: 当日最高报价 | DZ17: 当日最高报价 | EA17: 当日最高报价 | EB17: 当日最高报价 | EC17: 当日最高报价 | ED17: 当日最高报价 | EE17: 当日最高报价 | EF17: 当日最高报价 | EG17: 当日最高报价 | EH17: 当日最高报价 | EI17: 当日最高报价 | EJ17: 当日最高报价 | EK17: 当日最高报价 | EL17: 当日最高报价 | EM17: 当日最高报价 | EN17: 当日最高报价 | EO17: 当日最高报价 | EP17: 当日最高报价 | EQ17: 当日最高报价 | ER17: 当日最高报价 | ES17: 当日最高报价 | ET17: 当日最高报价 | EU17: 当日最高报价 | EV17: 当日最高报价 | EW17: 当日最高报价 | EX17: 当日最高报价 | EY17: 当日最高报价 | EZ17: 金额 | FA17: 当日最高报价 | FB17: 全部公开报价 | FC17: 金额 | FD17: 当日最高报价 | FE17: 全部公开报价 | FF17: 金额 | FG17: 挂牌利率/促销利率 | FH17: 当日最高报价 | FI17: 当日最高报价 | FJ17: 当日最高报价 | FK17: 当日最高报价 | FL17: 当日最高报价 | FM17: 当日最高报价 | FN17: 当日最高报价 | FO17: 当日最高报价 | FP17: 当日最高报价 | FQ17: 当日最高报价 | FR17: 当日最高报价 | FS17: 当日最高报价 | FT17: 当日最高报价 | FU17: 当日最高报价 | FV17: 当日最高报价 | FW17: 当日最高报价 | FX17: 当日最高报价 | FY17: 当日最高报价 | FZ17: 当日最高报价 | GA17: 当日最高报价 | GB17: 当日最高报价 | GC17: 当日最高报价 | GD17: 当日最高报价 | GE17: 当日最高报价 | GF17: 当日最高报价 | GG17: 当日最高报价 | GH17: 当日最高报价 | GI17: 当日最高报价 | GJ17: 当日最高报价 | GK17: 当日最高报价 | GL17: 当日最高报价 | GM17: 当日最高报价 | GN17: 当日最高报价 | GO17: 当日最高报价 | GP17: 当日最高报价 | GQ17: 当日最高报价 | GR17: 当日最高报价 | GS17: 当日最高报价 | GT17: 当日最高报价 | GU17: 当日最高报价 | GV17: 当日最高报价 | GW17: 当日最高报价 | GX17: 当日最高报价 | GY17: 当日最高报价 | GZ17: 当日最高报价 | HA17: 当日最高报价 | HB17: 当日最高报价 | HC17: 当日最高报价 | HD17: 当日最高报价 | HE17: 当日最高报价 | HF17: 当日最高报价变动
A18: CIMB | B18: 1.25% 手机银行 （个人） | C18: 0.0125 | D18: 0.0125 | E18: 0.0125 | F18: 0.013 | G18: 0.013 | H18: 0.013 | I18: 0.013 | J18: 0.013 | K18: 0.013 | L18: 0.013 | M18: 0.013 | N18: 0.013 | O18: 0.013 | P18: 0.013 | Q18: 0.013 | R18: 0.013 | S18: 0.0125 | T18: 0.0125 | U18: 0.0125 | V18: 0.0125 | W18: 0.013 | X18: 0.013 | Y18: 0.013 | Z18: 0.013 | AA18: 0.013 | AB18: 0.013 | AC18: 0.013 | AD18: 0.013 | AE18: 0.014 | AF18: 0.015 | AG18: 0.016 | AH18: 0.016 | AI18: 0.016 | AJ18: 0.017 | AK18: 0.017 | AL18: 0.017 | AM18: 0.0175 | AN18: 0.0185 | AO18: 0.02 | AP18: 0.021 | AQ18: 0.022 | AR18: 0.022 | AS18: 0.0225 | AT18: 0.0225 | AU18: 0.022 | AV18: 0.023 | AW18: 0.0235 | AX18: 0.0235 | AY18: 0.0235 | AZ18: 0.0235 | BA18: 0.0235 | BB18: 0.0245 | BC18: 0.0245 | BD18: 0.0245 | BE18: 0.026 | BF18: 0.0275 | BG18: 0.0275 | BH18: 0.0275 | BI18: 0.0275 | BJ18: 0.027 | BK18: 0.027 | BL18: 0.027 | BM18: 0.027 | BN18: 0.027 | BO18: 0.028 | BP18: 0.028 | BQ18: 0.028 | BR18: 0.028 | BS18: 0.028 | BT18: 0.028 | BU18: 0.028 | BV18: 0.028 | BW18: 0.028 | BX18: 0.028 | BY18: 0.028 | BZ18: 0.028 | CA18: 0.028 | CB18: 0.028 | CC18: 0.03 | CD18: 0.03 | CE18: 0.03 | CF18: 0.031 | CG18: 0.031 | CH18: 0.032 | CI18: 0.032 | CJ18: 0.032 | CK18: 0.033 | CL18: 0.033 | CM18: 0.033 | CN18: 0.033 | CO18: 0.033 | CP18: 0.033 | CQ18: 0.033 | CR18: 0.033 | CS18: 0.033 | CT18: 0.033 | CU18: 0.033 | CV18: 0.033 | CW18: 0.033 | CX18: 0.033 | CY18: 0.033 | CZ18: 0.033 | DA18: 0.0335 | DB18: 0.0335 | DC18: 0.0335 | DD18: 0.0335 | DE18: 0.035 | DF18: 0.035 | DG18: 0.035 | DH18: 0.035 | DI18: 0.035 | DJ18: 0.035 | DK18: 0.035 | DL18: 0.035 | DM18: 0.035 | DN18: 0.035 | DO18: 0.035 | DP18: 0.035 | DQ18: 0.035 | DR18: - | EZ18: ≥10,000 | HF18: =C18-D18 -> 0 | HG18: 10k
B19: 1.30% 手机银行 （财富）
A20: HLF | B20: >60,000 | C20: - | D20: - | E20: - | F20: - | G20: - | H20: - | I20: - | J20: - | K20: - | L20: - | M20: 0.013 | N20: 0.013 | O20: 0.013 | P20: 0.013 | Q20: 0.013 | S20: - | T20: - | U20: - | V20: - | W20: - | X20: - | Y20: - | Z20: - | AA20: - | AB20: - | AC20: - | AD20: - | AE20: - | AF20: - | AG20: - | AH20: - | AI20: - | AJ20: - | AK20: - | AL20: - | AM20: - | AN20: - | AO20: - | AP20: - | AQ20: - | AR20: - | AS20: - | AT20: - | AU20: - | AV20: - | AW20: - | AX20: - | AY20: - | AZ20: - | BA20: - | BB20: - | BC20: - | BD20: - | BE20: - | BF20: - | BG20: - | BH20: - | BI20: - | BJ20: - | BK20: - | BL20: - | BM20: - | BN20: - | BO20: - | BP20: - | BQ20: - | BR20: - | BS20: - | BT20: - | BU20: - | BV20: - | BW20: - | BX20: - | BY20: - | BZ20: - | CA20: - | CB20: - | CC20: - | CD20: - | CE20: - | CF20: - | CG20: - | CH20: - | CI20: - | CJ20: - | CK20: - | CL20: - | CM20: - | CN20: 0.029 | CO20: 0.029 | CP20: 0.029 | CQ20: 0.029 | CR20: 0.029 | CS20: 0.029 | CT20: 0.029 | CU20: 0.029 | CV20: 0.029 | CW20: 0.029 | CX20: 0.0295 | CY20: 0.0295 | CZ20: 0.0295 | DA20: 0.0305 | DB20: 0.0305 | DC20: - | DD20: - | DE20: - | DF20: - | DG20: - | DH20: - | DI20: - | DJ20: - | DK20: - | DL20: - | DM20: - | DN20: - | DO20: - | DP20: - | DQ20: - | DR20: - | DS20: 0.0358 | DT20: 0.0358 | DU20: 0.0358 | DV20: 0.0358 | DW20: 0.0338 | DX20: 0.0338 | DY20: - | DZ20: - | EA20: - | EB20: 3.00%（5-month） | EC20: 3.00%（5-month） | ED20: 3.00%（5-month） | EE20: - | EF20: - | EG20: - | EH20: - | EI20: - | EJ20: - | EK20: - | EL20: - | EM20: 0.0338 | EN20: 0.0338 | EO20: 0.0338 | EP20: 0.0338 | EQ20: 0.0338 | ER20: 0.031 | ES20: 0.031 | ET20: 0.031 | EU20: 0.031 | EZ20: 20,000-50,000 | HF20: =C20-D20 -> #VALUE!
B21: - | EZ21: >= 50,000
A22: CITI | B22: 1.25% (Citigold Client) 1.45% (Citigold Private Client) 1.50% (Citigold Private Client and Citigold 新客户) | C22: 0.0125 | D22: 0.0125 | E22: 0.0125 | F22: 0.013 | G22: 0.013 | H22: 0.013 | I22: - | J22: - | K22: - | L22: - | M22: - | N22: - | O22: - | P22: - | Q22: - | R22: - | S22: - | T22: - | U22: - | V22: - | W22: - | X22: - | Y22: - | Z22: - | AA22: - | AB22: 0.0125 | AC22: 0.0125 | AD22: 0.0125 | AE22: 0.0125 | AF22: 0.014 | AG22: 0.014 | AH22: 0.014 | AI22: 0.014 | AJ22: 0.018 | AK22: 0.018 | AL22: 0.018 | AM22: 0.018 | AN22: 0.018 | AO22: 0.021 | AP22: 0.021 | AQ22: 0.021 | AR22: 0.021 | AS22: 0.02 | AT22: 0.02 | AU22: 0.02 | AV22: 0.02 | AW22: 0.02 | AX22: 0.022 | AY22: 0.022 | AZ22: 0.022 | BA22: 0.022 | BB22: 0.024 | BC22: 0.024 | BD22: 0.024 | BE22: 0.024 | BF22: 0.025 | BG22: 0.025 | BH22: 0.025 | BI22: 0.025 | BJ22: 0.024 | BK22: 0.024 | BL22: 0.024 | BM22: 0.024 | BN22: 0.024 | BO22: 0.024 | BP22: 0.024 | BQ22: 0.024 | BR22: 0.024 | BS22: 0.024 | BT22: 0.024 | BU22: 0.024 | BV22: 0.024 | BW22: 0.0245 | BX22: 0.0245 | BY22: 0.0245 | BZ22: 0.0245 | CA22: 0.0245 | CB22: 0.0255 | CC22: 0.0255 | CD22: 0.0255 | CE22: 0.0255 | CF22: 0.0265 | CG22: 0.0265 | CH22: 0.0265 | CI22: 0.0265 | CJ22: 0.0265 | CK22: 0.025 | CL22: 0.025 | CM22: 0.025 | CN22: 0.025 | CO22: 0.025 | CP22: 0.025 | CQ22: 0.025 | CR22: 0.025 | CS22: 0.025 | CT22: 0.025 | CU22: 0.025 | CV22: 0.025 | CW22: 0.031 | CX22: 0.033 | CY22: 0.033 | CZ22: 0.033 | DA22: 0.033 | DB22: 0.033 | DC22: 0.034 | DD22: 0.034 | DE22: 0.034 | DF22: 0.034 | DG22: 0.035 | DH22: 0.035 | DI22: 0.035 | DJ22: 0.035 | DK22: 0.035 | DL22: 0.035 | DM22: 0.035 | DN22: 0.035 | DO22: 0.035 | DP22: 0.035 | DQ22: 3.7%(citi private) | DR22: 3.7%(citi private) | DS22: 3.7%(citi private) | DT22: 3.7%(citi private) | DU22: 3.7%(citi private) | DV22: 3.7%(citi private) | DW22: 3.2%（Citi priority/citibanking/citi plus） | DX22: 3.5%(citi private) | DY22: 3.5%(citi private) | DZ22: 3.5%(citi private) | EA22: 0.034 | EB22: 0.034 | EC22: 0.034 | ED22: 0.034 | EE22: 0.034 | EF22: 0.034 | EG22: 0.034 | EH22: 0.034 | EI22: 0.034 | EJ22: 0.0368 | EK22: 0.0368 | EL22: 0.0368 | EM22: 0.0368 | EN22: 0.0388 | EO22: 0.0388 | EP22: 0.0388 | EQ22: 0.0388 | ER22: 0.04 | EZ22: 50,000-3,000,000 | HF22: =C22-D22 -> 0 | HG22: Fresh Fund 10k Fresh Fund 350k-10mil
A23: RHB | B23: 1.20% (personal） | C23: 0.012 | D23: 0.012 | E23: 0.012 | F23: 0.012 | G23: 0.012 | H23: 0.012 | I23: 0.0145 | J23: 0.0145 | K23: 0.0145 | L23: 0.0145 | M23: 0.0145 | N23: 0.0145 | O23: 0.0145 | P23: 0.013 | Q23: 0.013 | R23: 0.0115 | S23: 0.0115 | T23: 0.0125 | U23: 0.0125 | V23: 0.0125 | W23: 0.014 | X23: 0.014 | Y23: 0.014 | Z23: 0.014 | AA23: 0.014 | AB23: 0.014 | AC23: 0.014 | AD23: 0.014 | AE23: 0.014 | AF23: 0.014 | AG23: 0.014 | AH23: 0.014 | AI23: 0.015 | AJ23: 0.017 | AK23: 0.017 | AL23: 0.017 | AM23: 0.018 | AN23: 0.018 | AO23: 0.022 | AP23: 0.022 | AQ23: 0.022 | AR23: 0.021 | AS23: 0.021 | AT23: 0.021 | AU23: 0.021 | AV23: 0.021 | AW23: 0.023 | AX23: 0.023 | AY23: 0.023 | AZ23: 0.023 | BA23: 0.023 | BB23: 0.025 | BC23: 0.025 | BD23: 0.025 | BE23: 0.028 | BF23: 0.028 | BG23: 0.028 | BH23: 0.0268 | BI23: 0.0268 | BJ23: 0.0268 | BK23: 0.0268 | BL23: 0.0268 | BM23: 0.03 | BN23: 0.03 | BO23: 0.03 | BP23: 0.03 | BQ23: 0.03 | BR23: 0.03 | BS23: 0.029 | BT23: 0.029 | BU23: 0.0285 | BV23: 0.0285 | BW23: 0.0285 | BX23: 0.0285 | BY23: 0.0285 | BZ23: 0.0275 | CA23: 0.0275 | CB23: 0.0275 | CC23: 0.03 | CD23: 0.03 | CE23: 0.0315 | CF23: 0.0315 | CG23: 0.033 | CH23: 0.033 | CI23: 0.034 | CJ23: 0.034 | CK23: 0.034 | CL23: 0.034 | CM23: 0.034 | CN23: 0.033 | CO23: 0.033 | CP23: 0.033 | CQ23: 0.033 | CR23: 0.033 | CS23: 0.033 | CT23: 0.033 | CU23: 0.033 | CV23: 0.033 | CW23: 0.033 | CX23: 0.031 | CY23: 0.031 | CZ23: 0.031 | DA23: 0.031 | DB23: 0.031 | DC23: 0.031 | DD23: 0.031 | DE23: 0.031 | DF23: 0.031 | DG23: 0.031 | DH23: 0.031 | DI23: 0.031 | DJ23: 0.031 | DK23: 0.031 | DL23: 0.031 | DM23: 0.031 | DN23: 0.031 | DO23: 0.031 | DP23: 0.031 | DQ23: 0.031 | DR23: 0.031 | DS23: 0.031 | DT23: 0.031 | DU23: 0.031 | DV23: 0.031 | DW23: 0.031 | DX23: 0.031 | DY23: 0.031 | DZ23: 0.031 | EA23: 0.031 | EB23: 0.031 | EC23: 0.031 | ED23: 0.031 | EE23: 0.031 | EF23: 0.031 | EG23: 0.031 | EH23: 0.031 | EI23: 0.031 | EJ23: 0.031 | EK23: 0.031 | EL23: 0.031 | EM23: 0.031 | EN23: 0.031 | EO23: 0.031 | EP23: 0.031 | EQ23: 0.031 | ER23: 0.031 | ES23: 0.031 | ET23: 0.031 | EU23: 0.031 | EV23: 0.031 | EW23: 0.034 | EX23: 0.034 | EY23: 0.034 | EZ23: ≥20,000 | FZ23: 0.034 | GA23: 0.034 | GB23: 0.034 | GC23: 0.034 | GD23: 0.0338 | GE23: 0.0338 | GF23: 0.0338 | GG23: 0.0338 | GH23: 0.0338 | GI23: 0.0338 | GJ23: 0.032 | HB23: 0.034 | HC23: 0.034 | HD23: 0.034 | HE23: 0.034 | HF23: =C23-D23 -> 0
B24: 1.30% (premier） | GK24: 0.032 | GL24: 0.032 | GM24: 0.032 | GN24: 0.032 | GO24: 0.032 | GP24: 0.032 | GQ24: 0.032 | GR24: 0.03 | GS24: 0.03 | GT24: 0.03 | GU24: 0.03 | GV24: 0.03 | GW24: - | HG24: 20k | HH24: from 19 Jan 2026
A25: ICBC | B25: 1.15%（online） | C25: 0.0135 | D25: 0.0135 | E25: 0.0135 | F25: 0.0135 | G25: 0.0135 | H25: 0.0135 | I25: 0.0135 | J25: 0.0135 | K25: 0.0135 | L25: 0.0135 | M25: 0.014 | N25: 0.014 | O25: 0.014 | P25: 0.014 | Q25: 0.014 | R25: 0.014 | S25: 0.0125 | T25: 0.0125 | U25: 0.0125 | V25: 0.0125 | W25: 0.0125 | X25: 0.0125 | Y25: 0.0125 | Z25: 0.0125 | AA25: 0.0125 | AB25: 0.0125 | AC25: 0.0125 | AD25: 0.0135 | AE25: 0.0135 | AF25: 0.0145 | AG25: 0.0145 | AH25: 0.015 | AI25: 0.016 | AJ25: 0.016 | AK25: 0.017 | AL25: 0.017 | AM25: 0.0185 | AN25: 0.0185 | AO25: 0.0185 | AP25: 0.0185 | AQ25: 0.0205 | AR25: 0.022 | AS25: 0.022 | AT25: 0.022 | AU25: 2.3%（电子银行） | AV25: 2.3%（电子银行） | AW25: 2.3%（电子银行） | AX25: 2.3%（电子银行） | AY25: 2.3%（电子银行） | AZ25: 2.45%电子/2.45%柜台 | BA25: 2.45%电子/2.45%柜台 | BB25: =#REF! -> #REF! | BC25: =#REF! -> #REF! | BD25: 0.0275 | BE25: 0.0275 | BF25: 0.0275 | BG25: 0.0275 | BH25: 0.029 | BI25: =#REF! -> #REF! | BJ25: =#REF! -> #REF! | BK25: =#REF! -> #REF! | BL25: =#REF! -> #REF! | BM25: =#REF! -> #REF! | BN25: =#REF! -> #REF! | BO25: =#REF! -> #REF! | BP25: =#REF! -> #REF! | ... BV25: =#REF! -> #REF! | BW25: 3.00%电子/3.00%柜台 | BX25: 2.75%电子/2.75%柜台 | BY25: =#REF! -> #REF! | BZ25: 2.75%电子/2.75%柜台 | CA25: =#REF! -> #REF! | CB25: 2.80%电子/2.80%柜台 | CC25: 3.05%（电子银行） | CD25: 3.2%新客户） 3.20%（电子银行） | CE25: 3.3%新客户） 3.25%（电子银行） | CF25: 0.0335 | CG25: 0.0335 | CH25: 0.0345 | CI25: 0.035 | CJ25: 0.035 | CK25: 0.035 | CL25: 0.035 | CM25: 0.035 | CN25: 0.035 | CO25: 0.035 | CP25: 0.035 | CQ25: 0.035 | CR25: 0.035 | CS25: 0.034 | CT25: 0.0335 | CU25: 0.0335 | CV25: 0.0335 | CW25: 0.0335 | CX25: 0.0335 | CY25: 0.0335 | CZ25: 0.0335 | DA25: 0.0335 | DB25: 0.0335 | DC25: 0.0335 | DD25: 0.0335 | DE25: 0.0335 | DF25: 0.0335 | DG25: 0.0335 | DH25: 0.0335 | DI25: 0.0335 | DJ25: 0.0335 | DK25: 0.0335 | DL25: 0.0335 | DM25: 0.0335 | DN25: 0.0335 | DO25: 0.0335 | DP25: 0.0335 | DQ25: 0.0335 | DR25: 0.0335 | DS25: 0.0335 | DT25: 0.0335 | DU25: 0.0335 | DV25: 0.0335 | DW25: 0.0335 | DX25: 0.0335 | DY25: 0.033 | DZ25: 0.033 | EA25: 0.033 | EB25: 0.033 | EC25: 0.033 | ED25: 0.033 | EE25: 0.033 | EF25: 0.033 | EG25: 0.033 | EH25: 0.033 | EI25: 0.033 | EJ25: 0.033 | EK25: 0.035 | EL25: 0.035 | EM25: 0.035 | EN25: 0.035 | EO25: 0.035 | EP25: 0.035 | EQ25: 0.0355 | ER25: 0.0355 | ES25: 0.0355 | ET25: 0.036 | EU25: 0.0365 | EV25: 0.0365 | EW25: 0.0365 | EX25: 0.0375 | EY25: 0.0375 | EZ25: ≥20,000 | FA25: 0.006 | FB25: 0.55% 柜面 | FC25: ≥500 | FD25: 0.006 | FE25: 0.55% 柜面 | FF25: ≥500 | FG25: 促销 | FH25: 0.0045 | FI25: 0.0045 | FJ25: 0.0045 | FK25: 0.0045 | FL25: 0.006 | FM25: 0.006 | FN25: 0.006 | FO25: 0.006 | FP25: 0.006 | FQ25: 0.006 | FR25: 0.006 | FS25: 0.006 | FT25: 0.006 | FU25: 0.006 | FV25: 0.006 | FW25: 0.006 | FX25: 0.006 | FY25: 0.016 | FZ25: 0.0375 | GA25: 0.0375 | GB25: 0.0375 | GC25: 0.039 | GD25: 0.039 | GE25: 0.039 | GF25: 0.039 | GG25: 0.039 | GH25: 0.03 | GI25: 0.03 | GJ25: 0.03 | GK25: 0.03 | GL25: 0.03 | GM25: 0.03 | GN25: 0.03 | GO25: 0.03 | GP25: 0.03 | GQ25: 0.03 | GR25: 0.03 | GS25: 0.0235 | GT25: 0.0235 | GU25: 0.0235 | GV25: 0.02 | GW25: 0.02 | GX25: 0.02 | GY25: 0.016 | GZ25: 0.016 | HA25: 0.016 | HB25: 0.0375 | HC25: 0.0375 | HD25: 0.0375 | HE25: 0.0375 | HF25: =C25-D25 -> 0 | HG25: 500-200k
B26: 1.35%（online）>200k | HG26: >200k
A27: BEA | B27: 1.40% fresh fund | C27: 0.0135 | D27: 0.0135 | E27: 0.0135 | F27: 0.014 | G27: 0.014 | H27: 0.014 | I27: 0.014 | J27: 0.014 | K27: 0.014 | L27: 0.014 | M27: 0.014 | N27: 0.014 | O27: 0.014 | P27: 0.014 | Q27: 0.014 | R27: 0.014 | S27: 0.014 | T27: 0.014 | U27: 0.014 | V27: 0.014 | W27: 0.014 | X27: 0.014 | Y27: 0.014 | Z27: 0.014 | AA27: 0.014 | AB27: 0.014 | AC27: 0.0145 | AD27: 0.0145 | AE27: 0.016 | AF27: 0.016 | AG27: 0.017 | AH27: 0.017 | AI27: 0.018 | AJ27: 0.018 | AK27: 0.018 | AL27: 0.02 | AM27: 0.02 | AN27: 0.021 | AO27: 0.022 | AP27: 0.022 | AQ27: 0.022 | AR27: 0.022 | AS27: 0.0235 | AT27: 0.025 | AU27: 0.025 | AV27: 0.025 | AW27: 0.025 | AX27: 0.025 | AY27: 0.025 | AZ27: 0.025 | BA27: 0.0265 | BB27: 0.0265 | BC27: 0.0265 | BD27: 0.0265 | BE27: 0.0275 | BF27: 0.0275 | BG27: 0.0275 | BH27: 0.029 | BI27: 0.029 | BJ27: 0.029 | BK27: 0.029 | BL27: 0.029 | BM27: 0.03 | BN27: 0.03 | BO27: 0.03 | BP27: 0.03 | BQ27: 0.03 | BR27: 0.029 | BS27: 0.029 | BT27: 0.029 | BU27: 0.029 | BV27: 0.029 | BW27: 0.029 | BX27: 0.029 | BY27: 0.029 | BZ27: 0.031 | CA27: 0.031 | CB27: 0.0295 | CC27: 0.03 | CD27: 0.0325 | CE27: 0.0325 | CF27: 0.0345 | CG27: 0.0345 | CH27: 0.0345 | CI27: 0.035 | CJ27: 0.035 | CK27: 0.034 | CL27: 0.034 | CM27: 0.034 | CN27: 0.034 | CO27: 0.034 | CP27: 0.034 | CQ27: 0.034 | CR27: 0.034 | CS27: 0.034 | CT27: 0.034 | CU27: 0.034 | CV27: 0.034 | CW27: 0.034 | CX27: 0.034 | CY27: 0.034 | CZ27: 0.034 | DA27: 0.034 | DB27: 0.034 | DC27: 0.034 | DD27: 0.034 | DE27: 0.034 | DF27: - | DG27: - | DH27: - | DI27: - | DJ27: - | DK27: - | DL27: - | DM27: - | DN27: - | DO27: - | DP27: - | DQ27: - | DR27: - | DS27: - | DT27: - | DU27: - | DV27: - | DW27: - | DX27: - | DY27: 0.034 | DZ27: 0.034 | EA27: 0.034 | EB27: 0.034 | EC27: 0.034 | ED27: 0.034 | EE27: 0.034 | EF27: 0.034 | EG27: 0.034 | EH27: 0.034 | EI27: 0.034 | EJ27: 0.034 | EK27: 0.034 | EL27: 0.034 | EM27: 0.034 | EN27: 0.034 | EO27: 0.034 | EP27: 0.034 | EQ27: 0.034 | ER27: 0.034 | ES27: 0.034 | ET27: 0.034 | EU27: 0.034 | EV27: 0.034 | EW27: 0.034 | EX27: 0.034 | EY27: 0.034 | EZ27: 100,000-2,000,000 | FZ27: 0.019 | GA27: 0.019 | GB27: 0.019 | GC27: 0.019 | GD27: 0.019 | GE27: 0.019 | GF27: 0.019 | GG27: 0.019 | GH27: 0.019 | GI27: 0.019 | GJ27: 0.019 | GK27: 0.019 | GL27: 0.019 | GM27: 0.019 | GN27: 0.019 | GO27: 0.019 | GP27: 0.019 | GQ27: 0.019 | GR27: 0.019 | GS27: 0.019 | GT27: 0.019 | GU27: 0.019 | GV27: 0.019 | GW27: 0.019 | GX27: 0.019 | HB27: 0.019 | HC27: 0.034 | HD27: 0.034 | HE27: 0.034 | HF27: =C27-D27 -> 0 | HG27: 100k-5mil
A28: HSBC | B28: 0.70% personal (counter) 0.75% premier w/o wealth products (counter) 1.35% premier w wealth holdings or FX Engaged (Mobile App only+$30K fresh funds) 1.40% (mobile banking, fresh fund S$30K) | C28: 0.014 | D28: 0.014 | E28: 0.007 | F28: 0.008 | G28: 0.008 | H28: 0.008 | I28: 0.008 | J28: 0.008 | K28: 0.008 | L28: 0.008 | M28: 0.008 | N28: 0.008 | O28: 0.017 | P28: 0.017 | Q28: 0.016 | R28: 0.016 | S28: 0.016 | T28: 0.016 | U28: 0.016 | V28: 0.008 | W28: 0.008 | X28: 0.008 | Y28: 0.008 | Z28: 0.008 | AA28: 0.008 | AB28: 0.008 | AC28: 0.008 | AD28: 0.008 | AE28: 0.0095 | AF28: 0.0105 | AG28: 0.0105 | AH28: 0.0115 | AI28: 0.0115 | AJ28: 0.0115 | AK28: 0.0085 | AL28: 0.0085 | AM28: 0.0085 | AN28: 0.0105 | AO28: 0.012 | AP28: 0.012 | AQ28: 0.014 | AR28: 0.014 | AS28: 0.0155 | AT28: 0.02 | AU28: 0.0155 | AV28: 0.016 | AW28: 0.016 | AX28: 0.016 | AY28: 0.019 | AZ28: 0.019 | BA28: 0.019 | BB28: 0.022 | BC28: 0.022 | BD28: 0.022 | BE28: 0.024 | BF28: 0.024 | BG28: 0.024 | BH28: 0.024 | BI28: 0.024 | BJ28: 0.0258 | BK28: 0.0258 | BL28: 0.0258 | BM28: 2.58%↓ | BN28: 0.0265 | BO28: 0.0265 | BP28: 0.0265 | BQ28: 0.0265 | BR28: 0.0265 | BS28: 0.0275 | BT28: 0.0275 | BU28: 0.0275 | BV28: 0.0275 | BW28: 0.0275 | BX28: 0.0275 | BY28: 2.9%（4M) | BZ28: 2.9%（4M) | CA28: 2.9%（4M) | CB28: 3.3%（4M) | CC28: 3.3%（4M) | CD28: 3.1%（4M) | CE28: 3.1%（4M) | CF28: - | EZ28: 30,000-100,000 | HF28: =C28-D28 -> 0
A29: BOC | B29: 1.15% (counter) | C29: 0.013 | D29: 0.013 | E29: 0.013 | F29: 0.013 | G29: 0.013 | H29: 0.0135 | I29: 0.0135 | J29: 0.0135 | K29: 0.0135 | L29: 0.014 | M29: 0.014 | N29: 0.014 | O29: 0.014 | P29: 0.014 | Q29: 0.014 | R29: 0.014 | S29: 0.014 | T29: 0.014 | U29: 0.014 | V29: 0.014 | W29: 0.014 | X29: 0.014 | Y29: 0.013 | Z29: 0.013 | AA29: 0.013 | AB29: 0.013 | AC29: 0.0135 | AD29: 0.0135 | AE29: 0.0145 | AF29: 0.0155 | AG29: 0.0165 | AH29: 0.017 | AI29: 0.017 | AJ29: 0.017 | AK29: 0.018 | AL29: 0.0182 | AM29: 0.0186 | AN29: 0.0195 | AO29: 0.02 | AP29: 0.02 | AQ29: 0.021 | AR29: 0.021 | AS29: 0.0215 | AT29: 0.0225 | AU29: 0.023 | AV29: 0.0235 | AW29: 0.024 | AX29: 0.0245 | AY29: 0.025 | AZ29: 0.025 | BA29: 0.025 | BB29: 0.025 | BC29: 0.025 | BD29: 0.0265 | BE29: 0.0275 | BF29: 0.0275 | BG29: 0.0275 | BH29: 0.028 | BI29: 0.028 | BJ29: 0.028 | BK29: 0.029 | BL29: 2.95%↓ | BM29: 0.03 | BN29: 0.03 | BO29: 0.03 | BP29: 0.03 | BQ29: 0.03 | BR29: 0.03 | BS29: 0.03 | BT29: 0.03 | BU29: 0.03 | BV29: 0.0305 | BW29: 0.0305 | BX29: 0.0305 | BY29: 0.031 | BZ29: 0.03 | CA29: 0.029 | CB29: 0.0305 | CC29: 0.0315 | CD29: 0.0315 | CE29: 0.032 | CF29: 0.0335 | CG29: 0.0335 | CH29: 0.0335 | CI29: 0.034 | CJ29: 0.0345 | CK29: 0.035 | CL29: 0.035 | CM29: 0.035 | CN29: 0.035 | CO29: 0.035 | CP29: 0.035 | CQ29: 0.035 | CR29: 0.034 | CS29: 0.034 | CT29: 0.033 | CU29: 0.033 | CV29: 0.033 | CW29: 0.0335 | CX29: 0.0335 | CY29: 0.0335 | CZ29: 0.0335 | DA29: 0.0335 | DB29: 0.034 | DC29: 0.034 | DD29: 0.034 | DE29: 0.034 | DF29: 0.034 | DG29: 0.0345 | DH29: 0.0345 | DI29: 0.0345 | DJ29: 0.0345 | DK29: 0.035 | DL29: 0.036 | DM29: 0.036 | DN29: 0.036 | DO29: 0.036 | DP29: 0.036 | DQ29: 0.036 | DR29: 0.0355 | DS29: 0.035 | DT29: 0.0345 | DU29: 0.0345 | DV29: 0.0335 | DW29: 0.0335 | DX29: 0.0335 | DY29: 0.0335 | DZ29: 0.034 | EA29: 0.034 | EB29: 0.034 | EC29: 0.0345 | ED29: 0.035 | EE29: 0.035 | EF29: 0.035 | EG29: 0.035 | EH29: 0.035 | EI29: 0.035 | EJ29: 0.035 | EK29: 0.035 | EL29: 0.035 | EM29: 0.035 | EN29: 0.035 | EO29: 0.035 | EP29: 0.035 | EQ29: 0.035 | ER29: 0.035 | ES29: 0.035 | ET29: 0.0355 | EU29: 0.0355 | EV29: 0.036 | EW29: 0.036 | EX29: 0.0365 | EY29: 0.037 | EZ29: ≥10,000 | FY29: 0.018 | FZ29: 0.0375 | GA29: 0.0375 | GB29: 0.0375 | GC29: 0.0375 | GD29: 0.038 | GE29: 0.038 | GF29: 0.039 | GG29: 0.038 | GH29: 0.038 | GI29: 0.038 | GJ29: 0.037 | GK29: 0.037 | GL29: 0.037 | GM29: 0.037 | GN29: 0.037 | GO29: 0.0365 | GP29: 0.036 | GQ29: 0.032 | GR29: 0.03 | GS29: 0.03 | GT29: 0.027 | GU29: 0.027 | GV29: 0.023 | GW29: 0.0215 | GX29: 0.021 | GY29: 0.02 | GZ29: 0.02 | HA29: 0.02 | HB29: 0.0375 | HC29: 0.037 | HD29: 0.0375 | HE29: 0.0375 | HF29: =C29-D29 -> 0
B30: 1.30% (手机银行) | EZ30: ≥500 | FA30: 0.018 | FB30: 0.018 | FC30: ≥5,000 | FD30: 0.006 | FE30: 0.006 | FF30: ≥5千 | FG30: 促销 | FH30: 0.0045 | FI30: 0.0045 | FJ30: 0.006 | FK30: 0.0045 | FL30: 0.006 | FM30: 0.006 | FN30: 0.006 | FO30: 0.006 | FP30: 0.008 | FQ30: 0.01 | FR30: 0.01 | FS30: 0.01 | FT30: 0.01 | FU30: 0.014 | FV30: 0.014 | FW30: 0.016 | FX30: 0.016
A31: SingFinance | B31: 1.25%(NewFund 10k) | C31: 0.0125 | D31: 0.0125 | E31: 0.0125 | F31: 0.013 | G31: 0.013 | H31: 0.013 | I31: 0.013 | J31: 0.013 | K31: 0.013 | L31: 0.013 | M31: 0.013 | N31: 0.013 | O31: 0.013 | P31: 0.014 | Q31: 0.014 | R31: 0.014 | S31: 0.014 | T31: 0.013 | U31: 0.012 | V31: 0.012 | W31: 0.012 | X31: 0.012 | Y31: 0.012 | Z31: 0.012 | AA31: 0.012 | AB31: 0.012 | AC31: 0.012 | AD31: 0.014 | AE31: 0.014 | AF31: 0.015 | AG31: 0.0155 | AH31: 0.016 | AI31: 0.016 | AJ31: 0.0165 | AK31: 0.0165 | AL31: 0.0165 | AM31: 0.0175 | AN31: 0.0175 | AO31: 0.0185 | AP31: 0.0195 | AQ31: 0.0205 | AR31: 0.0205 | AS31: 0.0205 | AT31: 0.0205 | AU31: 0.0205 | AV31: 0.0205 | AW31: 0.0205 | AX31: 0.022 | AY31: 0.023 | AZ31: 0.023 | BA31: 0.0245 | BB31: 0.0245 | BC31: 0.0255 | BD31: 0.0255 | BE31: 0.0265 | BF31: 0.0265 | BG31: 0.0265 | BH31: 0.027 | BI31: 0.027 | BJ31: 0.027 | BK31: 0.027 | BL31: 0.027 | BM31: 0.027 | BN31: 0.027 | BO31: 0.027 | BP31: 0.027 | BQ31: 0.027 | BR31: 0.027 | BS31: 0.027 | BT31: 0.027 | BU31: 0.027 | BV31: 0.027 | BW31: 0.027 | BX31: 0.027 | BY31: 0.027 | BZ31: 0.027 | CA31: 0.027 | CB31: 0.027 | CC31: 0.0275 | CD31: 0.0275 | CE31: 0.0275 | CF31: 0.0285 | CG31: 0.0285 | CH31: 0.0295 | CI31: 0.0295 | CJ31: 0.0295 | CK31: 0.0295 | CL31: 0.0295 | CM31: 0.0295 | CN31: 0.0295 | CO31: 0.03 | CP31: 0.03 | CQ31: 0.03 | CR31: 0.03 | CS31: 0.03 | CT31: 0.03 | CU31: 0.03 | CV31: 0.03 | CW31: 0.03 | CX31: 0.03 | CY31: 0.03 | CZ31: 0.03 | DA31: 0.03 | DB31: 0.03 | DC31: 0.0305 | DD31: 0.0305 | DE31: 0.0305 | DF31: 0.03 | DG31: 0.03 | DH31: 0.03 | DI31: 0.03 | DJ31: 0.0318 | DK31: 0.0318 | DL31: 0.0335 | DM31: 0.034 | DN31: 0.034 | DO31: 0.034 | DP31: 0.034 | DQ31: 0.034 | DR31: 0.034 | DS31: 0.033 | DT31: 0.033 | DU31: 0.033 | DV31: 0.032 | DW31: 0.03 | DX31: 0.03 | DY31: 0.03 | DZ31: 0.03 | EA31: 0.032 | EB31: 0.032 | EC31: 0.032 | ED31: 0.032 | EE31: 0.032 | EF31: 0.032 | EG31: 0.032 | EH31: 0.032 | EI31: - | EJ31: - | EK31: - | EL31: 0.03 | EM31: 0.031 | EN31: 0.031 | EO31: 0.031 | EP31: 0.031 | EQ31: 0.031 | ER31: 0.033 | ES31: 0.033 | ET31: 0.033 | EU31: 0.0345 | EV31: 0.0345 | EW31: 0.0355 | EX31: 0.0355 | EY31: 0.0355 | EZ31: ≥10,000 | FA31: - | FB31: - | FC31: ≥10,000 | FS31: 0.002 | FU31: 0.0138 | FV31: 0.0138 | FW31: 0.0138 | FX31: 0.0138 | FY31: - | FZ31: - | GA31: - | GB31: - | GC31: - | GD31: - | GE31: - | GF31: - | GG31: - | GH31: - | GI31: - | GJ31: - | GK31: - | GL31: - | GM31: - | GN31: - | GO31: - | GP31: - | GQ31: - | GR31: - | GS31: - | GT31: - | GU31: - | GV31: - | GW31: - | GX31: - | GY31: - | GZ31: - | HA31: - | HB31: - | HC31: 0.0355 | HD31: - | HE31: - | HF31: =C31-D31 -> 0
B32: 1.20%(NewFund 1k) | EZ32: ≥1,000
A33: OCBC | B33: 1.40%（fresh fund 50k-3mil）88 days | C33: 0.014 | D33: 0.014 | E33: 0.014 | F33: 0.016 | G33: 0.016 | H33: 0.016 | I33: 0.016 | J33: 0.018 | K33: 0.018 | L33: 0.018 | M33: 0.018 | N33: 0.018 | O33: 0.0145 | P33: 0.0145 | Q33: 0.0145 | R33: 0.0145 | S33: 0.0155 | T33: 0.0155 | U33: 0.0155 | V33: 0.0155 | W33: 0.0178 | X33: 0.0178 | Y33: 0.0178 | Z33: 0.0178 | AA33: 0.0178 | HF33: =C33-D33 -> 0
B34: 1.35%（fresh fund 25k-3000k） | AB34: 0.0188 | AC34: 0.0188 | AD34: 0.0208 | AE34: 0.0208 | AF34: 0.0208 | AG34: 0.0208 | AH34: - | AI34: - | AJ34: - | AK34: - | AL34: - | AM34: - | AN34: - | AO34: - | AP34: - | AQ34: - | AR34: - | AS34: - | AT34: - | AU34: - | AV34: - | AW34: - | AX34: - | AY34: - | AZ34: - | BA34: - | BB34: - | BC34: - | BD34: - | BE34: - | BF34: - | BG34: - | BH34: - | BI34: - | BJ34: - | BK34: - | BL34: - | BM34: - | BN34: - | BO34: - | BP34: - | BQ34: - | BR34: - | BS34: - | BT34: - | BU34: - | BV34: - | BW34: - | BX34: - | BY34: - | BZ34: - | CA34: - | CB34: - | CC34: - | CD34: - | CE34: - | CF34: - | CG34: - | CH34: - | CI34: - | CJ34: - | CK34: - | CL34: - | CM34: - | CN34: - | CO34: - | CP34: - | CQ34: - | CR34: - | CS34: - | CT34: - | CU34: - | CV34: - | CW34: - | CX34: - | CY34: - | CZ34: - | DA34: - | DB34: - | DC34: - | DD34: - | DE34: - | DF34: - | DG34: - | DH34: - | DI34: - | DJ34: - | DK34: - | DL34: - | DM34: - | DN34: - | DO34: - | DP34: - | DQ34: - | DR34: - | DS34: - | DT34: - | DU34: - | DV34: - | DW34: - | DX34: - | DY34: - | DZ34: - | EA34: - | EB34: - | EC34: - | ED34: - | EE34: - | EF34: - | EG34: - | EH34: - | EI34: - | EJ34: - | EK34: - | EL34: - | EM34: - | EN34: - | EO34: - | EP34: - | EQ34: - | ER34: - | ES34: - | ET34: - | EU34: - | EV34: - | EW34: - | EX34: - | EY34: - | EZ34: - | FA34: - | FB34: - | FC34: - | FD34: - | FE34: - | FF34: - | FG34: - | FH34: - | FI34: - | FJ34: - | FK34: - | FL34: - | FM34: - | FN34: - | FO34: - | FP34: - | FQ34: - | FR34: - | FS34: - | FT34: - | FU34: - | FV34: - | FW34: - | FX34: - | FY34: - | FZ34: - | GA34: - | GB34: - | GC34: - | GD34: - | GE34: - | GF34: - | GG34: - | GH34: - | GI34: - | GJ34: - | GK34: - | GL34: - | GM34: - | GN34: - | GO34: - | GP34: - | GQ34: - | GR34: - | GS34: - | GT34: - | GU34: - | GV34: - | GW34: - | GX34: - | GY34: - | GZ34: - | HA34: - | HB34: - | HC34: - | HD34: - | HE34: -
A35: HLB | B35: 1.50%(Online S$10K) 1.50%(Others S$100K) | C35: - | D35: - | E35: - | F35: - | G35: - | H35: - | I35: - | J35: - | K35: - | L35: - | M35: - | N35: - | O35: 0.015 | P35: 0.015 | HF35: =C35-D35 -> #VALUE!
A36: 6 Months
A37: 日期 | C37: =C3 -> 46099 | D37: =D3 -> 46092 | E37: =E3 -> 46085 | F37: =F3 -> 46078 | G37: =G3 -> 46071 | H37: =H3 -> 46064 | I37: =I3 -> 46057 | J37: =J3 -> 46050 | ... AF37: =AF3 -> 45896 | AG37: 45889 | AH37: 45882 | AI37: 45875 | AJ37: 45868 | AK37: 45861 | AL37: 45854 | AM37: 45847 | AN37: 45840 | AO37: =AO3 -> 45833 | AP37: 45826 | AQ37: =AQ3 -> 45819 | AR37: =AR3 -> 45812 | AS37: =AS3 -> 45805 | AT37: =AT3 -> 45798 | AU37: =AU3 -> 45792 | AV37: =AV3 -> 45785 | AW37: =AW3 -> 45777 | AX37: =AX3 -> 45771 | ... EH37: =EH3 -> 45148 | EI37: 45141 | EJ37: 45134 | EK37: 45127 | EL37: 45120 | EM37: 45113 | EN37: 45105 | EO37: 45099 | EP37: 45092 | EQ37: 45085 | ER37: 45076 | ES37: 45070 | ET37: 45063 | EU37: 45056 | EV37: 45049 | EW37: 45042 | EX37: 45035 | EY37: 45028 | FA37: 44803 | FD37: 44706 | FH37: 5月6日 | FI37: 44685 | FJ37: 44699 | FK37: 44690 | FL37: 44713 | FM37: 44720 | FN37: 44727 | FO37: 44733 | FP37: 44741 | FQ37: 44755 | FR37: 44748 | FS37: 44769 | FT37: 44762 | FU37: 44783 | FV37: 44776 | FW37: 44797 | FX37: 44790 | FY37: 44805 | FZ37: 45000 | GA37: 44993 | GB37: 44986 | GC37: 44979 | GD37: 44972 | GE37: 44965 | GF37: 44958 | GG37: 44951 | GH37: 44944 | GI37: 44937 | GJ37: 44930 | GK37: 44923 | GL37: 44916 | GM37: 44910 | GN37: 44902 | GO37: 44896 | GP37: 44888 | GQ37: 44881 | GR37: 44874 | GS37: 44868 | GT37: 44860 | GU37: 44853 | GV37: 44846 | GW37: 44839 | GX37: 44831 | GY37: 44825 | GZ37: 44818 | HA37: 44811 | HB37: 45002 | HC37: 45020 | HD37: 45014 | HE37: 45008
B38: 全部公开报价 | C38: 当日最高报价 | D38: 当日最高报价 | E38: 当日最高报价 | F38: 当日最高报价 | G38: 当日最高报价 | H38: 当日最高报价 | I38: 当日最高报价 | J38: 当日最高报价 | K38: 当日最高报价 | L38: 当日最高报价 | M38: 当日最高报价 | N38: 当日最高报价 | O38: 当日最高报价 | P38: 当日最高报价 | Q38: 当日最高报价 | R38: 当日最高报价 | S38: 当日最高报价 | T38: 当日最高报价 | U38: 当日最高报价 | V38: 当日最高报价 | W38: 当日最高报价 | X38: 当日最高报价 | Y38: 当日最高报价 | Z38: 当日最高报价 | AA38: 当日最高报价 | AB38: 当日最高报价 | AC38: 当日最高报价 | AD38: 当日最高报价 | AE38: 当日最高报价 | AF38: 当日最高报价 | AG38: 当日最高报价 | AH38: 当日最高报价 | AI38: 当日最高报价 | AJ38: 当日最高报价 | AK38: 当日最高报价 | AL38: 当日最高报价 | AM38: 当日最高报价 | AN38: 当日最高报价 | AO38: 当日最高报价 | AP38: 当日最高报价 | AQ38: 当日最高报价 | AR38: 当日最高报价 | AS38: 当日最高报价 | AT38: 当日最高报价 | AU38: 当日最高报价 | AV38: 当日最高报价 | AW38: 当日最高报价 | AX38: 当日最高报价 | AY38: 当日最高报价 | AZ38: 当日最高报价 | BA38: 当日最高报价 | BB38: 当日最高报价 | BC38: 当日最高报价 | BD38: 当日最高报价 | BE38: 当日最高报价 | BF38: 当日最高报价 | BG38: 当日最高报价 | BH38: 当日最高报价 | BI38: 当日最高报价 | BJ38: 当日最高报价 | BK38: 当日最高报价 | BL38: 当日最高报价 | BM38: 当日最高报价 | BN38: 当日最高报价 | BO38: 当日最高报价 | BP38: 当日最高报价 | BQ38: 当日最高报价 | BR38: 当日最高报价 | BS38: 当日最高报价 | BT38: 当日最高报价 | BU38: 当日最高报价 | BV38: 当日最高报价 | BW38: 当日最高报价 | BX38: 当日最高报价 | BY38: 当日最高报价 | BZ38: 当日最高报价 | CA38: 当日最高报价 | CB38: 当日最高报价 | CC38: 当日最高报价 | CD38: 当日最高报价 | CE38: 当日最高报价 | CF38: 当日最高报价 | CG38: 当日最高报价 | CH38: 当日最高报价 | CI38: 当日最高报价 | CJ38: 当日最高报价 | CK38: 当日最高报价 | CL38: 当日最高报价 | CM38: 当日最高报价 | CN38: 当日最高报价 | CO38: 当日最高报价 | CP38: 当日最高报价 | CQ38: 当日最高报价 | CR38: 当日最高报价 | CS38: 当日最高报价 | CT38: 当日最高报价 | CU38: 当日最高报价 | CV38: 当日最高报价 | CW38: 当日最高报价 | CX38: 当日最高报价 | CY38: 当日最高报价 | CZ38: 当日最高报价 | DA38: 当日最高报价 | DB38: 当日最高报价 | DC38: 当日最高报价 | DD38: 当日最高报价 | DE38: 当日最高报价 | DF38: 当日最高报价 | DG38: 当日最高报价 | DH38: 当日最高报价 | DI38: 当日最高报价 | DJ38: 当日最高报价 | DK38: 当日最高报价 | DL38: 当日最高报价 | DM38: 当日最高报价 | DN38: 当日最高报价 | DO38: 当日最高报价 | DP38: 当日最高报价 | DQ38: 当日最高报价 | DR38: 当日最高报价 | DS38: 当日最高报价 | DT38: 当日最高报价 | DU38: 当日最高报价 | DV38: 当日最高报价 | DW38: 当日最高报价 | DX38: 当日最高报价 | DY38: 当日最高报价 | DZ38: 当日最高报价 | EA38: 当日最高报价 | EB38: 当日最高报价 | EC38: 当日最高报价 | ED38: 当日最高报价 | EE38: 当日最高报价 | EF38: 当日最高报价 | EG38: 当日最高报价 | EH38: 当日最高报价 | EI38: 当日最高报价 | EJ38: 当日最高报价 | EK38: 当日最高报价 | EL38: 当日最高报价 | EM38: 当日最高报价 | EN38: 当日最高报价 | EO38: 当日最高报价 | EP38: 当日最高报价 | EQ38: 当日最高报价 | ER38: 当日最高报价 | ES38: 当日最高报价 | ET38: 当日最高报价 | EU38: 当日最高报价 | EV38: 当日最高报价 | EW38: 当日最高报价 | EX38: 当日最高报价 | EY38: 当日最高报价 | EZ38: 金额 | FA38: 当日最高报价 | FB38: 全部公开报价 | FC38: 金额 | FD38: 当日最高报价 | FE38: 全部公开报价 | FF38: 金额 | FG38: 挂牌利率/促销利率 | FH38: 当日最高报价 | FI38: 当日最高报价 | FJ38: 当日最高报价 | FK38: 当日最高报价 | FL38: 当日最高报价 | FM38: 当日最高报价 | FN38: 当日最高报价 | FO38: 当日最高报价 | FP38: 当日最高报价 | FQ38: 当日最高报价 | FR38: 当日最高报价 | FS38: 当日最高报价 | FT38: 当日最高报价 | FU38: 当日最高报价 | FV38: 当日最高报价 | FW38: 当日最高报价 | FX38: 当日最高报价 | FY38: 当日最高报价 | FZ38: 当日最高报价 | GA38: 当日最高报价 | GB38: 当日最高报价 | GC38: 当日最高报价 | GD38: 当日最高报价 | GE38: 当日最高报价 | GF38: 当日最高报价 | GG38: 当日最高报价 | GH38: 当日最高报价 | GI38: 当日最高报价 | GJ38: 当日最高报价 | GK38: 当日最高报价 | GL38: 当日最高报价 | GM38: 当日最高报价 | GN38: 当日最高报价 | GO38: 当日最高报价 | GP38: 当日最高报价 | GQ38: 当日最高报价 | GR38: 当日最高报价 | GS38: 当日最高报价 | GT38: 当日最高报价 | GU38: 当日最高报价 | GV38: 当日最高报价 | GW38: 当日最高报价 | GX38: 当日最高报价 | GY38: 当日最高报价 | GZ38: 当日最高报价 | HA38: 当日最高报价 | HB38: 当日最高报价 | HC38: 当日最高报价 | HD38: 当日最高报价 | HE38: 当日最高报价 | HF38: 当日最高报价变动
A39: SCB | B39: 1.25% (personal banking) | C39: 0 | D39: 0 | E39: 0 | F39: 0.0125 | G39: 0.0135 | H39: 0.0135 | I39: 0.0145 | J39: 0.0145 | K39: 0.011 | L39: 0.011 | M39: 0.0115 | N39: 0.0115 | O39: 0.0115 | P39: 0.0115 | Q39: 0.0115 | R39: 0.0115 | S39: 0.0105 | T39: 0.011 | U39: 0.011 | V39: 0.011 | W39: 0.011 | X39: 0.011 | Y39: 0.011 | Z39: 0.011 | AA39: 0.011 | AB39: 0.011 | AC39: 0.011 | AD39: 0.011 | AE39: 0.0115 | AF39: 0.012 | AG39: 0.013 | AH39: 0.0135 | AI39: 0.014 | AJ39: 0.014 | AK39: 0.014 | AL39: 0.0145 | AM39: 0.0145 | AN39: 1.55%（5M) | AO39: 1.65%（5M) | AP39: 1.70%（5M) | AQ39: 1.75%（5M) | AR39: 1.90%（5M) | AS39: 1.95%（5M) | AT39: 1.95%（5M) | AU39: 1.95%（5M) | AV39: 2.00%（5M) | AW39: 2.00%（5M) | AX39: 2.00%（5M) | AY39: 0.022 | AZ39: 0.022 | BA39: 0.022 | BB39: 0.022 | BC39: 0.022 | BD39: 0.022 | BE39: 0.023 | BF39: 0.023 | BG39: 0.024 | BH39: 0.025 | BI39: 0.025 | BJ39: 0.0258 | BK39: 0.0258 | BL39: 0.024 | BM39: 0.024 | BN39: 0.024 | BO39: 0.0255 | BP39: 0.0255 | BQ39: 0.0255 | BR39: 0.0255 | BS39: 0.0255 | BT39: 0.0255 | BU39: 0.0255 | BV39: 0.0255 | BW39: - | BX39: - | BY39: - | BZ39: - | CA39: - | CB39: - | CC39: - | CD39: - | CE39: - | CF39: 3.10% (priority private) | CG39: 3.10% (priority private) | CH39: 3.10% (priority private) | CI39: 3.10% (priority private) | CJ39: 3.10% (priority private) | CK39: 3.10% (priority private) | CL39: 3.10% (priority private) | CM39: 3.10% (priority private) | CN39: 3.10% (priority private) | CO39: 3.10% (priority private) | CP39: 3.10% (priority private) | CQ39: 3.10% (priority private) | CR39: 3.20% (priority private) | CS39: 3.20% (priority private) | CT39: 3.20% (priority private) | CU39: 3.20% (priority private) | CV39: 3.20% (priority private) | CW39: 3.20% (priority private) | CX39: 3.20% (priority private) | CY39: 3.20% (priority private) | CZ39: 3.20% (priority private) | DA39: 3.20% (priority private) | DB39: 3.20% (priority private) | DC39: 3.20% (priority private) | DD39: 3.20% (priority private) | DE39: 3.30% (priority private) | DF39: 3.30% (priority private) | DG39: 3.30% (priority private) | DH39: 0.033 | DI39: 0.033 | DJ39: 0.033 | DK39: 0.033 | DL39: 0.033 | DM39: 0.033 | DN39: 0.034 | DO39: 0.034 | DP39: 0.034 | DQ39: 0.034 | DR39: 0.034 | DS39: 0.034 | DT39: 0.034 | DU39: 0.032 | DV39: 0.032 | DW39: 0.032 | DX39: 0.032 | DY39: 0.032 | DZ39: 0.032 | EA39: 0.034 | EB39: 0.034 | EC39: 0.034 | ED39: 0.034 | EE39: 0.034 | EF39: 0.034 | EG39: 0.034 | EH39: 0.034 | EI39: 0.034 | EJ39: 0.034 | EK39: 0.034 | EL39: 0.034 | EM39: 0.034 | EN39: 0.034 | EO39: 0.034 | EP39: 0.034 | EQ39: 0.034 | ER39: 0.034 | ES39: 0.034 | ET39: 0.034 | EU39: 0.034 | EZ39: ≥25,000 | HF39: =C39-D39 -> 0 | HG39: 25k | HH39: 28 Jan - 1 Feb 2026
B40: 1.30% (priority banking) | EZ40: ≥25,000
B41: 1.35% (priority private banking) | EZ41: ≥25,000
A42: BEA | B42: - | V42: - | W42: - | X42: - | Y42: - | Z42: - | AA42: - | AB42: - | AC42: - | AD42: - | AE42: - | AF42: - | AG42: - | AH42: - | AI42: - | AJ42: - | AK42: - | AL42: - | AM42: - | AN42: - | AO42: - | AP42: - | AQ42: - | AR42: - | AS42: - | AT42: - | AU42: - | AV42: - | AW42: - | AX42: - | AY42: - | AZ42: - | BA42: - | BB42: - | BC42: - | BD42: - | BE42: - | BF42: - | BG42: - | BH42: - | BI42: - | BJ42: - | BK42: - | BL42: - | BM42: - | BN42: - | BO42: - | BP42: - | BQ42: - | BR42: - | BS42: - | BT42: - | BU42: - | BV42: - | BW42: - | BX42: - | BY42: - | BZ42: - | CA42: - | CB42: - | CC42: - | CD42: - | CE42: - | CF42: - | CG42: - | CH42: - | CI42: - | CJ42: - | CK42: - | CL42: - | CM42: - | CN42: - | CO42: - | CP42: - | CQ42: - | CR42: - | CS42: - | CT42: - | CU42: - | CV42: - | CW42: - | CX42: - | CY42: - | CZ42: - | DA42: - | DB42: - | DC42: - | DD42: - | DE42: - | DF42: - | DG42: - | DH42: - | DI42: - | DJ42: - | DK42: - | DL42: - | DM42: - | DN42: - | DO42: - | DP42: - | DQ42: - | DR42: - | DS42: - | DT42: - | DU42: - | DV42: - | DW42: - | DX42: - | DY42: 0.0345 | DZ42: 0.0345 | EA42: 0.0345 | EB42: 0.0345 | EC42: 0.0345 | ED42: 0.0345 | EE42: 0.0345 | EF42: 0.0345 | EG42: 0.0345 | EH42: 0.0345 | EI42: 0.0345 | EJ42: 0.0345 | EK42: 0.0345 | EL42: 0.0345 | EM42: 0.0345 | EN42: 0.0345 | EO42: 0.0345 | EP42: 0.0345 | EQ42: 0.035 | ER42: 0.035 | ES42: 0.036 | ET42: 0.036 | EU42: 0.036 | EV42: 0.036 | EW42: 0.036 | EX42: 0.036 | EY42: 0.036 | EZ42: ≥100,000 | FZ42: 0.036 | GA42: 0.036 | GB42: 0.036 | GC42: 0.036 | GD42: 0.036 | GE42: 0.036 | GF42: 0.036 | GG42: 0.036 | GH42: 0.036 | GI42: 0.036 | GJ42: 0.041 | GK42: 0.041 | GL42: 0.041 | GM42: 0.041 | GN42: 0.024 | GO42: 0.024 | GP42: 0.024 | GQ42: 0.024 | GR42: 0.024 | GS42: 0.024 | GT42: 0.024 | GU42: 0.024 | GV42: 0.024 | GW42: 0.024 | GX42: 0.024 | HB42: 0.036 | HC42: 0.036 | HD42: 0.036 | HE42: 0.036 | HF42: -
A43: SBI | B43: 1.50%（50k-200k） | C43: 0.0115 | D43: 0.0115 | E43: 0.0115 | F43: 0.0115 | G43: 0.0115 | H43: 0.009 | I43: 0.009 | J43: 0.009 | K43: 0.009 | L43: 0.009 | M43: 0.009 | N43: 0.009 | O43: 0.009 | P43: 0.009 | Q43: 0.009 | R43: 0.009 | S43: 0.009 | T43: 0.009 | U43: 0.009 | V43: 0.009 | W43: - | X43: - | Y43: - | Z43: - | AA43: - | AB43: - | AC43: - | AD43: - | AE43: 0.016 | AF43: 0.016 | AG43: 0.016 | AH43: 0.016 | AI43: 0.016 | AJ43: 0.016 | AK43: - | AL43: - | AM43: - | AN43: - | AO43: - | AP43: - | AQ43: - | AR43: 0.0235 | AS43: 0.0235 | AT43: 0.0235 | AU43: 0.0235 | AV43: 0.0235 | AW43: 0.025 | AX43: 0.025 | AY43: 0.025 | AZ43: 0.025 | BA43: 0.025 | BB43: 0.025 | BC43: 0.025 | BD43: 0.0285 | BE43: 0.0285 | BF43: 0.0285 | BG43: 0.0285 | BH43: 0.0265 | BI43: 0.0265 | BJ43: 0.0265 | BK43: 0.0265 | BL43: 0.0265 | BM43: 0.0265 | BN43: 0.0265 | BO43: 0.0265 | BP43: 0.0265 | BQ43: 0.0265 | BR43: - | BS43: - | BT43: - | BU43: - | BV43: 0.029 | BW43: 0.029 | BX43: 0.029 | BY43: 0.029 | BZ43: 0.029 | CA43: 0.0315 | CB43: 0.0315 | CC43: 0.0315 | CD43: 0.0315 | CE43: 0.0315 | CF43: 0.0315 | CG43: 0.0315 | CH43: 0.034 | CI43: 0.034 | CJ43: 0.034 | CK43: 0.034 | CL43: 0.034 | CM43: 0.034 | CN43: 0.034 | CO43: 0.0335 | CP43: 0.0335 | CQ43: 0.0335 | CR43: 0.0335 | CS43: 0.0335 | CT43: 0.0335 | CU43: 0.0335 | CV43: 0.0335 | CW43: - | CX43: - | CY43: - | CZ43: - | DA43: - | DB43: - | DC43: - | DD43: - | DE43: - | DF43: 0.0355 | DG43: 0.0355 | DH43: 0.0355 | DI43: 0.0355 | DJ43: 0.0365 | DK43: 0.0365 | DL43: 0.0365 | DM43: 0.0365 | DN43: 0.0365 | DO43: 0.0365 | DP43: 0.0365 | DQ43: 0.0365 | DR43: - | DS43: 0.0355 | DT43: 0.0355 | DU43: 0.0355 | DV43: 0.0355 | DW43: 0.0355 | DX43: 0.0355 | DY43: 0.0355 | DZ43: 0.0355 | EA43: 0.0355 | EB43: 0.0355 | EC43: 0.0355 | ED43: 0.0355 | EE43: 0.0355 | EF43: 0.0355 | EG43: 0.032 | EH43: 0.032 | EI43: 0.032 | EJ43: 0.032 | EK43: 0.032 | EL43: 0.032 | EM43: 0.032 | EN43: 0.032 | EO43: 0.035 | EP43: 0.035 | EQ43: 0.035 | ER43: 0.035 | ES43: 0.035 | ET43: 0.0375 | EU43: 0.0375 | EV43: 0.0375 | EW43: 0.0375 | EX43: 0.0375 | EY43: 0.0375 | EZ43: 50,000-1,000,000 | FA43: 0.0225 | FB43: 0.0225 | FC43: ≥25,000 | FD43: 0.0125 | FE43: 0.009 | FF43: 1千-2.49万 | FG43: 挂牌 | FH43: 0.0125 | FI43: 0.0125 | FJ43: 0.0125 | FK43: 0.0125 | FL43: 0.0125 | FM43: 0.0125 | FN43: 0.0125 | FO43: 0.0125 | FP43: 0.016 | FQ43: 0.016 | FR43: 0.016 | FS43: 0.02 | FT43: 0.016 | FU43: 0.0225 | FV43: 0.02 | FW43: 0.0225 | FX43: 0.0225 | FY43: 0.0225 | FZ43: 0.04 | GA43: 0.04 | GB43: 0.04 | GC43: 0.04 | GD43: 0.04 | GE43: 0.04 | GF43: 0.04 | GG43: 0.04 | GH43: 0.04 | GI43: 0.04 | GJ43: 0.04 | GK43: 0.04 | GL43: 0.0375 | GM43: 0.0375 | GN43: 0.0375 | GO43: 0.0375 | GP43: 0.0375 | GQ43: 0.0375 | GR43: 0.0333 | GS43: 3.33% fresh fund | GT43: 3.33% fresh fund | GU43: 3.33% fresh fund | GV43: 3.33% fresh fund | GW43: 0.0265 | GX43: 0.0265 | GY43: 0.0265 | GZ43: 0.0265 | HA43: 0.0265 | HB43: 0.04 | HC43: 0.0375 | HD43: 0.0375 | HE43: 0.04 | HF43: =C41-D41 -> 0
B44: 1.15%（50k） | HF44: =W44-AT44 -> 0
A45: ICBC | B45: 1.10%（online） | C45: 0.0115 | D45: 0.0115 | E45: 0.0115 | F45: 0.0115 | G45: 0.0115 | H45: 0.0115 | I45: 0.0115 | J45: 0.0115 | K45: 0.0115 | L45: 0.0115 | M45: 0.012 | N45: 0.012 | O45: 0.012 | P45: 0.014 | Q45: 0.014 | R45: 0.014 | S45: 0.012 | T45: 0.012 | U45: 0.012 | V45: 0.012 | W45: 0.012 | X45: 0.012 | Y45: 0.012 | Z45: 0.012 | AA45: 0.012 | AB45: 0.012 | AC45: 0.012 | AD45: 0.0135 | AE45: 0.0135 | AF45: 0.0145 | AG45: 0.0145 | AH45: 0.015 | AI45: 0.016 | AJ45: 0.016 | AK45: 0.0165 | AL45: 0.0165 | AM45: 0.018 | AN45: 0.018 | AO45: 0.018 | AP45: 0.018 | AQ45: 0.02 | AR45: 0.0215 | AS45: 2.15%（电子银行） | AT45: =#REF! -> #REF! | AU45: 2.25%（电子银行） | AV45: 2.25%（电子银行） | AW45: 2.25%（电子银行） | AX45: 2.25%（电子银行） | AY45: 2.25%（电子银行） | AZ45: 2.40%电子/2.40%柜台 | BA45: 2.40%电子/2.40%柜台 | BB45: =BC45 -> 2.75% （电子银行） | BC45: =BD45 -> 2.75% （电子银行） | BD45: =BE45 -> 2.75% （电子银行） | BE45: =BF45 -> 2.75% （电子银行） | BF45: =BG45 -> 2.75% （电子银行） | BG45: =BH45 -> 2.75% （电子银行） | BH45: =BI45 -> 2.75% （电子银行） | BI45: =BJ45 -> 2.75% （电子银行） | ... CB45: =CC45 -> 2.75% （电子银行） | CC45: 2.75% （电子银行） | CD45: 0.029 | CE45: 0.031 | CF45: 0.031 | CG45: 0.031 | CH45: 0.031 | CI45: 0.0315 | CJ45: 0.0315 | CK45: 0.0315 | CL45: 0.0315 | CM45: 0.0315 | CN45: 0.0315 | CO45: 0.0315 | CP45: 0.0315 | CQ45: 0.0315 | CR45: 0.0315 | CS45: 0.0315 | CT45: 0.0315 | CU45: 0.0315 | CV45: 0.0315 | CW45: 0.032 | CX45: 0.032 | CY45: 0.032 | CZ45: 0.032 | DA45: 0.032 | DB45: 0.032 | DC45: 0.032 | DD45: 0.032 | DE45: 0.032 | DF45: 0.032 | DG45: 0.032 | DH45: 0.032 | DI45: 0.032 | DJ45: 0.032 | DK45: 0.032 | DL45: 0.032 | DM45: 0.032 | DN45: 0.032 | DO45: 0.032 | DP45: 0.032 | DQ45: 0.032 | DR45: 0.032 | DS45: 0.032 | DT45: 0.032 | DU45: 0.032 | DV45: 0.032 | DW45: 0.032 | DX45: 0.032 | DY45: 0.032 | DZ45: 0.032 | EA45: 0.032 | EB45: 0.032 | EC45: 0.032 | ED45: 0.032 | EE45: 0.032 | EF45: 0.032 | EG45: 0.032 | EH45: 0.032 | EI45: 0.032 | EJ45: 0.032 | EK45: 0.0335 | EL45: 0.0335 | EM45: 0.034 | EN45: 0.034 | EO45: 0.034 | EP45: 0.034 | EQ45: 0.034 | ER45: 0.034 | ES45: 0.034 | ET45: 0.0355 | EU45: 0.0355 | EV45: 0.0355 | EW45: 0.0365 | EX45: 0.0315 | EY45: 0.0315 | EZ45: ≥20,000 | FA45: 0.0125 | FB45: 1.25% 电子银行 | FC45: ≥500 | FD45: 0.0125 | FE45: 1.2% 柜面 | FF45: ≥500 | FG45: 促销 | FH45: 0.0055 | FI45: 0.0055 | FJ45: 0.0055 | FK45: 0.0055 | FL45: 0.0125 | FM45: 0.0125 | FN45: 0.0125 | FO45: 0.0125 | FP45: 0.0125 | FQ45: 0.0125 | FR45: 0.0125 | FS45: 0.0125 | FT45: 0.0125 | FU45: 0.0125 | FV45: 0.0125 | FW45: 0.0125 | FX45: 0.0125 | FY45: 0.019 | FZ45: 0.0315 | GA45: 0.0315 | GB45: 0.0315 | GC45: 0.0315 | GD45: 0.0315 | GE45: 0.0315 | GF45: 0.0315 | GG45: 0.0315 | GH45: 0.0315 | GI45: 0.0315 | GJ45: 0.0315 | GK45: 0.0315 | GL45: 0.0315 | GM45: 0.0315 | GN45: 0.0315 | GO45: 0.0315 | GP45: 0.0315 | GQ45: 0.0315 | GR45: 0.0315 | GS45: 0.029 | GT45: 0.029 | GU45: 0.029 | GV45: 0.0225 | GW45: 0.0225 | GX45: 0.0225 | GY45: 0.019 | GZ45: 0.019 | HA45: 0.019 | HB45: 0.0315 | HC45: 0.0315 | HD45: 0.0315 | HE45: 0.0315 | HF45: =C45-D45 -> 0 | HG45: 500-200k
B46: 1.15%（online）>200k | HG46: >200k
A47: BOC | B47: $500手机银行 | C47: 0.0135 | D47: 0.0135 | E47: 0.0135 | F47: 0.0135 | G47: 0.0135 | H47: 0.0135 | I47: 0.0135 | J47: 0.0135 | K47: 0.0135 | L47: 0.0135 | M47: 0.0135 | N47: 0.0135 | O47: 0.0135 | P47: 0.0135 | Q47: 0.0135 | R47: 0.0135 | S47: 0.0135 | T47: 0.014 | U47: 0.014 | V47: 0.014 | W47: 0.0135 | X47: 0.0135 | Y47: 0.0135 | Z47: 0.0135 | AA47: 0.013 | AB47: 0.013 | AC47: 0.0138 | AD47: 0.014 | AE47: 0.015 | AF47: 0.0155 | AG47: 0.016 | AH47: 0.017 | AI47: 0.017 | AJ47: 0.017 | AK47: 0.017 | AL47: 0.0175 | AM47: 0.0182 | AN47: 0.0185 | AO47: 0.019 | AP47: 0.019 | AQ47: 0.02 | AR47: 0.02 | AS47: 0.022 | AT47: 0.022 | AU47: 0.0225 | AV47: 0.0235 | AW47: 0.024 | AX47: 0.0245 | AY47: 0.0245 | AZ47: 0.0245 | BA47: 0.0245 | BB47: 0.0245 | BC47: 0.0245 | BD47: 0.0255 | BE47: 0.026 | BF47: 0.027 | BG47: 0.027 | BH47: 0.027 | BI47: 0.0275 | BJ47: 0.0275 | BK47: 0.0275 | BL47: 0.0275 | BM47: 0.0275 | BN47: 0.0275 | BO47: 0.0275 | BP47: 0.0275 | BQ47: 0.0275 | BR47: 0.0275 | BS47: 0.0275 | BT47: 0.0275 | BU47: 0.0275 | BV47: 0.0275 | BW47: 0.028 | BX47: 0.028 | BY47: 0.028 | BZ47: 0.028 | CA47: 0.028 | CB47: 0.0285 | CC47: 0.0285 | CD47: 0.0285 | CE47: 0.029 | CF47: 0.031 | CG47: 0.031 | CH47: 0.031 | CI47: 0.032 | CJ47: 0.033 | CK47: 0.033 | CL47: 0.033 | CM47: 0.033 | CN47: 0.033 | CO47: 0.033 | CP47: 0.033 | CQ47: 0.033 | CR47: 0.032 | CS47: 0.032 | CT47: 0.032 | CU47: 0.032 | CV47: 0.032 | CW47: 0.032 | CX47: 0.032 | CY47: 0.032 | CZ47: 0.0325 | DA47: 0.0325 | DB47: 0.033 | DC47: 0.033 | DD47: 0.033 | DE47: 0.033 | DF47: 0.033 | DG47: 0.0335 | DH47: 0.0335 | DI47: 0.0335 | DJ47: 0.0335 | DK47: 0.034 | DL47: 0.0345 | DM47: 0.0345 | DN47: 0.0355 | DO47: 0.0355 | DP47: 0.0355 | DQ47: 0.0355 | DR47: 0.035 | DS47: 0.0345 | DT47: 0.0345 | DU47: 0.033 | DV47: 0.033 | DW47: 0.033 | DX47: 0.033 | DY47: 0.033 | DZ47: 0.033 | EA47: 0.0335 | EB47: 0.0335 | EC47: 0.0335 | ED47: 0.0335 | EE47: 0.0335 | EF47: 0.0335 | EG47: 0.0335 | EH47: 0.0335 | EI47: 0.0335 | EJ47: 0.0335 | EK47: 0.0335 | EL47: 0.0335 | EM47: 0.0335 | EN47: 0.0335 | EO47: 0.0335 | EP47: 0.0335 | EQ47: 0.0345 | ER47: 0.0345 | ES47: 0.0345 | ET47: 0.035 | EU47: 0.0355 | EV47: 0.036 | EW47: 0.036 | EX47: 0.0365 | EY47: 0.037 | EZ47: ≥10,000 | FY47: 0.021 | FZ47: 0.038 | GA47: 0.038 | GB47: 0.038 | GC47: 0.038 | GD47: 0.0385 | GE47: 0.0385 | GF47: 0.04 | GG47: 0.04 | GH47: 0.04 | GI47: 0.04 | GJ47: 0.0395 | GK47: 0.0395 | GL47: 0.0395 | GM47: 0.0395 | GN47: 0.0395 | GO47: 0.0385 | GP47: 0.0385 | GQ47: 0.0335 | GR47: 0.0315 | GS47: 0.0315 | GT47: 0.03 | GU47: 0.03 | GV47: 0.0285 | GW47: 0.0255 | GX47: 0.025 | GY47: 0.0225 | GZ47: 0.0225 | HA47: 0.0225 | HB47: 0.038 | HC47: 0.037 | HD47: 0.0375 | HE47: 0.038 | HF47: =C47-D47 -> 0
EZ48: ≥500 | FA48: 0.021 | FB48: 0.021 | FC48: ≥5,000 | FD48: 0.009 | FE48: 0.009 | FF48: ≥5千 | FG48: 促销 | FH48: 0.0055 | FI48: 0.0055 | FJ48: 0.009 | FK48: 0.0055 | FL48: 0.009 | FM48: 0.009 | FN48: 0.009 | FO48: 0.009 | FP48: 0.012 | FQ48: 0.013 | FR48: 0.013 | FS48: 0.013 | FT48: 0.013 | FU48: 0.017 | FV48: 0.017 | FW48: 0.019 | FX48: 0.019 | HF48: =W48-AT48 -> 0
A49: RHB | B49: 1.20% (personal） | C49: 0.012 | D49: 0.012 | E49: 0.012 | F49: 0.012 | G49: 0.012 | H49: 0.012 | I49: 0.0145 | J49: 0.0145 | K49: 0.0145 | L49: 0.0145 | M49: 0.0145 | N49: 0.0145 | O49: 0.0145 | P49: 0.0125 | Q49: 0.0125 | R49: 0.011 | S49: 0.011 | T49: 0.012 | U49: 0.012 | V49: 0.012 | W49: 0.013 | X49: 0.013 | Y49: 0.013 | Z49: 0.013 | AA49: 0.013 | AB49: 0.011 | AC49: 0.011 | AD49: 0.011 | AE49: 0.011 | AF49: 0.011 | AG49: 0.011 | AH49: 0.011 | AI49: 0.012 | AJ49: 0.015 | AK49: 0.016 | AL49: 0.016 | AM49: 0.018 | AN49: 0.018 | AO49: 0.022 | AP49: 0.022 | AQ49: 0.022 | AR49: 0.021 | AS49: 0.021 | AT49: 0.021 | AU49: 0.021 | AV49: 0.021 | AW49: 0.023 | AX49: 0.023 | AY49: 0.023 | AZ49: 0.023 | BA49: 0.023 | BB49: 0.025 | BC49: 0.025 | BD49: 0.025 | BE49: 0.028 | BF49: 0.028 | BG49: 0.028 | BH49: 0.0268 | BI49: 0.0268 | BJ49: 0.0268 | BK49: 0.0268 | BL49: 0.0268 | BM49: 0.03 | BN49: 0.03 | BO49: 0.03 | BP49: 0.03 | BQ49: 0.03 | BR49: 0.03 | BS49: 0.029 | BT49: 0.029 | BU49: 0.0285 | BV49: 0.0285 | BW49: 0.0285 | BX49: 0.0285 | BY49: 0.0285 | BZ49: 0.0265 | CA49: 0.0265 | CB49: 0.0265 | CC49: 0.03 | CD49: 0.03 | CE49: 0.0315 | CF49: 0.0315 | CG49: 0.033 | CH49: 0.033 | CI49: 0.034 | CJ49: 0.034 | CK49: 0.034 | CL49: 0.034 | CM49: 0.034 | CN49: 0.033 | CO49: 0.033 | CP49: 0.033 | CQ49: 0.033 | CR49: 0.033 | CS49: 0.033 | CT49: 0.033 | CU49: 0.033 | CV49: 0.033 | CW49: 0.033 | CX49: 0.032 | CY49: 0.032 | CZ49: 0.032 | DA49: 0.032 | DB49: 0.032 | DC49: 0.032 | DD49: 0.032 | DE49: 0.033 | DF49: 0.033 | DG49: 0.033 | DH49: 0.033 | DI49: 0.033 | DJ49: 0.033 | DK49: 0.033 | DL49: 0.0345 | DM49: 0.0345 | DN49: 0.0345 | DO49: 0.0345 | DP49: 0.0368 | DQ49: 0.0368 | DR49: 0.0368 | DS49: 0.0368 | DT49: 0.0368 | DU49: 0.0368 | DV49: 0.0368 | DW49: 0.0368 | DX49: 0.0368 | DY49: 0.0368 | DZ49: 0.0368 | EA49: 0.0368 | EB49: 0.0368 | EC49: 0.0345 | ED49: 0.0345 | EE49: 0.0345 | EF49: 0.0345 | EG49: 0.0345 | EH49: 0.0345 | EI49: 0.0345 | EJ49: 0.0345 | EK49: 0.0345 | EL49: 0.0345 | EM49: 0.0355 | EN49: 0.0355 | EO49: 0.0355 | EP49: 0.0355 | EQ49: 0.0355 | ER49: 0.0355 | ES49: 0.0355 | ET49: 0.0355 | EU49: 0.0355 | EV49: 0.0355 | EW49: 0.041 | EX49: 0.041 | EY49: 0.036 | EZ49: ≥20000 | FA49: 0.019 | FB49: 1.9%财富 | FC49: ≥20000 | FU49: - | FW49: 0.019 | FX49: 0.019 | FY49: 0.019 | FZ49: 0.036 | GA49: 0.036 | GB49: 0.036 | GC49: 0.036 | GD49: 0.0388 | GE49: 0.0388 | GF49: 0.0388 | GG49: 0.0388 | GH49: 0.0388 | GI49: 0.0388 | GJ49: 0.031 | GK49: 0.031 | GL49: 0.031 | GM49: 0.031 | GN49: 0.031 | GO49: 0.031 | GP49: 0.031 | GQ49: 0.031 | GR49: 0.031 | GS49: 0.031 | GT49: 0.031 | GU49: 0.031 | GV49: 0.031 | GW49: 0.024 | GX49: 0.019 | GY49: 0.019 | GZ49: 0.019 | HA49: 0.019 | HB49: 0.036 | HC49: 0.036 | HD49: 0.036 | HE49: 0.036 | HF49: =C49-D49 -> 0
B50: 1.30% (premier） | HF50: =W50-AT50 -> 0 | HG50: 20k | HH50: from 19 Jan 2026
A51: CIMB | B51: 1.3% 手机银行 （个人） | C51: 0.013 | D51: 0.013 | E51: 0.013 | F51: 0.013 | G51: 0.013 | H51: 0.013 | I51: 0.013 | J51: 0.013 | K51: 0.013 | L51: 0.013 | M51: 0.013 | N51: 0.013 | O51: 0.013 | P51: 0.0125 | Q51: 0.0125 | R51: 0.0125 | S51: 0.012 | T51: 0.012 | U51: 0.012 | V51: 0.012 | W51: 0.0125 | X51: 0.0125 | Y51: 0.0125 | Z51: 0.0125 | AA51: 0.0125 | AB51: 0.013 | AC51: 0.013 | AD51: 0.013 | AE51: 0.014 | AF51: 0.0145 | AG51: 0.0155 | AH51: 0.0155 | AI51: 0.0155 | AJ51: 0.0155 | AK51: 0.0155 | AL51: 0.0155 | AM51: 0.0165 | AN51: 0.0175 | AO51: 0.019 | AP51: 0.02 | AQ51: 0.021 | AR51: 0.021 | AS51: 0.0215 | AT51: 0.0215 | AU51: 0.021 | AV51: 0.021 | AW51: 0.021 | AX51: 0.022 | AY51: 0.022 | AZ51: 0.022 | BA51: 0.022 | BB51: 0.023 | BC51: 0.023 | BD51: 0.023 | BE51: 0.0245 | BF51: 0.026 | BG51: 0.026 | BH51: 0.026 | BI51: 0.026 | BJ51: 0.0275 | BK51: 0.0275 | BL51: 0.0275 | BM51: 0.0275 | BN51: 0.0275 | BO51: 0.028 | BP51: 0.028 | BQ51: 0.028 | BR51: 0.028 | BS51: 0.028 | BT51: 0.028 | BU51: 0.028 | BV51: 0.028 | BW51: 0.028 | BX51: 0.028 | BY51: 0.028 | BZ51: 0.028 | CA51: 0.028 | CB51: 0.028 | CC51: 0.03 | CD51: 0.03 | CE51: 0.03 | CF51: 0.031 | CG51: 0.031 | CH51: 0.033 | CI51: 0.033 | CJ51: 0.033 | CK51: 0.034 | CL51: 0.034 | CM51: 0.034 | CN51: 0.034 | CO51: 0.0325 | CP51: 0.0325 | CQ51: 0.0325 | CR51: 0.0325 | CS51: 0.0325 | CT51: 0.0325 | CU51: 0.0325 | CV51: 0.0325 | CW51: 0.033 | CX51: 0.033 | CY51: 0.033 | CZ51: 0.033 | DA51: 0.034 | DB51: 0.034 | DC51: 0.034 | DD51: 0.034 | DE51: 0.0355 | DF51: 0.0355 | DG51: 0.0355 | DH51: 0.0355 | DI51: 0.0355 | DJ51: 0.0355 | DK51: 0.0355 | DL51: 0.0355 | DM51: 0.0355 | DN51: 0.0355 | DO51: 0.0355 | DP51: 0.0355 | DQ51: 0.0355 | DR51: 0.0345 | DS51: 0.0345 | DT51: 0.0345 | DU51: 0.0345 | DV51: 0.0345 | DW51: 0.0345 | DX51: 0.0345 | DY51: 0.0345 | DZ51: 0.0345 | EA51: 0.0345 | EB51: 0.0345 | EC51: 0.0345 | ED51: 0.0345 | EE51: 0.034 | EF51: 0.034 | EG51: 0.034 | EH51: 0.034 | EI51: 0.034 | EJ51: 0.032 | EK51: 0.032 | EL51: 0.032 | EM51: 0.032 | EN51: 0.032 | EO51: 0.032 | EP51: 0.032 | EQ51: 0.032 | ER51: 0.034 | ES51: 0.034 | ET51: 0.034 | EU51: 0.034 | EV51: 0.034 | EW51: 0.035 | EX51: 0.035 | EY51: 0.035 | EZ51: ≥10,000 | FA51: 0.013 | FB51: 1.30%财富 | FC51: ≥10,000 | FD51: 0.0035 | FE51: 0.003 | FF51: 1千-9.99万 | FH51: 0.0035 | FI51: 0.0035 | FJ51: 0.0035 | FK51: 0.0035 | FL51: 0.0035 | FM51: 0.0035 | FN51: 0.0035 | FO51: 0.0035 | FP51: 0.0035 | FQ51: 0.0035 | FR51: 0.0035 | FS51: 0.0035 | FT51: 0.0035 | FU51: 0.013 | FV51: 0.013 | FW51: 0.013 | FX51: 0.013 | FY51: 0.015 | FZ51: 0.036 | GA51: 0.036 | GB51: 0.036 | GC51: 0.037 | GD51: 0.037 | GE51: 0.037 | GF51: 0.037 | GG51: 0.04 | GH51: 0.04 | GI51: 0.04 | GJ51: 0.04 | GK51: 0.04 | GL51: 0.04 | GM51: 0.04 | GN51: 0.04 | GO51: 0.04 | GP51: 0.03 | GQ51: 0.03 | GR51: 0.03 | GS51: 0.03 | GT51: 0.02 | GU51: 0.02 | GV51: 0.02 | GW51: 0.02 | GX51: 0.015 | GY51: 0.015 | GZ51: 0.015 | HA51: 0.015 | HB51: 0.036 | HC51: 0.035 | HD51: 0.036 | HE51: 0.036 | HF51: =C51-D51 -> 0 | HG51: 10k
B52: 1.35% 手机银行 （财富） | FB52: 1.25%个人 | FE52: 0.0035 | FF52: ≥10万 | HF52: =W52-AT52 -> 0
A53: UOB | B53: 1.20%(fresh fund) | C53: 0.012 | D53: 0.012 | E53: 0.012 | F53: 0.012 | G53: 0.012 | H53: 0.012 | I53: 0.012 | J53: 0.012 | K53: 0.012 | L53: 0.012 | M53: 0.012 | N53: 0.012 | O53: 0.012 | P53: 0.012 | Q53: 0.012 | R53: 0.012 | S53: 0.012 | T53: 0.012 | U53: 0.012 | V53: 0.012 | W53: 0.012 | X53: 0.012 | Y53: 0.012 | Z53: 0.012 | AA53: 0.012 | AB53: 0.012 | AC53: 0.012 | AD53: 0.0135 | AE53: 0.0135 | AF53: 0.015 | AG53: 0.015 | AH53: 0.0155 | AI53: 0.0155 | AJ53: 0.0165 | AK53: 0.0165 | AL53: 0.0165 | AM53: 0.0165 | AN53: 0.0175 | AO53: 0.0185 | AP53: 0.0185 | AQ53: 0.0185 | AR53: 0.02 | AS53: 0.02 | AT53: 0.02 | AU53: 0.02 | AV53: 0.02 | AW53: 0.021 | AX53: 0.021 | AY53: 0.021 | AZ53: 0.021 | BA53: 0.023 | BB53: 0.023 | BC53: 0.023 | BD53: 0.023 | BE53: 0.024 | BF53: 0.024 | BG53: 0.024 | BH53: 0.024 | BI53: 0.024 | BJ53: 0.024 | BK53: 0.024 | BL53: 0.024 | BM53: 0.024 | BN53: 0.024 | BO53: 0.024 | BP53: 0.024 | BQ53: 0.025 | BR53: 0.025 | BS53: 0.025 | BT53: 0.025 | BU53: 0.026 | BV53: 0.026 | BW53: 0.027 | BX53: 0.027 | BY53: 0.027 | BZ53: 0.027 | CA53: 0.027 | CB53: 0.027 | CC53: 0.027 | CD53: 0.027 | CE53: 0.027 | CF53: 0.027 | CG53: 0.027 | CH53: 0.027 | CI53: 0.027 | CJ53: 0.027 | CK53: 0.027 | CL53: 0.027 | CM53: 0.027 | CN53: 0.027 | CO53: 0.027 | CP53: 0.027 | CQ53: 0.027 | CR53: 0.027 | CS53: 0.027 | CT53: 0.027 | CU53: 0.027 | CV53: 0.027 | CW53: 0.027 | CX53: 0.028 | CY53: 0.028 | CZ53: 0.029 | DA53: 0.029 | DB53: 0.029 | DC53: 0.029 | DD53: 0.029 | DE53: 0.03 | DF53: 0.03 | DG53: 0.031 | DH53: 0.031 | DI53: 0.031 | DJ53: 0.031 | DK53: 0.031 | DL53: 0.031 | DM53: 0.031 | DN53: 0.031 | DO53: 0.031 | DP53: 0.031 | DQ53: 0.031 | DR53: 0.031 | DS53: 0.031 | DT53: 0.031 | DU53: 0.031 | DV53: 0.031 | DW53: 0.031 | DX53: 0.031 | DY53: 0.031 | DZ53: 0.027 | EA53: 0.027 | EB53: 0.027 | EC53: 0.027 | ED53: 0.027 | EE53: 0.027 | EF53: 0.027 | EG53: 0.027 | EH53: 0.027 | EI53: 0.027 | EJ53: 0.027 | EK53: 0.027 | EL53: 0.027 | EM53: 0.027 | EN53: 0.027 | EO53: 0.027 | EP53: 0.029 | EQ53: 0.029 | ER53: 0.031 | ES53: 0.031 | ET53: 0.032 | EU53: 0.0345 | EV53: 0.0345 | EW53: 0.0355 | EX53: 0.0355 | EY53: 0.0355 | EZ53: ≥10,000 | FZ53: 0.0395 | GA53: 0.0395 | GB53: 0.0395 | GC53: 0.0395 | GD53: 0.0395 | GE53: 0.0395 | GF53: 0.0395 | GG53: 0.0395 | GH53: 0.0395 | GI53: 0.0395 | GJ53: 0.0395 | GK53: 0.0395 | GL53: 0.0395 | GM53: 0.0395 | GN53: 0.0395 | GO53: 0.0395 | GP53: 0.0395 | GQ53: 0.0395 | HB53: 0.0395 | HC53: 0.0355 | HD53: 0.0355 | HE53: 0.0355 | HF53: =C53-D53 -> 0
A54: SingFinance | B54: 1.25%(NewFund 10k) | C54: 0.0125 | D54: 0.0125 | E54: 0.0125 | F54: 0.013 | G54: 0.013 | H54: 0.013 | I54: 0.013 | J54: 0.013 | K54: 0.013 | L54: 0.013 | M54: 0.013 | N54: 0.013 | O54: 0.013 | P54: 0.014 | Q54: 0.014 | R54: 0.014 | S54: 0.014 | T54: 0.013 | U54: 0.012 | V54: 0.012 | W54: 0.012 | X54: 0.012 | Y54: 0.012 | Z54: 0.012 | AA54: 0.012 | AB54: 0.012 | AC54: 0.0135 | AD54: 0.014 | AE54: 0.014 | AF54: 0.015 | AG54: 0.0155 | AH54: 0.0155 | AI54: 0.0155 | AJ54: 0.0165 | AK54: 0.0165 | AL54: 0.0165 | AM54: 0.0175 | AN54: 0.0175 | AO54: 0.0185 | AP54: 0.019 | AQ54: 0.02 | AR54: 0.02 | AS54: 0.02 | AT54: 0.02 | AU54: 0.02 | AV54: 0.02 | AW54: 0.02 | AX54: 0.0215 | AY54: 0.0225 | AZ54: 0.0225 | BA54: 0.024 | BB54: 0.024 | BC54: 0.025 | BD54: 0.025 | BE54: 0.026 | BF54: 0.026 | BG54: 0.026 | BH54: 0.026 | BI54: 0.026 | BJ54: 0.026 | BK54: 0.026 | BL54: 0.026 | BM54: 0.026 | BN54: 0.026 | BO54: 0.026 | BP54: 0.026 | BQ54: 0.026 | BR54: 0.0265 | BS54: 0.0265 | BT54: 0.0265 | BU54: 0.0265 | BV54: 0.0265 | BW54: 0.0265 | BX54: 0.0265 | BY54: 0.0265 | BZ54: 0.0265 | CA54: 0.0265 | CB54: 0.0265 | CC54: 0.028 | CD54: 0.028 | CE54: 0.028 | CF54: 0.029 | CG54: 0.029 | CH54: 0.0295 | CI54: 0.0295 | CJ54: 0.0295 | CK54: 0.0295 | CL54: 0.0295 | CM54: 0.0295 | CN54: 0.0295 | CO54: 0.0305 | CP54: 0.0305 | CQ54: 0.0305 | CR54: 0.0305 | CS54: 0.0305 | CT54: 0.0305 | CU54: 0.0305 | CV54: 0.0305 | CW54: 0.0305 | CX54: 0.0305 | CY54: 0.03 | CZ54: 0.03 | DA54: 0.0305 | DB54: 0.0305 | DC54: 0.0305 | DD54: 0.0305 | DE54: 0.0305 | DF54: 0.03 | DG54: 0.03 | DH54: 0.03 | DI54: 0.03 | DJ54: 0.0318 | DK54: 0.0318 | DL54: 0.0335 | DM54: 0.034 | DN54: 0.034 | DO54: 0.034 | DP54: 0.034 | DQ54: 0.034 | DR54: 0.034 | DS54: 0.033 | DT54: 0.033 | DU54: 0.033 | DV54: 0.032 | DW54: 0.03 | DX54: 0.03 | DY54: 0.03 | DZ54: 0.03 | EA54: 0.032 | EB54: 0.032 | EC54: 0.032 | ED54: 0.032 | EE54: 0.032 | EF54: 0.032 | EG54: 0.032 | EH54: 0.032 | EI54: - | EJ54: - | EK54: - | EL54: 0.03 | EM54: 0.031 | EN54: 0.031 | EO54: 0.031 | EP54: 0.031 | EQ54: 0.031 | ER54: 0.033 | ES54: 0.033 | ET54: 0.033 | EU54: 0.0345 | EV54: 0.0345 | EW54: 0.0355 | EX54: 0.0355 | EY54: 0.0355 | EZ54: ≥10,000 | FA54: - | FB54: - | FC54: ≥10,000 | FS54: 0.002 | FU54: 0.0138 | FV54: 0.0138 | FW54: 0.0138 | FX54: 0.0138 | FY54: - | FZ54: - | GA54: - | GB54: - | GC54: - | GD54: - | GE54: - | GF54: - | GG54: - | GH54: - | GI54: - | GJ54: - | GK54: - | GL54: - | GM54: - | GN54: - | GO54: - | GP54: - | GQ54: - | GR54: - | GS54: - | GT54: - | GU54: - | GV54: - | GW54: - | GX54: - | GY54: - | GZ54: - | HA54: - | HB54: - | HC54: 0.0355 | HD54: - | HE54: - | HF54: =C54-D54 -> 0
B55: 1.20%(NewFund 1k) | EZ55: ≥1,000 | HF55: =W55-AT55 -> 0
A56: Maybank | B56: 1.30% online | C56: 0.013 | D56: 0.013 | E56: 0.013 | F56: 0.013 | G56: 0.013 | H56: 0.013 | I56: 0.013 | J56: 0.013 | K56: 0.013 | L56: 0.0141 | M56: 0.0141 | N56: 0.0141 | O56: 0.0141 | P56: 0.0141 | Q56: 0.0141 | R56: 0.0155 | S56: 0.013 | T56: 0.013 | U56: 0.013 | V56: 0.0125 | W56: 0.0125 | X56: 0.012 | Y56: 0.012 | Z56: 0.012 | AA56: 0.012 | AB56: 0.012 | AC56: 0.0125 | AD56: 0.0125 | AE56: 0.0135 | AF56: 0.0145 | AG56: 0.0145 | AH56: 0.015 | AI56: 0.0161 | AJ56: 0.017 | AK56: 0.017 | AL56: 0.017 | AM56: 0.0175 | AN56: 0.0175 | AO56: 0.0175 | AP56: 0.0175 | AQ56: 0.0189 | AR56: 0.0205 | AS56: 2.45% savings bundle(EIR=2.25%) | AT56: 2.45% savings bundle(EIR=2.25%) | AU56: 2.45% savings bundle(EIR=2.25%) | AV56: 2.45% savings bundle(EIR=2.25%) | AW56: 2.45% savings bundle(EIR=2.25%) | AX56: 2.9% savings bundle(EIR=2.66%) | AY56: 2.9% savings bundle(EIR=2.66%) | AZ56: 2.9% savings bundle(EIR=2.66%) | BA56: 2.9% savings bundle(EIR=2.66%) | BB56: 2.9% savings bundle(EIR=2.66%) | BC56: 2.9% savings bundle(EIR=2.66%) | BD56: 2.9% savings bundle(EIR=2.66%) | BE56: 2.9% savings bundle(EIR=2.66%) | BF56: 2.9% savings bundle(EIR=2.66%) | BG56: 2.9% savings bundle(EIR=2.66%) | BH56: 2.9% savings bundle(EIR=2.66%) | BI56: 2.9% savings bundle(EIR=2.66%) | BJ56: 2.9% savings bundle(EIR=2.66%) | BK56: 3.05% savings bundle(EIR=2.80%) | BL56: 3.05% savings bundle(EIR=2.80%) | BM56: 3.05% savings bundle(EIR=2.80%) | BN56: 3.05% savings bundle(EIR=2.80%) | BO56: 3.05% savings bundle(EIR=2.80%) | BP56: 3.15% savings bundle(EIR=2.89%) | BQ56: 3.15% savings bundle(EIR=2.89%) | BR56: 3.15% savings bundle(EIR=2.89%) | BS56: 3.25% savings bundle(EIR=2.95%) | BT56: 3.25% savings bundle(EIR=2.95%) | BU56: 3.25% savings bundle(EIR=2.95%) | BV56: 3.25% savings bundle(EIR=2.95%) | BW56: 3.45% savings bundle(EIR=3.16%) | BX56: 3.45% savings bundle(EIR=3.16%) | BY56: 3.45% savings bundle(EIR=3.16%) | BZ56: 3.45% savings bundle(EIR=3.16%) | CA56: 3.45% savings bundle(EIR=3.16%) | CB56: 3.45% savings bundle(EIR=3.16%) | CC56: 3.55% savings bundle | CD56: 3.55% savings bundle | CE56: 3.55% savings bundle | CF56: 3.55% savings bundle | CG56: 3.55% savings bundle | CH56: 3.55% savings bundle | CI56: 3.55% savings bundle | CJ56: 0.032 | CK56: - | CL56: - | CM56: - | CN56: - | CO56: - | CP56: - | CQ56: - | CR56: - | CS56: - | CT56: - | CU56: - | CV56: - | CW56: - | CX56: - | CY56: - | CZ56: - | DA56: - | DB56: - | DC56: - | DD56: - | DE56: - | DF56: - | DG56: - | DH56: - | DI56: - | DJ56: - | DK56: - | DL56: - | DM56: - | DN56: - | DO56: - | DP56: - | DQ56: - | DR56: - | DS56: - | DT56: - | DU56: - | DV56: - | DW56: - | DX56: - | DY56: - | DZ56: - | EA56: - | EB56: - | EC56: - | ED56: - | EE56: - | EF56: - | EG56: - | EH56: - | EI56: - | EJ56: - | EK56: - | EL56: - | EM56: - | EN56: 0.03 | EO56: 0.03 | EP56: 0.03 | EQ56: 0.03 | ER56: 0.03 | ES56: 0.03 | ET56: 0.03 | EU56: 0.03 | EV56: 0.03 | EW56: 0.03 | EX56: 0.03 | EY56: 0.03 | EZ56: ≥20,000 | FZ56: 0.037 | GA56: 0.037 | GB56: 0.037 | GC56: 0.037 | GD56: 0.037 | GE56: 0.037 | GF56: 0.035 | GG56: 0.035 | GH56: 0.035 | GI56: 0.035 | GJ56: 0.035 | GK56: 0.035 | GL56: 0.035 | GM56: 0.035 | GN56: 0.035 | GO56: 0.035 | GP56: 0.028 | GQ56: 0.028 | GR56: 0.028 | GS56: 0.028 | GT56: 0.028 | GU56: 0.028 | GV56: 0.028 | GW56: 0.028 | HB56: 0.037 | HC56: 0.03 | HD56: 0.037 | HE56: 0.037 | HF56: =C56-D56 -> 0 | HG56: =(1.75%*20000+0.25%*2000)/22000 -> 0.016136364
A57: HLF | B57: 2% (7M) - s$5,000 TO s$20,000 | C57: 0.0125 | D57: 0.0125 | E57: 0.0123 | F57: 0.0123 | G57: 0.015 | H57: 0.015 | I57: 0.015 | J57: 0.015 | K57: 0.015 | L57: 0.0133 | M57: 0.013 | N57: 0.013 | O57: 0.013 | P57: 0.013 | Q57: 0.0125 | R57: 0.0125 | S57: 0.0125 | T57: 0.0125 | U57: 0.0125 | V57: 0.0128 | W57: 0.0128 | X57: 0.0128 | Y57: - | Z57: - | AA57: - | AB57: - | AC57: - | AD57: - | AE57: - | AF57: - | AG57: - | AH57: - | AI57: - | AJ57: - | AK57: - | AL57: - | AM57: - | AN57: - | AO57: - | AP57: - | AQ57: - | AR57: - | AS57: 2.05% (7M) | AT57: 2.05% (7M) | AU57: 2.05% (7M) | AV57: - | AW57: - | AX57: - | AY57: - | AZ57: - | BA57: - | BB57: - | BC57: - | BD57: - | BE57: 2.65%（电子银行） | BF57: 2.65%（电子银行） | BG57: 2.65%（电子银行） | BH57: 2.65%（电子银行） | BI57: 2.65%（电子银行） | BJ57: 2.65%（电子银行） | BK57: 2.65%（电子银行） | BL57: 2.65%（电子银行） | BM57: 2.65%（电子银行）↓ | BN57: 2.75%（电子银行） | BO57: 2.75%（电子银行） | BP57: 2.75%（电子银行） | BQ57: 2.8%（电子银行） | BR57: 2.8%（电子银行） | BS57: 2.8%（电子银行） | BT57: 2.8%（电子银行） | BU57: 2.8%（电子银行） | BV57: 2.8%（电子银行） | BW57: 2.8%（电子银行） | BX57: 2.8%（电子银行） | BY57: 2.8%（电子银行） | BZ57: 2.8%（电子银行） | CA57: 2.8%（电子银行） | CB57: 3.05% （电子银行） | CC57: 3.05% （电子银行） | CD57: 0.03 | CE57: 0.03 | CF57: 0.031 | CG57: 0.031 | CH57: 0.031 | CI57: 0.0305 | CJ57: 0.029 | EZ57: 5000-20000 | HF57: =C57-D57 -> 0 | HG57: new branch open special at 1.28& p.a. for 5 months placement of min.$80K
B58: 1.28% (5M) 80k FF (branch opening special promo) | EZ58: 20000-50000
B59: 1.20% - s$5,000 to S$20,000(5M) 1.25% - s$20,000 to S$60,000(5M) 1.30(5M) 60,000 | EZ59: ≥20000
B60: 1.50%（4M/5M)$ 50,000 | HG60: Fresh fund, from 22 Jan 2026 to further notice
B61: 1.23% 20,000
B62: 1.20% - s$5,000 to S$20,000(5,6M) 1.25% - s$20,000 to S$60,000(5,6M)
A63: HSBC | B63: 0.75% personal (counter) 0.80% premier w/o wealth products (counter) 1.15% premier w wealth products (counter) | C63: 0.0075 | D63: 0.0075 | E63: 0.0075 | F63: 0.0085 | G63: 0.0085 | H63: 0.0085 | I63: 0.0085 | J63: 0.008 | K63: 0.008 | L63: 0.008 | M63: 0.008 | N63: 0.008 | O63: 0.008 | P63: 0.008 | Q63: 0.008 | R63: 0.008 | S63: 0.007 | T63: 0.007 | U63: 0.007 | V63: 0.007 | W63: 0.007 | X63: 0.007 | Y63: 0.007 | Z63: 0.007 | AA63: 0.007 | AB63: 0.007 | AC63: 0.007 | AD63: 0.007 | AE63: 0.0085 | AF63: 0.0095 | AG63: 0.0095 | AH63: 0.011 | AI63: 0.011 | AJ63: 0.011 | AK63: 0.0085 | AL63: 0.0085 | AM63: 0.0085 | AN63: 0.0105 | AO63: 0.012 | AP63: 0.012 | AQ63: 0.014 | AR63: 0.014 | AS63: 0.015 | AT63: 0.0195 | AU63: 0.015 | AV63: 0.016 | AW63: 0.016 | AX63: 0.016 | AY63: 0.019 | AZ63: 0.019 | BA63: 0.019 | BB63: 0.0235 | BC63: 0.0235 | BD63: 0.0235 | BE63: 0.0255 | BF63: 0.027 | BG63: 0.027 | BH63: 0.027 | BI63: 0.027 | BJ63: 0.0278 | BK63: 0.0278 | BL63: 0.0278 | BM63: 2.78%↑ | BN63: 0.026 | BO63: 0.026 | BP63: 0.026 | BQ63: 0.026 | BR63: 0.026 | BS63: 0.0265 | BT63: 0.0265 | BU63: 0.0265 | BV63: 0.0265 | BW63: 0.0265 | BX63: 0.0265 | BY63: 0.03 | BZ63: 0.03 | CA63: 0.03 | CB63: 0.0305 | CC63: 0.0305 | CD63: 0.0295 | CE63: 0.0295 | CF63: 0.0325 | CG63: 0.0325 | CH63: 0.0325 | CI63: 0.0325 | CJ63: 0.0335 | CK63: 0.0335 | CL63: 0.0335 | CM63: 0.0335 | CN63: 0.0335 | CO63: 0.031 | CP63: 3.2%（柜台） | EZ63: 30,000-200,000 | HF63: =C63-D63 -> 0
A64: CITI | B64: 1.15% (Citigold Client) 1.35% (Citigold Private Client) 1.40% (Citigold Private Client and Citigold 新客户) | C64: 0.0115 | D64: 0.0115 | E64: 0.0115 | G64: - | H64: - | I64: - | J64: - | K64: - | L64: - | M64: - | N64: - | O64: - | P64: - | Q64: - | R64: - | S64: - | T64: - | U64: - | V64: - | W64: - | X64: - | Y64: - | Z64: - | AA64: - | AB64: 0.0125 | AC64: 0.0125 | AD64: 0.0125 | AE64: 0.0125 | AF64: 0.014 | AG64: 0.014 | AH64: 0.014 | AI64: 0.014 | AJ64: 0.018 | AK64: 0.018 | AL64: 0.018 | AM64: 0.018 | AN64: 0.018 | AO64: 0.021 | AP64: 0.021 | AQ64: 0.021 | AR64: 0.021 | AS64: 0.02 | AT64: 0.02 | AU64: 0.02 | AV64: 0.02 | AW64: 0.02 | AX64: 0.022 | AY64: 0.022 | AZ64: 0.022 | BA64: 0.022 | BB64: 0.024 | BC64: 0.024 | BD64: 0.024 | BE64: 0.024 | BF64: 0.025 | BG64: 0.025 | BH64: 0.025 | BI64: 0.025 | BJ64: 0.024 | BK64: 0.024 | BL64: 0.024 | BM64: 0.024 | BN64: 0.024 | BO64: 0.024 | BP64: 0.024 | BQ64: 0.024 | BR64: 0.024 | BS64: 0.024 | BT64: 0.024 | BU64: 0.024 | BV64: 0.024 | BW64: 0.0245 | BX64: 0.0245 | BY64: 0.0245 | BZ64: 0.0245 | CA64: 0.0245 | CB64: 0.0255 | CC64: 0.0255 | CD64: 0.0255 | CE64: 0.0255 | CF64: 0.0265 | CG64: 0.0265 | CH64: 0.0265 | CI64: 0.0265 | CJ64: 0.0265 | CK64: 0.025 | CL64: 0.025 | CM64: 0.025 | CN64: 0.025 | CO64: 0.025 | CP64: 0.025 | CQ64: 0.025 | CR64: 0.025 | CS64: 0.025 | CT64: 0.025 | CU64: 0.025 | CV64: 0.025 | CW64: 0.03 | EZ64: 50,000-3,000,000 | HF64: =C65-D65 -> 0 | HG64: Fresh Fund 10k
HG65: Fresh Fund 10k
CX66: 0.03 | CY66: 0.03 | CZ66: 0.03 | DA66: 0.03 | DB66: 0.03 | DC66: 0.03 | DD66: 0.03 | DE66: 0.03 | DF66: 0.03 | DG66: 0.032 | DH66: 0.032 | DI66: 0.032 | DJ66: 0.032 | DK66: 0.032 | DL66: 0.033 | DM66: 0.033 | DN66: 0.033 | DO66: 0.033 | DP66: 0.033 | DQ66: 3.5%(citi gold/private) | DR66: 3.5%(citi gold/private) | DS66: 3.5%(citi gold/private) | DT66: 3.5%(citi gold/private) | DU66: 3.5%(citi gold/private) | DV66: 3.5%(citi gold/private) | DW66: 3.45%(citi private) | DX66: 3.45%(citi private) | DY66: 3.45%(citi private) | DZ66: 3.1%(citi private) | EA66: - | EB66: - | EC66: - | ED66: - | EE66: 0.034 | EF66: 0.034 | EG66: 0.034 | EH66: 0.034 | EI66: 0.034 | EJ66: 0.0348 | EK66: 0.0348 | EL66: 0.0348 | EM66: 0.0348 | EN66: 0.0348 | EO66: 0.0348 | EP66: 0.0348 | EQ66: 0.0348 | ER66: 0.0348 | HG66: 10k-50k
A67: OCBC（5M） | B67: 3.10% (CPF Time Deposit) | W67: 0.031 | X67: 0.031 | Y67: 0.031 | Z67: 0.031 | AA67: 0.031 | AB67: 0.031 | AC67: 0.031 | AD67: 0.031 | AE67: 0.031 | AF67: 0.031 | AG67: 0.031 | AH67: 0.031 | AI67: 0.031 | AJ67: 0.031 | AK67: 0.031 | AL67: 0.031 | AM67: 0.031 | AN67: 0.031 | AO67: 0.031 | AP67: 0.031 | AQ67: 0.031 | AR67: 0.031 | AS67: 0.031 | AT67: 0.031 | AU67: 0.031 | AV67: 0.031 | AW67: 0.031 | AX67: 0.031 | AY67: 0.031 | AZ67: 0.031 | BA67: 0.031 | BB67: 0.031 | BC67: 0.031 | BD67: 0.031 | BE67: 0.031 | BF67: 0.031 | BG67: 0.031 | BH67: 0.031 | BI67: 0.031 | BJ67: 0.031 | BK67: 0.031 | BL67: 0.031 | BM67: 0.031 | BN67: 0.031 | BO67: 0.031 | BP67: 0.031 | BQ67: 0.031 | BR67: 0.031 | BS67: 0.031 | BT67: 0.031 | BU67: 0.031 | BV67: 0.031 | BW67: 0.031 | BX67: 0.031 | BY67: 0.031 | BZ67: 0.031 | CA67: 0.031 | CB67: 0.031 | CC67: 0.031 | CD67: 0.031 | CE67: 0.031 | CF67: 0.031 | CG67: 0.031 | CH67: 0.031 | CI67: 0.032 | CJ67: 0.032 | CK67: 0.032 | CL67: - | EZ67: ≥30,000 | HF67: -
A68: OCBC | C68: - | D68: - | E68: - | F68: - | G68: - | H68: - | I68: - | J68: - | K68: - | L68: - | M68: - | N68: - | O68: - | P68: - | Q68: - | R68: - | S68: - | T68: - | U68: - | V68: - | W68: - | X68: - | Y68: - | Z68: - | AA68: - | AB68: - | AC68: - | AD68: - | AE68: - | AF68: - | AG68: - | AH68: - | AI68: - | AJ68: - | AK68: - | AL68: - | AM68: - | AN68: - | AO68: - | AP68: - | AQ68: - | AR68: - | AS68: - | AT68: - | AU68: - | AV68: - | AW68: - | AX68: - | AY68: - | AZ68: - | BA68: - | BB68: - | BC68: - | BD68: - | BE68: 0.0245 | BF68: 0.0245 | BG68: 0.0245 | BH68: 0.0245 | BI68: 0.0245 | BJ68: 0.0245 | BK68: 0.0245 | BL68: 0.0245 | BM68: 0.0245 | BN68: 0.0245 | BO68: 0.0245 | BP68: 0.0245 | BQ68: 0.0245 | BR68: 0.0245 | BS68: 0.026 | BT68: 0.026 | BU68: 0.026 | BV68: 0.026 | BW68: 0.026 | BX68: 0.026 | BY68: 0.026 | BZ68: 0.026 | CA68: 0.026 | CB68: 0.028 | CC68: 0.029 | CD68: 0.029 | CE68: 0.029 | CF68: 0.029 | CG68: 0.029 | CH68: 0.029 | CI68: 0.029 | CJ68: 0.029 | CK68: 0.029 | CL68: 0.029 | CM68: 0.029 | CN68: 0.029 | CO68: 0.026 | CP68: 0.026 | CQ68: 0.026 | CR68: 0.026 | CS68: 0.028 | CT68: 0.028 | CU68: 0.028 | CV68: 0.028 | CW68: 0.028 | CX68: 0.029 | CY68: 0.029 | CZ68: 0.029 | DA68: 0.029 | DB68: 0.029 | DC68: 0.029 | DD68: 0.03 | DE68: 0.03 | DF68: 0.03 | DG68: 0.03 | DH68: 0.031 | DI68: 0.031 | DJ68: 0.031 | DK68: 0.031 | DL68: 0.031 | DM68: 0.031 | DN68: 0.031 | DO68: 0.031 | DP68: 0.031 | DQ68: 0.031 | DR68: 0.031 | DS68: 0.027 | DT68: 0.027 | DU68: 0.027 | DV68: 0.027 | DW68: 0.027 | DX68: 0.027 | DY68: 0.027 | DZ68: 0.027 | EA68: 0.027 | EB68: 0.027 | EC68: 0.027 | ED68: 0.027 | EE68: 0.027 | EF68: 0.027 | EG68: 0.027 | EH68: 0.027 | EI68: 0.027 | EJ68: 0.027 | EK68: 0.027 | EL68: 0.027 | EM68: 0.027 | EN68: 0.027 | EO68: 0.027 | EP68: 0.027 | EQ68: 0.03 | ER68: 0.032 | ES68: 0.032 | ET68: 0.033 | EU68: 0.033 | EV68: 0.034 | EW68: 0.034 | EX68: 0.034 | EY68: 0.035 | EZ68: ≥30,000 | FZ68: 3.55% (5M) | GA68: 3.55% (5M) | GB68: 3.55% (5M) | HB68: 3.55% (5M) | HC68: 0.035 | HD68: 0.035 | HE68: 3.55% (5M) | HF68: -
A70: HLB | B70: 1.50%(Online S$10K) 1.45%(Branch S$100K) | C70: 0.015 | D70: 0.015 | E70: 0.015 | F70: 0.015 | G70: 0.015 | H70: 0.015 | J70: 0.016 | K70: 0.016 | M70: - | N70: - | O70: 0.015 | P70: 0.015 | Q70: 0.0135 | W70: - | X70: - | Y70: - | Z70: - | AA70: - | AB70: - | AC70: - | AD70: - | AE70: - | AF70: - | AG70: - | AH70: - | AI70: - | AJ70: - | AK70: - | AL70: - | AM70: - | AN70: - | AO70: - | AP70: - | AQ70: - | AR70: - | AS70: - | AT70: - | AU70: - | AV70: - | AW70: - | AX70: - | AY70: 0.028 | AZ70: 0.028 | BA70: 0.028 | BB70: 0.028 | BC70: 0.028 | BD70: 0.028 | BE70: 0.028 | BF70: - | EZ70: >=100,000 | HF70: =C70-D70 -> 0 | HG70: 2 - 30 Apr 2026
A71: 9 Months
A72: 日期 | C72: =C3 -> 46099 | D72: =D3 -> 46092 | E72: =E3 -> 46085 | F72: =F3 -> 46078 | G72: =G3 -> 46071 | H72: =H3 -> 46064 | I72: 46057 | J72: =J3 -> 46050 | K72: =K3 -> 46043 | L72: =L3 -> 46036 | M72: =M3 -> 46029 | N72: =N3 -> 46022 | O72: =O3 -> 46015 | P72: =P3 -> 46008 | Q72: =Q3 -> 46001 | ... AF72: =AF3 -> 45896 | AG72: 45889 | AH72: 45882 | AI72: 45875 | AJ72: 45868 | AK72: 45861 | AL72: 45854 | AM72: 45847 | AN72: 45840 | AO72: =AO3 -> 45833 | AP72: 45826 | AQ72: =AQ3 -> 45819 | AR72: =AR3 -> 45812 | AS72: =AS3 -> 45805 | AT72: =AT3 -> 45798 | AU72: =AU3 -> 45792 | AV72: =AV3 -> 45785 | AW72: =AW3 -> 45777 | AX72: =AX3 -> 45771 | ... EH72: =EH3 -> 45148 | EI72: 45141 | EJ72: 45134 | EK72: 45127 | EL72: 45120 | EM72: 45113 | EN72: 45105 | EO72: 45099 | EP72: 45092 | EQ72: 45085 | ER72: 45076 | ES72: 45070 | ET72: 45063 | EU72: 45056 | EV72: 45049 | EW72: 45042 | EX72: 45035 | EY72: 45028 | FA72: 44803 | FD72: 44706 | FH72: 5月6日 | FI72: 44685 | FJ72: 44699 | FK72: 44690 | FL72: 44713 | FM72: 44720 | FN72: 44727 | FO72: 44733 | FP72: 44741 | FQ72: 44755 | FR72: 44748 | FS72: 44769 | FT72: 44762 | FU72: 44783 | FV72: 44776 | FW72: 44797 | FX72: 44790 | FY72: 44805 | FZ72: 45000 | GA72: 44993 | GB72: 44986 | GC72: 44979 | GD72: 44972 | GE72: 44965 | GF72: 44958 | GG72: 44951 | GH72: 44944 | GI72: 44937 | GJ72: 44930 | GK72: 44923 | GL72: 44916 | GM72: 44910 | GN72: 44902 | GO72: 44896 | GP72: 44888 | GQ72: 44881 | GR72: 44874 | GS72: 44868 | GT72: 44860 | GU72: 44853 | GV72: 44846 | GW72: 44839 | GX72: 44831 | GY72: 44825 | GZ72: 44818 | HA72: 44811 | HB72: 45002 | HC72: 45020 | HD72: 45014 | HE72: 45008
B73: 全部公开报价 | C73: 当日最高报价 | D73: 当日最高报价 | E73: 当日最高报价 | F73: 当日最高报价 | G73: 当日最高报价 | H73: 当日最高报价 | I73: 当日最高报价 | J73: 当日最高报价 | K73: 当日最高报价 | L73: 当日最高报价 | M73: 当日最高报价 | N73: 当日最高报价 | O73: 当日最高报价 | P73: 当日最高报价 | Q73: 当日最高报价 | R73: 当日最高报价 | S73: 当日最高报价 | T73: 当日最高报价 | U73: 当日最高报价 | V73: 当日最高报价 | W73: 当日最高报价 | X73: 当日最高报价 | Y73: 当日最高报价 | Z73: 当日最高报价 | AA73: 当日最高报价 | AB73: 当日最高报价 | AC73: 当日最高报价 | AD73: 当日最高报价 | AE73: 当日最高报价 | AF73: 当日最高报价 | AG73: 当日最高报价 | AH73: 当日最高报价 | AI73: 当日最高报价 | AJ73: 当日最高报价 | AK73: 当日最高报价 | AL73: 当日最高报价 | AM73: 当日最高报价 | AN73: 当日最高报价 | AO73: 当日最高报价 | AP73: 当日最高报价 | AQ73: 当日最高报价 | AR73: 当日最高报价 | AS73: 当日最高报价 | AT73: 当日最高报价 | AU73: 当日最高报价 | AV73: 当日最高报价 | AW73: 当日最高报价 | AX73: 当日最高报价 | AY73: 当日最高报价 | AZ73: 当日最高报价 | BA73: 当日最高报价 | BB73: 当日最高报价 | BC73: 当日最高报价 | BD73: 当日最高报价 | BE73: 当日最高报价 | BF73: 当日最高报价 | BG73: 当日最高报价 | BH73: 当日最高报价 | BI73: 当日最高报价 | BJ73: 当日最高报价 | BK73: 当日最高报价 | BL73: 当日最高报价 | BM73: 当日最高报价 | BN73: 当日最高报价 | BO73: 当日最高报价 | BP73: 当日最高报价 | BQ73: 当日最高报价 | BR73: 当日最高报价 | BS73: 当日最高报价 | BT73: 当日最高报价 | BU73: 当日最高报价 | BV73: 当日最高报价 | BW73: 当日最高报价 | BX73: 当日最高报价 | BY73: 当日最高报价 | BZ73: 当日最高报价 | CA73: 当日最高报价 | CB73: 当日最高报价 | CC73: 当日最高报价 | CD73: 当日最高报价 | CE73: 当日最高报价 | CF73: 当日最高报价 | CG73: 当日最高报价 | CH73: 当日最高报价 | CI73: 当日最高报价 | CJ73: 当日最高报价 | CK73: 当日最高报价 | CL73: 当日最高报价 | CM73: 当日最高报价 | CN73: 当日最高报价 | CO73: 当日最高报价 | CP73: 当日最高报价 | CQ73: 当日最高报价 | CR73: 当日最高报价 | CS73: 当日最高报价 | CT73: 当日最高报价 | CU73: 当日最高报价 | CV73: 当日最高报价 | CW73: 当日最高报价 | CX73: 当日最高报价 | CY73: 当日最高报价 | CZ73: 当日最高报价 | DA73: 当日最高报价 | DB73: 当日最高报价 | DC73: 当日最高报价 | DD73: 当日最高报价 | DE73: 当日最高报价 | DF73: 当日最高报价 | DG73: 当日最高报价 | DH73: 当日最高报价 | DI73: 当日最高报价 | DJ73: 当日最高报价 | DK73: 当日最高报价 | DL73: 当日最高报价 | DM73: 当日最高报价 | DN73: 当日最高报价 | DO73: 当日最高报价 | DP73: 当日最高报价 | DQ73: 当日最高报价 | DR73: 当日最高报价 | DS73: 当日最高报价 | DT73: 当日最高报价 | DU73: 当日最高报价 | DV73: 当日最高报价 | DW73: 当日最高报价 | DX73: 当日最高报价 | DY73: 当日最高报价 | DZ73: 当日最高报价 | EA73: 当日最高报价 | EB73: 当日最高报价 | EC73: 当日最高报价 | ED73: 当日最高报价 | EE73: 当日最高报价 | EF73: 当日最高报价 | EG73: 当日最高报价 | EH73: 当日最高报价 | EI73: 当日最高报价 | EJ73: 当日最高报价 | EK73: 当日最高报价 | EL73: 当日最高报价 | EM73: 当日最高报价 | EN73: 当日最高报价 | EO73: 当日最高报价 | EP73: 当日最高报价 | EQ73: 当日最高报价 | ER73: 当日最高报价 | ES73: 当日最高报价 | ET73: 当日最高报价 | EU73: 当日最高报价 | EV73: 当日最高报价 | EW73: 当日最高报价 | EX73: 当日最高报价 | EY73: 当日最高报价 | EZ73: 金额 | FA73: 当日最高报价 | FB73: 全部公开报价 | FC73: 金额 | FD73: 当日最高报价 | FE73: 全部公开报价 | FF73: 金额 | FG73: 挂牌利率/促销利率 | FH73: 当日最高报价 | FI73: 当日最高报价 | FJ73: 当日最高报价 | FK73: 当日最高报价 | FL73: 当日最高报价 | FM73: 当日最高报价 | FN73: 当日最高报价 | FO73: 当日最高报价 | FP73: 当日最高报价 | FQ73: 当日最高报价 | FR73: 当日最高报价 | FS73: 当日最高报价 | FT73: 当日最高报价 | FU73: 当日最高报价 | FV73: 当日最高报价 | FW73: 当日最高报价 | FX73: 当日最高报价 | FY73: 当日最高报价 | FZ73: 当日最高报价 | GA73: 当日最高报价 | GB73: 当日最高报价 | GC73: 当日最高报价 | GD73: 当日最高报价 | GE73: 当日最高报价 | GF73: 当日最高报价 | GG73: 当日最高报价 | GH73: 当日最高报价 | GI73: 当日最高报价 | GJ73: 当日最高报价 | GK73: 当日最高报价 | GL73: 当日最高报价 | GM73: 当日最高报价 | GN73: 当日最高报价 | GO73: 当日最高报价 | GP73: 当日最高报价 | GQ73: 当日最高报价 | GR73: 当日最高报价 | GS73: 当日最高报价 | GT73: 当日最高报价 | GU73: 当日最高报价 | GV73: 当日最高报价 | GW73: 当日最高报价 | GX73: 当日最高报价 | GY73: 当日最高报价 | GZ73: 当日最高报价 | HA73: 当日最高报价 | HB73: 当日最高报价 | HC73: 当日最高报价 | HD73: 当日最高报价 | HE73: 当日最高报价 | HF73: 当日最高报价变动
A74: ICBC | B74: 1.00%（online） | C74: 0.0105 | D74: 0.0105 | E74: 0.0105 | F74: 0.0105 | G74: 0.0105 | H74: 0.0105 | I74: 0.0105 | J74: 0.0105 | K74: 0.0105 | L74: 0.0105 | M74: 0.0115 | N74: 0.0115 | O74: 0.0115 | P74: 0.0115 | Q74: 0.0115 | R74: 0.0115 | S74: 0.0115 | T74: 0.0115 | U74: 0.0115 | V74: 0.0115 | W74: 0.0115 | X74: 0.0115 | Y74: 0.0115 | Z74: 0.0115 | AA74: 0.0115 | AB74: 0.0115 | AC74: 0.0115 | AD74: 0.0125 | AE74: 0.0125 | AF74: 0.014 | AG74: 0.014 | AH74: 0.0145 | AI74: 0.0155 | AJ74: 0.0155 | AK74: 0.0165 | AL74: 0.0165 | AM74: 0.018 | AN74: 0.018 | AO74: 0.018 | AP74: 0.018 | AQ74: 0.02 | AR74: 2.15%（电子银行） | AS74: 2.15%（电子银行） | AT74: =#REF! -> #REF! | AU74: 2.25%（电子银行） | AV74: 2.25%（电子银行） | AW74: 2.25%（电子银行） | AX74: 2.25%（电子银行） | AY74: 2.25%（电子银行） | AZ74: 2.40%电子/2.40%柜台 | BA74: 2.40%电子/2.40%柜台 | BB74: =BC74 -> 2.70%（电子银行） | BC74: =BD74 -> 2.70%（电子银行） | BD74: =BE74 -> 2.70%（电子银行） | BE74: =BF74 -> 2.70%（电子银行） | BF74: =BG74 -> 2.70%（电子银行） | BG74: =BH74 -> 2.70%（电子银行） | BH74: =BI74 -> 2.70%（电子银行） | BI74: =BJ74 -> 2.70%（电子银行） | ... CB74: =CC74 -> 2.70%（电子银行） | CC74: 2.70%（电子银行） | CD74: 0.028 | CE74: 0.029 | CF74: 0.029 | CG74: 0.029 | CH74: 0.0295 | CI74: 0.03 | CJ74: 0.03 | CK74: 0.03 | CL74: 0.0305 | CM74: 0.0305 | CN74: 0.0305 | CO74: 0.0305 | CP74: 0.0305 | CQ74: 0.0305 | CR74: 0.0305 | CS74: 0.0305 | CT74: 0.0305 | CU74: 0.0305 | CV74: 0.0305 | CW74: 0.031 | CX74: 0.031 | CY74: 0.031 | CZ74: 0.031 | DA74: 0.031 | DB74: 0.031 | DC74: 0.031 | DD74: 0.031 | DE74: 0.031 | DF74: 0.031 | DG74: 0.031 | DH74: 0.031 | DI74: 0.031 | DJ74: 0.031 | DK74: 0.031 | DL74: 0.031 | DM74: 0.031 | DN74: 0.031 | DO74: 0.031 | DP74: 0.031 | DQ74: 0.031 | DR74: 0.031 | DS74: 0.031 | DT74: 0.032 | DU74: 0.032 | DV74: 0.032 | DW74: 0.032 | DX74: 0.032 | DY74: 0.032 | DZ74: 0.032 | EA74: 0.032 | EB74: 0.032 | EC74: 0.032 | ED74: 0.032 | EE74: 0.032 | EF74: 0.032 | EG74: 0.032 | EH74: 0.032 | EI74: 0.032 | EJ74: 0.032 | EK74: 0.033 | EL74: 0.033 | EM74: 0.0335 | EN74: 0.0335 | EO74: 0.0335 | EP74: 0.0335 | EQ74: 0.034 | ER74: 0.034 | ES74: 0.034 | ET74: 0.0345 | EU74: 0.035 | EV74: 0.035 | EW74: 0.036 | EX74: 0.0325 | EY74: 0.0325 | EZ74: ≥20,000 | FA74: 0.0125 | FB74: 1.25% 电子银行 | FC74: ≥500 | FD74: 0.0125 | FE74: 1.2% 柜面 | FF74: ≥500 | FG74: 促销 | FH74: 0.0055 | FI74: 0.0055 | FJ74: 0.0055 | FK74: 0.0055 | FL74: 0.0125 | FM74: 0.0125 | FN74: 0.0125 | FO74: 0.0125 | FP74: 0.0125 | FQ74: 0.0125 | FR74: 0.0125 | FS74: 0.0125 | FT74: 0.0125 | FU74: 0.0125 | FV74: 0.0125 | FW74: 0.0125 | FX74: 0.0125 | FY74: 0.019 | FZ74: 0.0325 | GA74: 0.0325 | GB74: 0.0325 | GC74: 0.0325 | GD74: 0.0325 | GE74: 0.0325 | GF74: 0.0325 | GG74: 0.0325 | GH74: 0.0325 | GI74: 0.0325 | GJ74: 0.0325 | GK74: 0.0325 | GL74: 0.0325 | GM74: 0.0325 | GN74: 0.0325 | GO74: 0.0325 | GP74: 0.0325 | GQ74: 0.0325 | GR74: 0.0325 | GS74: 0.03 | GT74: 0.03 | GU74: 0.03 | GV74: 0.0245 | GW74: 0.0245 | GX74: 0.0245 | GY74: 0.021 | GZ74: 0.021 | HA74: 0.021 | HB74: 0.0325 | HC74: 0.0325 | HD74: 0.0325 | HE74: 0.0325 | HF74: =C74-D74 -> 0 | HG74: 500-20k
B75: 1.05%（online）>200k | HG75: >200k
A76: BOC | B76: $500手机银行 | C76: 0.012 | D76: 0.012 | E76: 0.012 | F76: 0.012 | G76: 0.012 | H76: 0.012 | I76: 0.012 | J76: 0.012 | K76: 0.012 | L76: 0.012 | M76: 0.012 | N76: 0.012 | O76: 0.012 | P76: 0.012 | Q76: 0.012 | R76: 0.012 | S76: 0.012 | T76: 0.012 | U76: 0.012 | V76: 0.0125 | W76: 0.0125 | X76: 0.0125 | Y76: 0.0125 | Z76: 0.0125 | AA76: 0.0118 | AB76: 0.0118 | AC76: 0.0125 | AD76: 0.0135 | AE76: 0.014 | AF76: 0.0145 | AG76: 0.015 | AH76: 0.016 | AI76: 0.016 | AJ76: 0.0155 | AK76: 0.016 | AL76: 0.017 | AM76: 0.0175 | AN76: 0.0175 | AO76: 0.019 | AP76: 0.019 | AQ76: 0.0195 | AR76: 0.02 | AS76: 0.0215 | AT76: 0.0215 | AU76: 0.022 | AV76: 0.0225 | AW76: 0.0235 | AX76: 0.024 | AY76: 0.0245 | AZ76: 0.024 | BA76: 0.024 | BB76: 0.0245 | BC76: 0.0245 | BD76: 0.0255 | BE76: 0.0265 | BF76: 0.027 | BG76: 0.027 | BH76: 0.027 | BI76: 0.027 | BJ76: 0.027 | BK76: 0.026 | BL76: 0.026 | BM76: 0.026 | BN76: 0.026 | BO76: 0.026 | BP76: 0.0255 | BQ76: 0.0255 | BR76: 0.0255 | BS76: 0.0255 | BT76: 0.0255 | BU76: 0.0255 | BV76: 0.0255 | BW76: 0.026 | BX76: 0.026 | BY76: 0.027 | BZ76: 0.027 | CA76: 0.027 | CB76: 0.028 | CC76: 0.028 | CD76: 0.028 | CE76: 0.028 | CF76: 0.029 | CG76: 0.029 | CH76: 0.029 | CI76: 0.0295 | CJ76: 0.03 | CK76: 0.03 | CL76: 0.0305 | CM76: 0.0305 | CN76: 0.0305 | CO76: 0.0305 | CP76: 0.0305 | CQ76: 0.0305 | CR76: 0.0305 | CS76: 0.0305 | CT76: 0.0305 | CU76: 0.0305 | CV76: 0.031 | CW76: 0.031 | CX76: 0.031 | CY76: 0.031 | CZ76: 0.0315 | DA76: 0.0315 | DB76: 0.032 | DC76: 0.032 | DD76: 0.032 | DE76: 0.032 | DF76: 0.032 | DG76: 0.032 | DH76: 0.032 | DI76: 0.032 | DJ76: 0.033 | DK76: 0.0335 | DL76: 0.0335 | DM76: 0.0335 | DN76: 0.0335 | DO76: 0.0335 | DP76: 0.0335 | DQ76: 0.0335 | DR76: 0.033 | DS76: 0.033 | DT76: 0.032 | DU76: 0.032 | DV76: 0.032 | DW76: 0.032 | DX76: 0.032 | DY76: 0.032 | DZ76: 0.032 | EA76: 0.0325 | EB76: 0.0325 | EC76: 0.0325 | ED76: 0.0325 | EE76: 0.0325 | EF76: 0.0325 | EG76: 0.0325 | EH76: 0.033 | EI76: 0.033 | EJ76: 0.033 | EK76: 0.033 | EL76: 0.033 | EM76: 0.033 | EN76: 0.033 | EO76: 0.033 | EP76: 0.033 | EQ76: 0.034 | ER76: 0.034 | ES76: 0.034 | ET76: 0.0345 | EU76: 0.035 | EV76: 0.035 | EW76: 0.0355 | EX76: 0.0365 | EY76: 0.037 | EZ76: ≥10,000 | FY76: 0.021 | FZ76: 0.038 | GA76: 0.038 | GB76: 0.038 | GC76: 0.038 | GD76: 0.0385 | GE76: 0.0385 | GF76: 0.04 | GG76: 0.04 | GH76: 0.04 | GI76: 0.04 | GJ76: 0.04 | GK76: 0.04 | GL76: 0.04 | GM76: 0.04 | GN76: 0.04 | GO76: 0.039 | GP76: 0.0385 | GQ76: 0.036 | GR76: 0.0325 | GS76: 0.0325 | GT76: 0.031 | GU76: 0.031 | GV76: 0.0295 | GW76: 0.027 | GX76: 0.0265 | GY76: 0.0245 | GZ76: 0.0245 | HA76: 0.0245 | HB76: 0.038 | HC76: 0.037 | HD76: 0.0375 | HE76: 0.038 | HF76: =C76-D76 -> 0
EZ77: ≥500 | FA77: 0.021 | FB77: 0.021 | FC77: ≥5,000 | FD77: 0.009 | FE77: 0.009 | FF77: ≥5千 | FG77: 促销 | FH77: 0.0055 | FI77: 0.0055 | FJ77: 0.009 | FK77: 0.0055 | FL77: 0.009 | FM77: 0.009 | FN77: 0.009 | FO77: 0.009 | FP77: 0.012 | FQ77: 0.013 | FR77: 0.013 | FS77: 0.013 | FT77: 0.013 | FU77: 0.017 | FV77: 0.017 | FW77: 0.019 | FX77: 0.019
A78: CIMB | B78: 1.10% 手机银行 （个人） | C78: 0.011 | D78: 0.011 | E78: 0.011 | F78: 0.011 | G78: 0.011 | H78: 0.011 | I78: 0.011 | J78: 0.011 | K78: 0.011 | L78: 0.011 | M78: 0.011 | N78: 0.011 | O78: 0.011 | P78: 0.011 | Q78: 0.011 | R78: 0.011 | S78: 0.011 | T78: 0.011 | U78: 0.011 | V78: 0.011 | W78: 0.011 | X78: 0.011 | Y78: 0.011 | Z78: 0.011 | AA78: 0.011 | AB78: 0.011 | AC78: 0.011 | AD78: 0.011 | AE78: 0.0115 | AF78: 0.012 | AG78: 0.0135 | AH78: 0.0135 | AI78: 0.0135 | AJ78: 0.014 | AK78: 0.014 | AL78: 0.014 | AM78: 0.0145 | AN78: 0.0155 | AO78: 0.017 | AP78: 0.018 | AQ78: 0.019 | AR78: 0.019 | AS78: 0.0195 | AT78: 0.0195 | AU78: 0.019 | AV78: 0.0195 | AW78: 0.0195 | AX78: 0.0205 | AY78: 0.0205 | AZ78: 0.0205 | BA78: 0.0205 | BB78: 0.0215 | BC78: 0.0215 | BD78: 0.0215 | BE78: 0.023 | BF78: 0.0245 | BG78: 0.0245 | BH78: 0.0245 | BI78: 0.0245 | BJ78: 0.026 | BK78: 0.026 | BL78: 0.026 | BM78: 0.026 | BN78: 0.026 | BO78: 0.026 | BP78: 0.026 | BQ78: 0.026 | BR78: 0.026 | BS78: 0.026 | BT78: 0.026 | BU78: 0.026 | BV78: 0.026 | BW78: 0.026 | BX78: 0.026 | BY78: 0.026 | BZ78: 0.026 | CA78: 0.026 | CB78: 0.026 | CC78: 0.027 | CD78: 0.027 | CE78: 0.027 | CF78: 0.028 | CG78: 0.028 | CH78: 0.0305 | CI78: 0.0305 | CJ78: 0.0305 | CK78: 0.0305 | CL78: 0.0305 | CM78: 0.0305 | CN78: 0.0305 | CO78: 0.0335 | CP78: 0.033 | CQ78: 0.033 | CR78: 0.0325 | CS78: 0.0325 | CT78: 0.0325 | CU78: 0.0325 | CV78: 0.0325 | CW78: 0.031 | CX78: 0.031 | CY78: 0.031 | CZ78: 0.031 | DA78: 0.032 | DB78: 0.032 | DC78: 0.032 | DD78: 0.032 | DE78: 0.034 | DF78: 0.034 | DG78: 0.034 | DH78: 0.034 | DI78: 0.034 | DJ78: 0.034 | DK78: 0.034 | DL78: 0.034 | DM78: 0.034 | DN78: 0.034 | DO78: 0.034 | DP78: 0.034 | DQ78: 0.034 | DR78: 0.034 | DS78: 0.034 | DT78: 0.034 | DU78: 0.034 | DV78: 0.034 | DW78: 0.034 | DX78: 0.034 | DY78: 0.034 | DZ78: 0.034 | EA78: 0.034 | EB78: 0.034 | EC78: 0.034 | ED78: 0.034 | EE78: 0.036 | EF78: 0.036 | EG78: 0.036 | EH78: 0.036 | EI78: 0.036 | EJ78: 0.034 | EK78: 0.034 | EL78: 0.034 | EM78: 0.034 | EN78: 0.034 | EO78: 0.034 | EP78: 0.034 | EQ78: 0.034 | ER78: 0.035 | ES78: 0.035 | ET78: 0.035 | EU78: 0.035 | EV78: 0.035 | EW78: 0.035 | EX78: 0.035 | EY78: 0.035 | EZ78: ≥10,000 | FA78: 0.013 | FB78: 1.30%财富 | FC78: ≥10,000 | FD78: 0.0035 | FE78: 0.003 | FF78: 1千-9.99万 | FH78: 0.0035 | FI78: 0.0035 | FJ78: 0.0035 | FK78: 0.0035 | FL78: 0.0035 | FM78: 0.0035 | FN78: 0.0035 | FO78: 0.0035 | FP78: 0.0035 | FQ78: 0.0035 | FR78: 0.0035 | FS78: 0.0035 | FT78: 0.0035 | FU78: 0.013 | FV78: 0.013 | FW78: 0.013 | FX78: 0.013 | FY78: 0.015 | FZ78: 0.035 | GA78: 0.035 | GB78: 0.035 | GC78: 0.035 | GD78: 0.035 | GE78: 0.035 | GF78: 0.035 | GG78: 0.041 | GH78: 0.041 | GI78: 0.041 | GJ78: 0.041 | GK78: 0.041 | GL78: 0.041 | GM78: 0.041 | GN78: 0.041 | GO78: 0.041 | GP78: 0.032 | GQ78: 0.032 | GR78: 0.032 | GS78: 0.032 | GT78: 0.021 | GU78: 0.021 | GV78: 0.021 | GW78: 0.021 | GX78: 0.016 | GY78: 0.016 | GZ78: 0.016 | HA78: 0.016 | HB78: 0.035 | HC78: 0.035 | HD78: 0.035 | HE78: 0.035 | HF78: =C78-D78 -> 0 | HG78: 10k
B79: 1.15% 手机银行 （财富） | FB79: 1.25%个人 | FE79: 0.0035 | FF79: ≥10万
A80: HLF | B80: 1.20% - s$5,000 to S$20,000 1.20% - s$20,000 and above | C80: 0.012 | D80: 0.012 | E80: 0.0125 | F80: 0.0125 | G80: 0.0125 | H80: 0.0125 | I80: 0.0125 | J80: 0.0125 | K80: 0.0133 | L80: 0.0133 | M80: 0.0125 | N80: 0.0125 | O80: 0.0125 | P80: 0.0125 | Q80: 0.0125 | R80: 0.012 | S80: 0.012 | T80: 0.012 | U80: 0.012 | V80: 0.011 | W80: 0.011 | X80: 0.011 | Y80: 0.011 | Z80: 0.011 | AA80: 0.012 | AB80: 0.012 | AC80: 0.012 | AD80: 0.012 | AE80: 0.012 | AF80: 0.0142 | AG80: 0.0142 | AH80: 0.0165 | AI80: 0.0165 | AJ80: 0.0165 | AK80: 0.0165 | AL80: 0.016 | AM80: 0.016 | AN80: 1.83%(10M) | AO80: 1.83%(10M) | AP80: 0.0183 | AQ80: 0.0183 | AR80: 0.0183 | AS80: 0.0185 | AT80: 1.85% (10M) | AU80: 1.85% (10M) | AV80: 0.022 | AW80: 0.022 | AX80: 0.022 | AY80: 0.023 | AZ80: 0.023 | BA80: 0.0245 | BB80: 0.0245 | BC80: 0.0255 | BD80: 0.0255 | BE80: 0.0255 | BF80: 0.0255 | BG80: 0.0255 | BH80: - | BI80: - | BJ80: - | BK80: - | BL80: - | BM80: - | BN80: - | BO80: - | BP80: - | BQ80: - | BR80: - | BS80: - | BT80: - | BU80: - | BV80: - | BW80: - | BX80: - | BY80: - | BZ80: - | CA80: - | CB80: - | CC80: - | CD80: - | CE80: - | CF80: - | CG80: - | CH80: - | CI80: - | CJ80: 0.028 | CK80: 0.028 | CL80: 0.028 | CM80: 0.028 | CN80: 0.028 | CO80: 0.028 | CP80: 0.028 | CQ80: 0.028 | CR80: 0.028 | CS80: 0.028 | CT80: 0.028 | CU80: 0.028 | CV80: 0.028 | CW80: 0.029 | CX80: 2.9% (9M&10M) | CY80: 2.9% (9M&10M) | CZ80: 2.9% (9M&10M) | DA80: 0.03 | DB80: 3.00%(10M) | DC80: 3.00%(10M) | DD80: 3.00%(10M) | DE80: 3.00%(8M) | DF80: 3.00%(8M) | DG80: 3.00%(8M) | DH80: 3.00%(8M) | DI80: 0.031 | DJ80: 0.031 | DK80: 0.031 | DL80: 0.031 | DM80: 0.033 | DN80: 0.033 | DO80: 0.033 | DP80: 0.033 | DQ80: 0.033 | DR80: 0.0335 | DS80: 0.0335 | DT80: 0.0335 | DU80: 0.0335 | DV80: 0.032 | DW80: 0.032 | DX80: 0.032 | DY80: - | DZ80: 3.1%（8M） | EA80: 3.1%（8M） | EB80: 3.1%（8M） | EC80: 0.031 | ED80: 0.0305 | EE80: - | EF80: - | EG80: - | EH80: - | EI80: 0.0305 | EJ80: 0.0305 | EK80: 0.0305 | EL80: 0.0305 | EM80: 0.0328 | EN80: 0.0328 | EO80: 0.0328 | EP80: 0.0328 | EQ80: 0.0328 | ER80: 0.0315 | ES80: 0.0315 | ET80: 0.033 | EU80: 0.033 | EV80: 0.035 | EW80: 0.035 | EX80: 0.035 | EY80: 20,000-50,000 | EZ80: >=20,000 | HF80: =C80-D80 -> 0
B81: 1.33% >50,000(8M) | EY81: ≥50,000 | EZ81: 5000-20000
A82: HLB | B82: 1.30%(Online S$10K) 1.30%(Others S$100K) | C82: - | D82: - | E82: - | F82: - | G82: - | H82: - | I82: - | J82: - | K82: - | L82: - | M82: - | O82: 0.013 | P82: 0.013 | Q82: 0.013 | R82: 0.013 | S82: 0.013 | T82: 0.013 | U82: 0.013 | HF82: =C82-D82 -> #VALUE! | HG82: 10k
A83: Maybank | B83: 1.45% online E.I.R 1.32% 1.30% (branch and online) | C83: 0.0132 | D83: 0.0132 | E83: 0.0132 | F83: 0.0132 | G83: 0.0132 | H83: 0.0132 | I83: 0.0132 | J83: 0.0132 | K83: 0.0132 | L83: 0.011 | M83: 0.011 | N83: 0.011 | O83: 0.011 | P83: 0.011 | Q83: 0.011 | R83: 0.011 | S83: 0.011 | T83: 0.011 | U83: 0.011 | V83: 0.011 | W83: 0.011 | X83: 0.011 | Y83: 0.011 | Z83: 0.011 | AA83: 0.011 | AB83: 0.011 | AC83: 0.0115 | AD83: 0.0115 | AE83: 0.013 | AF83: 0.014 | AG83: 0.014 | AH83: 0.015 | AI83: 0.0157 | AJ83: 0.0166 | AK83: 0.0166 | AL83: 0.0166 | AM83: 0.0184 | AN83: 0.0184 | AO83: 0.0184 | AP83: 0.0184 | AQ83: 0.0198 | AR83: 0.0215 | AS83: 2.25% savings bundle(EIR=2.07%) | AT83: 2.25% savings bundle(EIR=2.07%) | AU83: 2.25% savings bundle(EIR=2.07%) | AV83: 2.25% savings bundle(EIR=2.07%) | AW83: 2.25% savings bundle(EIR=2.07%) | AX83: 2.70% savings bundle(EIR=2.48%) | AY83: 2.70% savings bundle(EIR=2.48%) | AZ83: 2.70% savings bundle(EIR=2.48%) | BA83: 2.70% savings bundle(EIR=2.48%) | BB83: 2.70% savings bundle(EIR=2.48%) | BC83: 2.70% savings bundle(EIR=2.48%) | BD83: 2.70% savings bundle(EIR=2.48%) | BE83: 2.70% savings bundle(EIR=2.48%) | BF83: 2.70% savings bundle(EIR=2.48%) | BG83: 2.70% savings bundle(EIR=2.48%) | BH83: 2.70% savings bundle(EIR=2.48%) | BI83: 2.70% savings bundle(EIR=2.48%) | BJ83: 2.70% savings bundle(EIR=2.48%) | BK83: 2.80% savings bundle(EIR=2.57%) | BL83: 2.80% savings bundle(EIR=2.57%) | BM83: 2.80% savings bundle(EIR=2.57%) | BN83: 2.80% savings bundle(EIR=2.57%) | BO83: 2.80% savings bundle(EIR=2.57%) | BP83: 2.90% savings bundle(EIR=2.66%) | BQ83: 2.90% savings bundle(EIR=2.66%) | BR83: 2.90% savings bundle(EIR=2.66%) | BS83: 3.10% savings bundle(EIR=2.95%) | BT83: 3.10% savings bundle(EIR=2.95%) | BU83: 3.10% savings bundle(EIR=2.95%) | BV83: 3.10% savings bundle(EIR=2.95%) | BW83: 3.25% savings bundle(EIR=2.95%) | BX83: 3.25% savings bundle(EIR=2.95%) | BY83: 3.25% savings bundle(EIR=2.95%) | BZ83: 3.25% savings bundle(EIR=2.95%) | CA83: 3.25% savings bundle(EIR=2.95%) | CB83: 3.25% savings bundle(EIR=2.95%) | CC83: 3.4% savings bundle | CD83: 3.4% savings bundle | CE83: 3.4% savings bundle | CF83: 3.4% savings bundle | CG83: 3.4% savings bundle | CH83: 3.4% savings bundle | CI83: 3.4% savings bundle | CJ83: 0.03 | CK83: 0.03 | CL83: 0.03 | CM83: 0.03 | CN83: 0.03 | CO83: 0.025 | CP83: 0.025 | CQ83: 0.025 | CR83: 0.025 | CS83: 0.025 | CT83: 0.025 | CU83: 0.025 | CV83: 0.025 | CW83: 0.025 | CX83: 0.025 | CY83: 0.025 | CZ83: 0.025 | DA83: 0.025 | DB83: 0.025 | DC83: 0.025 | DD83: 0.025 | DE83: 0.025 | DF83: 0.025 | DG83: 0.0255 | DH83: 0.0255 | DI83: 0.0255 | DJ83: 0.0255 | DK83: 0.0255 | DL83: 0.0255 | DM83: 0.0255 | DN83: 0.0255 | DO83: 0.0255 | DP83: 0.0255 | DQ83: 0.0255 | DR83: 0.0255 | DS83: 0.0255 | DT83: 0.0255 | DU83: 0.0255 | DV83: 0.0255 | DW83: 0.028 | DX83: 0.028 | DY83: 0.028 | DZ83: 0.028 | EA83: 0.028 | EB83: 0.028 | EC83: 0.029 | ED83: 0.029 | EE83: 0.029 | EF83: 0.029 | EG83: 0.029 | EH83: 0.029 | EI83: 0.029 | EJ83: 0.029 | EK83: 0.029 | EL83: 0.029 | EM83: 0.029 | EN83: 0.031 | EO83: 0.031 | EP83: 0.031 | EQ83: 0.031 | ER83: 0.031 | ES83: 0.031 | ET83: 0.031 | EU83: 0.031 | EV83: 0.031 | EW83: 0.031 | EX83: 0.031 | EY83: 0.031 | EZ83: ≥20,000 | FZ83: 3.80% (柜台) | GA83: 3.80% (柜台) | GB83: 3.80% (柜台) | GC83: 3.80% (柜台) | GD83: 3.80% (柜台) | GE83: 3.8% (柜台) | GF83: 0.036 | GG83: 0.036 | GH83: 0.036 | GI83: 0.036 | GJ83: 0.036 | GK83: 0.036 | GL83: 0.036 | GM83: 0.036 | GN83: 0.036 | GO83: 0.036 | GP83: 0.029 | GQ83: 0.029 | GR83: 0.029 | GS83: 0.029 | GT83: 0.029 | GU83: 0.029 | GV83: 0.029 | GW83: 0.029 | HB83: 3.80% (柜台) | HC83: 0.031 | HD83: 3.80% (柜台) | HE83: 3.80% (柜台) | HF83: =C83-D83 -> 0 | HG83: from 20 Jan 2026
A84: UOB | B84: 1.00% (10M) | C84: 0.01 | D84: 0.01 | E84: 0.01 | F84: 0.01 | G84: 0.01 | H84: 0.01 | I84: 0.01 | J84: 0.01 | K84: 0.01 | L84: 0.01 | M84: 0.01 | N84: 0.01 | O84: 0.01 | P84: 0.01 | Q84: 0.01 | R84: 0.01 | S84: 0.01 | T84: 0.01 | U84: 0.01 | V84: 0.01 | W84: 0.01 | X84: 0.01 | Y84: 0.01 | Z84: 0.01 | AA84: 0.01 | AB84: 0.01 | AC84: 1.0% (10M) | AD84: 1.10% (10M) | AE84: 1.10% (10M) | AF84: 1.30% (10M) | AG84: 1.30% (10M) | AH84: 1.40% (10M) | AI84: 1.40% (10M) | AJ84: 1.45% (10M) | AK84: 1.45% (10M) | AL84: 1.45% (10M) | AM84: 1.45% (10M) | AN84: 1.60% (10M) | AO84: 1.60% (10M) | AP84: 1.60% (10M) | AQ84: 1.60% (10M) | AR84: 1.70% (10M) | AS84: 1.70% (10M) | AT84: 1.70%(10M) | AU84: 1.70%(10M) | AV84: 1.70%(10M) | AW84: 1.90%10M) | AX84: 1.90%10M) | AY84: 2.00%(10M) | AZ84: 2.00%(10M) | BA84: 2.1%(10M) | BB84: 2.1%(10M) | BC84: 2.1%(10M) | BD84: 2.1%(10M) | BE84: 2.2%(10M) | BF84: 2.2%(10M) | BG84: 2.2%(10M) | BH84: 2.2%(10M) | BI84: 2.2%(10M) | BJ84: 2.2%(10M) | BK84: 2.2%(10M) | BL84: 2.2%(10M) | BM84: 2.2%(10M) | BN84: 2.2%(10M) | BO84: 2.3%(10M) | BP84: 2.3%(10M) | BQ84: 2.3%(10M) | BR84: 2.3%(10M) | BS84: 2.3%(10M) | BT84: 2.3%(10M) | BU84: 2.4%(10M) | BV84: 2.4%(10M) | BW84: 2.5%(10M) | BX84: 2.5%(10M) | BY84: 2.5%(10M) | BZ84: 2.5%(10M) | CA84: 2.5%(10M) | CB84: 2.5%(10M) | CC84: 2.5%(10M) | CD84: 2.5%(10M) | CE84: 2.5%(10M) | CF84: 2.6%(10M) | CG84: 2.6%(10M) | CH84: 2.6%(10M) | CI84: 2.6%(10M) | CJ84: 2.6%(10M) | CK84: 2.6%(10M) | CL84: 2.6%(10M) | CM84: 2.6%(10M) | CN84: 2.6%(10M) | CO84: 2.6%(10M) | CP84: 2.6%(10M) | CQ84: 2.6%(10M) | CR84: 2.6%(10M) | CS84: 2.6%(10M) | CT84: 2.6%(10M) | CU84: 2.6%(10M) | CV84: 2.6%(10M) | CW84: 2.6%(10M) | CX84: 2.6%(10M) | CY84: 2.6%(10M) | CZ84: 0.026 | DA84: 0.027 | DB84: 2.7%（10M) | DC84: 2.7%（10M) | DD84: 2.7%（10M) | DE84: 2.9%（10M) | DF84: 0.029 | DG84: 0.031 | DH84: 0.031 | DI84: 0.031 | DJ84: 0.031 | DK84: 0.031 | DL84: 0.031 | DM84: 0.031 | DN84: 0.031 | DO84: 0.031 | DP84: 0.031 | DQ84: 0.031 | DR84: 0.031 | DS84: 0.031 | DT84: 0.031 | DU84: 0.031 | DV84: 0.031 | DW84: 0.031 | DX84: 0.031 | DY84: 0.031 | DZ84: 0.027 | EA84: 0.027 | EB84: 0.027 | EC84: 0.027 | ED84: 0.027 | EE84: 0.027 | EF84: 0.027 | EG84: 0.027 | EH84: 0.027 | EI84: 0.027 | EJ84: 0.027 | EK84: 0.027 | EL84: 0.027 | EM84: 0.027 | EN84: 0.027 | EO84: 0.029 | EP84: 2.90% (10M) | EQ84: 2.90% (10M) | ER84: 3.10% (10M) | ES84: 3.10% (10M) | ET84: 3.20% (10M) | EU84: 3.45% (10M) | EV84: 3.45% (10M) | EW84: 3.55% (10M) | EX84: 3.55% (10M) | EY84: 3.55% (10M) | EZ84: ≥10,000 | FZ84: 3.95% (10M) | GA84: 3.95% (10M) | GB84: 3.95% (10M) | GC84: 3.95% (10M) | GD84: 3.95% (10M) | GE84: 3.95% (10M) | GF84: 3.95% (10M) | GG84: 3.95% (10M) | GH84: 3.95% (10M) | GI84: 3.95% (10M) | GJ84: 3.95% (10M) | GK84: 3.95% (10M) | GL84: 3.95% (10M) | GM84: 3.95% (10M) | GN84: 3.95% (10M) | GO84: 3.95% (10M) | GP84: 3.95% (10M) | GQ84: 3.7% (10M) | GR84: 3.7% (10M) | GS84: 3% (10M) | HB84: 3.95% (10M) | HC84: 3.55% (10M) | HD84: 3.55% (10M) | HE84: 3.55% (10M) | HF84: =C84-D84 -> 0
A85: SCB | B85: 1.10% (personal banking) | C85: 0.011 | D85: 0.011 | E85: 0.012 | F85: 0 | G85: 0.0135 | H85: 0.0135 | I85: 0.0145 | J85: 0.0145 | K85: 0.011 | L85: 0.011 | M85: 0.0115 | N85: 0.0115 | O85: 0.0115 | P85: 0.0115 | Q85: 0.0115 | R85: 0.0115 | S85: 0.0105 | T85: 0.011 | U85: 0.011 | V85: 0.011 | W85: 0.011 | X85: 0.011 | Y85: 0.011 | Z85: 0.011 | AA85: 0.011 | AB85: 0.011 | AC85: 0.011 | AD85: 0.011 | AE85: 0.0115 | AF85: 0.012 | AG85: 0.013 | AH85: 0.0135 | AI85: 0.014 | AJ85: 0.014 | AK85: 0.014 | AL85: 0.0145 | AM85: 0.0145 | AN85: 1.55%（5M) | AO85: 1.65%（5M) | AP85: 1.70%（5M) | AQ85: 1.75%（5M) | AR85: 1.90%（5M) | AS85: 1.95%（5M) | AT85: 1.95%（5M) | AU85: 1.95%（5M) | AV85: 2.00%（5M) | AW85: 2.00%（5M) | AX85: 2.00%（5M) | AY85: 0.022 | AZ85: 0.022 | BA85: 0.022 | BB85: 0.022 | BC85: 0.022 | BD85: 0.022 | BE85: 0.023 | BF85: 0.023 | BG85: 0.024 | BH85: 0.025 | BI85: 0.025 | BJ85: 0.0258 | BK85: 0.0258 | BL85: 0.024 | BM85: 0.024 | BN85: 0.024 | BO85: 0.0255 | BP85: 0.0255 | BQ85: 0.0255 | BR85: 0.0255 | BS85: 0.0255 | BT85: 0.0255 | BU85: 0.0255 | BV85: 0.0255 | BW85: - | BX85: - | BY85: - | BZ85: - | CA85: - | CB85: - | CC85: - | CD85: - | CE85: - | CF85: 3.10% (priority private) | CG85: 3.10% (priority private) | CH85: 3.10% (priority private) | CI85: 3.10% (priority private) | CJ85: 3.10% (priority private) | CK85: 3.10% (priority private) | CL85: 3.10% (priority private) | CM85: 3.10% (priority private) | CN85: 3.10% (priority private) | CO85: 3.10% (priority private) | CP85: 3.10% (priority private) | CQ85: 3.10% (priority private) | CR85: 3.20% (priority private) | CS85: 3.20% (priority private) | CT85: 3.20% (priority private) | CU85: 3.20% (priority private) | CV85: 3.20% (priority private) | CW85: 3.20% (priority private) | CX85: 3.20% (priority private) | CY85: 3.20% (priority private) | CZ85: 3.20% (priority private) | DA85: 3.20% (priority private) | DB85: 3.20% (priority private) | DC85: 3.20% (priority private) | DD85: 3.20% (priority private) | DE85: 3.30% (priority private) | DF85: 3.30% (priority private) | DG85: 3.30% (priority private) | DH85: 0.033 | DI85: 0.033 | DJ85: 0.033 | DK85: 0.033 | DL85: 0.033 | DM85: 0.033 | DN85: 0.034 | DO85: 0.034 | DP85: 0.034 | DQ85: 0.034 | DR85: 0.034 | DS85: 0.034 | DT85: 0.034 | DU85: 0.032 | DV85: 0.032 | DW85: 0.032 | DX85: 0.032 | DY85: 0.032 | DZ85: 0.032 | EA85: 0.034 | EB85: 0.034 | EC85: 0.034 | ED85: 0.034 | EE85: 0.034 | EF85: 0.034 | EG85: 0.034 | EH85: 0.034 | EI85: 0.034 | EJ85: 0.034 | EK85: 0.034 | EL85: 0.034 | EM85: 0.034 | EN85: 0.034 | EO85: 0.034 | EP85: 0.034 | EQ85: 0.034 | ER85: 0.034 | ES85: 0.034 | ET85: 0.034 | EU85: 0.034 | EZ85: ≥25,000 | HF85: =C85-D85 -> 0 | HG85: >$25k
B86: 1.15% (priority banking) | EZ86: ≥25,000 | HG86: 1-9 Mar
B87: 1.20% (priority private banking) | EZ87: ≥25,000
A88: OCBC | B88: 1.15%电子银行 | C88: - | D88: - | E88: - | F88: 0.0115 | G88: 0.0115 | H88: 0.0115 | I88: 0.0115 | J88: 0.0115 | K88: 0.0115 | L88: 0.0115 | M88: 0.0115 | N88: 0.0115 | O88: 0.0115 | P88: 0.0115 | Q88: 0.0115 | R88: 0.0115 | S88: 0.0115 | T88: 0.0115 | U88: 0.0115 | V88: 0.0115 | W88: 0.0115 | X88: 0.0115 | Y88: 0.0115 | Z88: 0.0115 | AA88: 0.0115 | AB88: 0.0115 | AC88: 0.0115 | AD88: 0.0115 | AE88: 0.0115 | AF88: 0.0135 | AG88: 0.0135 | AH88: 0.0135 | AI88: 0.015 | AJ88: 0.015 | AK88: 0.015 | AL88: 0.015 | AM88: 0.015 | AN88: 0.017 | AO88: 0.017 | AP88: 0.0175 | AQ88: 0.0175 | AR88: 1.90%电子银行 | AS88: =AT88 -> 0 | AT88: =AU88 -> 0 | AU88: =AV88 -> 0 | AV88: =AW88 -> 0 | AW88: =AX88 -> 0 | AX88: =AY88 -> 0 | AY88: =AZ88 -> 0 | AZ88: =BA88 -> 0 | ... BD88: =BE88 -> 0 | EZ88: ≥30,000 | HF88: =C88-D88 -> #VALUE!
B89: 1.10%counter
A90: 12 Months
A91: 日期 | C91: =C3 -> 46099 | D91: =D3 -> 46092 | E91: =E3 -> 46085 | F91: =F3 -> 46078 | G91: =G3 -> 46071 | H91: =H3 -> 46064 | I91: =I3 -> 46057 | J91: =J3 -> 46050 | ... AF91: =AF3 -> 45896 | AG91: 45889 | AH91: 45882 | AI91: 45875 | AJ91: 45868 | AK91: 45861 | AL91: 45854 | AM91: 45847 | AN91: 45840 | AO91: =AO3 -> 45833 | AP91: 45826 | AQ91: =AQ3 -> 45819 | AR91: =AR3 -> 45812 | AS91: =AS3 -> 45805 | AT91: =AT3 -> 45798 | AU91: =AU3 -> 45792 | AV91: =AV3 -> 45785 | AW91: =AW3 -> 45777 | AX91: =AX3 -> 45771 | ... EH91: =EH3 -> 45148 | EI91: 45141 | EJ91: 45134 | EK91: 45127 | EL91: 45120 | EM91: 45113 | EN91: 45105 | EO91: 45099 | EP91: 45092 | EQ91: 45085 | ER91: 45076 | ES91: 45070 | ET91: 45063 | EU91: 45056 | EV91: 45049 | EW91: 45042 | EX91: 45035 | EY91: 45028 | FA91: 44803 | FD91: 44706 | FH91: 5月6日 | FI91: 44685 | FJ91: 44699 | FK91: 44690 | FL91: 44713 | FM91: 44720 | FN91: 44727 | FO91: 44733 | FP91: 44741 | FQ91: 44755 | FR91: 44748 | FS91: 44769 | FT91: 44762 | FU91: 44783 | FV91: 44776 | FW91: 44797 | FX91: 44790 | FY91: 44805 | FZ91: 45000 | GA91: 44993 | GB91: 44986 | GC91: 44979 | GD91: 44972 | GE91: 44965 | GF91: 44958 | GG91: 44951 | GH91: 44944 | GI91: 44937 | GJ91: 44930 | GK91: 44923 | GL91: 44916 | GM91: 44910 | GN91: 44902 | GO91: 44896 | GP91: 44888 | GQ91: 44881 | GR91: 44874 | GS91: 44868 | GT91: 44860 | GU91: 44853 | GV91: 44846 | GW91: 44839 | GX91: 44831 | GY91: 44825 | GZ91: 44818 | HA91: 44811 | HB91: 45002 | HC91: 45020 | HD91: 45014 | HE91: 45008
B92: 全部公开报价 | C92: 当日最高报价 | D92: 当日最高报价 | E92: 当日最高报价 | F92: 当日最高报价 | G92: 当日最高报价 | H92: 当日最高报价 | I92: 当日最高报价 | J92: 当日最高报价 | K92: 当日最高报价 | L92: 当日最高报价 | M92: 当日最高报价 | N92: 当日最高报价 | O92: 当日最高报价 | P92: 当日最高报价 | Q92: 当日最高报价 | R92: 当日最高报价 | S92: 当日最高报价 | T92: 当日最高报价 | U92: 当日最高报价 | V92: 当日最高报价 | W92: 当日最高报价 | X92: 当日最高报价 | Y92: 当日最高报价 | Z92: 当日最高报价 | AA92: 当日最高报价 | AB92: 当日最高报价 | AC92: 当日最高报价 | AD92: 当日最高报价 | AE92: 当日最高报价 | AF92: 当日最高报价 | AG92: 当日最高报价 | AH92: 当日最高报价 | AI92: 当日最高报价 | AJ92: 当日最高报价 | AK92: 当日最高报价 | AL92: 当日最高报价 | AM92: 当日最高报价 | AN92: 当日最高报价 | AO92: 当日最高报价 | AP92: 当日最高报价 | AQ92: 当日最高报价 | AR92: 当日最高报价 | AS92: 当日最高报价 | AT92: 当日最高报价 | AU92: 当日最高报价 | AV92: 当日最高报价 | AW92: 当日最高报价 | AX92: 当日最高报价 | AY92: 当日最高报价 | AZ92: 当日最高报价 | BA92: 当日最高报价 | BB92: 当日最高报价 | BC92: 当日最高报价 | BD92: 当日最高报价 | BE92: 当日最高报价 | BF92: 当日最高报价 | BG92: 当日最高报价 | BH92: 当日最高报价 | BI92: 当日最高报价 | BJ92: 当日最高报价 | BK92: 当日最高报价 | BL92: 当日最高报价 | BM92: 当日最高报价 | BN92: 当日最高报价 | BO92: 当日最高报价 | BP92: 当日最高报价 | BQ92: 当日最高报价 | BR92: 当日最高报价 | BS92: 当日最高报价 | BT92: 当日最高报价 | BU92: 当日最高报价 | BV92: 当日最高报价 | BW92: 当日最高报价 | BX92: 当日最高报价 | BY92: 当日最高报价 | BZ92: 当日最高报价 | CA92: 当日最高报价 | CB92: 当日最高报价 | CC92: 当日最高报价 | CD92: 当日最高报价 | CE92: 当日最高报价 | CF92: 当日最高报价 | CG92: 当日最高报价 | CH92: 当日最高报价 | CI92: 当日最高报价 | CJ92: 当日最高报价 | CK92: 当日最高报价 | CL92: 当日最高报价 | CM92: 当日最高报价 | CN92: 当日最高报价 | CO92: 当日最高报价 | CP92: 当日最高报价 | CQ92: 当日最高报价 | CR92: 当日最高报价 | CS92: 当日最高报价 | CT92: 当日最高报价 | CU92: 当日最高报价 | CV92: 当日最高报价 | CW92: 当日最高报价 | CX92: 当日最高报价 | CY92: 当日最高报价 | CZ92: 当日最高报价 | DA92: 当日最高报价 | DB92: 当日最高报价 | DC92: 当日最高报价 | DD92: 当日最高报价 | DE92: 当日最高报价 | DF92: 当日最高报价 | DG92: 当日最高报价 | DH92: 当日最高报价 | DI92: 当日最高报价 | DJ92: 当日最高报价 | DK92: 当日最高报价 | DL92: 当日最高报价 | DM92: 当日最高报价 | DN92: 当日最高报价 | DO92: 当日最高报价 | DP92: 当日最高报价 | DQ92: 当日最高报价 | DR92: 当日最高报价 | DS92: 当日最高报价 | DT92: 当日最高报价 | DU92: 当日最高报价 | DV92: 当日最高报价 | DW92: 当日最高报价 | DX92: 当日最高报价 | DY92: 当日最高报价 | DZ92: 当日最高报价 | EA92: 当日最高报价 | EB92: 当日最高报价 | EC92: 当日最高报价 | ED92: 当日最高报价 | EE92: 当日最高报价 | EF92: 当日最高报价 | EG92: 当日最高报价 | EH92: 当日最高报价 | EI92: 当日最高报价 | EJ92: 当日最高报价 | EK92: 当日最高报价 | EL92: 当日最高报价 | EM92: 当日最高报价 | EN92: 当日最高报价 | EO92: 当日最高报价 | EP92: 当日最高报价 | EQ92: 当日最高报价 | ER92: 当日最高报价 | ES92: 当日最高报价 | ET92: 当日最高报价 | EU92: 当日最高报价 | EV92: 当日最高报价 | EW92: 当日最高报价 | EX92: 当日最高报价 | EY92: 当日最高报价 | EZ92: 金额 | FA92: 当日最高报价 | FB92: 全部公开报价 | FC92: 金额 | FD92: 当日最高报价 | FE92: 全部公开报价 | FF92: 金额 | FG92: 挂牌利率/促销利率 | FH92: 当日最高报价 | FI92: 当日最高报价 | FJ92: 当日最高报价 | FK92: 当日最高报价 | FL92: 当日最高报价 | FM92: 当日最高报价 | FN92: 当日最高报价 | FO92: 当日最高报价 | FP92: 当日最高报价 | FQ92: 当日最高报价 | FR92: 当日最高报价 | FS92: 当日最高报价 | FT92: 当日最高报价 | FU92: 当日最高报价 | FV92: 当日最高报价 | FW92: 当日最高报价 | FX92: 当日最高报价 | FY92: 当日最高报价 | FZ92: 当日最高报价 | GA92: 当日最高报价 | GB92: 当日最高报价 | GC92: 当日最高报价 | GD92: 当日最高报价 | GE92: 当日最高报价 | GF92: 当日最高报价 | GG92: 当日最高报价 | GH92: 当日最高报价 | GI92: 当日最高报价 | GJ92: 当日最高报价 | GK92: 当日最高报价 | GL92: 当日最高报价 | GM92: 当日最高报价 | GN92: 当日最高报价 | GO92: 当日最高报价 | GP92: 当日最高报价 | GQ92: 当日最高报价 | GR92: 当日最高报价 | GS92: 当日最高报价 | GT92: 当日最高报价 | GU92: 当日最高报价 | GV92: 当日最高报价 | GW92: 当日最高报价 | GX92: 当日最高报价 | GY92: 当日最高报价 | GZ92: 当日最高报价 | HA92: 当日最高报价 | HB92: 当日最高报价 | HC92: 当日最高报价 | HD92: 当日最高报价 | HE92: 当日最高报价 | HF92: 当日最高报价变动
A93: HLB | B93: 1.30%(Online S$10K) 1.25%(Branch S$100K) | C93: 0.013 | D93: 0.013 | E93: 0.013 | F93: 0.013 | G93: 0.013 | H93: 0.013 | J93: 0.013 | K93: 0.013 | M93: - | N93: - | O93: 0.013 | P93: 0.013 | Q93: 0.013 | W93: 0.0365 | X93: 0.0365 | Y93: 0.0365 | Z93: 0.0365 | AA93: 0.0365 | AB93: 0.0365 | AC93: 0.0365 | AD93: 0.0365 | AE93: 0.0365 | AF93: 0.0365 | AG93: 0.0365 | AH93: 0.0365 | AI93: 0.0365 | AJ93: 0.0365 | AK93: 0.0365 | AL93: 0.0365 | AM93: 0.0365 | AN93: 0.0365 | AO93: 0.0365 | AP93: 0.0365 | AQ93: 0.0365 | AR93: 0.0365 | AS93: 0.0365 | AT93: 0.0365 | AU93: 0.0365 | AV93: 0.0365 | AW93: 0.0365 | AX93: 0.0365 | AY93: 0.0365 | AZ93: 0.0365 | BA93: 0.0365 | BB93: 0.0365 | BC93: 0.0365 | BD93: 0.0365 | BE93: 0.0365 | BF93: 0.0365 | BG93: 0.0365 | BH93: 0.0365 | BI93: 0.0365 | BJ93: 0.0365 | BK93: 0.0365 | BL93: 0.0365 | BM93: 0.0365 | BN93: 0.0365 | BO93: 0.0365 | BP93: 0.0365 | BQ93: 0.0365 | BR93: 0.0365 | BS93: 0.0365 | BT93: 0.0365 | BU93: 0.0365 | BV93: 0.0365 | BW93: 0.0365 | BX93: 0.0365 | BY93: 0.0365 | BZ93: 0.0365 | CA93: 0.0365 | CB93: 0.0365 | CC93: 0.0365 | CD93: 0.0365 | CE93: 0.0365 | CF93: 0.0365 | CG93: 0.0365 | CH93: 0.0365 | CI93: 0.0365 | CJ93: 0.0365 | CK93: 0.0365 | CL93: 0.0365 | CM93: 0.0365 | CN93: 0.0365 | CO93: 0.0365 | CP93: 0.0365 | CQ93: 0.0365 | CR93: 0.0365 | CS93: 0.0365 | CT93: 0.0365 | CU93: 0.0365 | CV93: 0.0365 | CW93: 0.0365 | CX93: 0.0365 | CY93: 0.0365 | CZ93: 0.0365 | DA93: 0.0365 | DB93: 0.0365 | DC93: 0.0365 | DD93: 0.0365 | DE93: 0.0365 | DF93: 0.0365 | DG93: 0.0365 | DH93: 0.0365 | DI93: 0.0365 | DJ93: 0.0365 | DK93: 0.0365 | DL93: 0.0365 | DM93: 0.0365 | DN93: 0.0365 | DO93: 0.0365 | DP93: 0.0365 | DQ93: 0.0365 | DR93: 0.0365 | DS93: 0.0365 | DT93: 0.0365 | DU93: 0.0365 | DV93: 0.0365 | DW93: 0.0365 | DX93: 0.0365 | DY93: 0.036 | DZ93: 0.036 | EA93: 0.0358 | EB93: 0.0358 | EC93: 0.0358 | ED93: 0.0358 | EE93: - | EF93: - | EG93: - | EH93: - | EI93: - | EJ93: - | EK93: - | EL93: - | EM93: - | EN93: - | EO93: - | EP93: - | EQ93: - | ER93: - | ES93: - | ET93: - | EU93: - | EV93: - | EW93: 0.0395 | EX93: 0.0395 | EY93: 0.0395 | EZ93: ≥100,000 | FZ93: 0.041 | GA93: 0.041 | GB93: 0.041 | GC93: 0.041 | GD93: 0.041 | GE93: 0.041 | GF93: 0.041 | GG93: 0.041 | GH93: 0.039 | GI93: 0.041 | GJ93: 0.041 | GK93: 0.041 | GL93: 0.041 | GM93: 0.041 | GN93: 0.041 | GO93: 0.041 | GP93: 0.041 | GQ93: 0.038 | GR93: 0.038 | GS93: 0.038 | GT93: 0.038 | GU93: 0.0275 | HB93: 0.041 | HC93: 0.0395 | HD93: 0.041 | HE93: 0.041 | HF93: =C93-D93 -> 0 | HG93: 15 - 31 Jan 2026
A94: RHB | B94: 1.25% (personal） | C94: 0.0125 | D94: 0.0125 | E94: 0.0125 | F94: 0.0125 | G94: 0.0125 | H94: 0.0125 | I94: 0.014 | J94: 0.014 | K94: 0.014 | L94: 0.012 | M94: 0.012 | N94: 0.012 | O94: 0.012 | P94: 0.0105 | Q94: 0.0105 | R94: 0.0105 | S94: 0.0105 | T94: 0.0105 | U94: 0.0105 | V94: 0.0105 | W94: 0.0115 | X94: 0.0115 | Y94: 0.0115 | Z94: 0.011 | AA94: 0.011 | AB94: 0.01 | AC94: 0.01 | AD94: 0.01 | AE94: 0.01 | AF94: 0.01 | AG94: 0.01 | AH94: 0.01 | AI94: 0.011 | AJ94: 0.013 | AK94: 0.014 | AL94: 0.014 | AM94: 0.016 | AN94: 0.016 | AO94: 0.021 | AP94: 0.021 | AQ94: 0.021 | AR94: 0.021 | AS94: 0.021 | AT94: 0.021 | AU94: 0.021 | AV94: 0.021 | AW94: 0.022 | AX94: 0.022 | AY94: 0.022 | AZ94: 0.022 | BA94: 0.022 | BB94: 0.0245 | BC94: 0.0245 | BD94: 0.0245 | BE94: 0.027 | BF94: 0.027 | BG94: 0.028 | BH94: 0.0268 | BI94: 0.0268 | BJ94: 0.0268 | BK94: 0.0268 | BL94: 0.0268 | BM94: 0.03 | BN94: 0.03 | BO94: 0.03 | BP94: 0.03 | BQ94: 0.03 | BR94: 0.03 | BS94: 0.0265 | BT94: 0.0265 | BU94: 0.026 | BV94: 0.026 | BW94: 0.026 | BX94: 0.026 | BY94: 0.026 | BZ94: 0.0255 | CA94: 0.0255 | CB94: 0.0255 | CC94: 0.027 | CD94: 0.027 | CE94: 0.0285 | CF94: 0.0285 | CG94: 0.031 | CH94: 0.031 | CI94: 0.033 | CJ94: 0.033 | CK94: 0.033 | CL94: 0.033 | CM94: 0.033 | CN94: 0.033 | CO94: 0.033 | CP94: 0.033 | CQ94: 0.033 | CR94: 0.033 | CS94: 0.033 | CT94: 0.033 | CU94: 0.033 | CV94: 0.0305 | CW94: 0.0305 | CX94: 0.0305 | CY94: 0.0305 | CZ94: 0.0305 | DA94: 0.0305 | DB94: 0.0305 | DC94: 0.0305 | DD94: 0.0305 | DE94: 0.032 | DF94: 0.032 | DG94: 0.032 | DH94: 0.032 | DI94: 0.032 | DJ94: 0.032 | DK94: 0.032 | DL94: 0.0335 | DM94: 0.0335 | DN94: 0.0335 | DO94: 0.0335 | DP94: 0.0368 | DQ94: 0.0368 | DR94: 0.0368 | DS94: 0.0368 | DT94: 0.0368 | DU94: 0.0368 | DV94: 0.0368 | DW94: 0.0368 | DX94: 0.0368 | DY94: 0.0368 | DZ94: 0.0368 | EA94: 0.0368 | EB94: 0.0368 | EC94: 0.0345 | ED94: 0.0345 | EE94: 0.0345 | EF94: 0.0345 | EG94: 0.0345 | EH94: 0.0345 | EI94: 0.0345 | EJ94: 0.0345 | EK94: 0.0345 | EL94: 0.0345 | EM94: 0.0355 | EN94: 0.0355 | EO94: 0.0355 | EP94: 0.0355 | EQ94: 0.0355 | ER94: 0.0355 | ES94: 0.0355 | ET94: 0.0355 | EU94: 0.0355 | EV94: 0.0355 | EW94: 0.04 | EX94: 0.04 | EY94: 0.039 | EZ94: ≥20,000 | FA94: 0.023 | FB94: 2.30% 财富 | FC94: ≥20,000 | FD94: 0.0135 | FE94: 0 | FF94: ＜2万 | FG94: 挂牌 | FH94: 0.012 | FI94: 0.012 | FJ94: 0.0135 | FK94: 0.012 | FL94: 0.0135 | FM94: 0.0155 | FN94: 0.0155 | FO94: 0.0155 | FP94: 0.0155 | FQ94: 0.019 | FR94: 0.019 | FS94: 0.019 | FT94: 0.019 | FU94: 0.019 | FV94: 0.019 | FW94: 0.023 | FX94: 0.023 | FY94: 0.025 | FZ94: 0.039 | GA94: 0.039 | GB94: 0.039 | GC94: 0.039 | GD94: 0.041 | GE94: 0.041 | GF94: 0.041 | GJ94: 0.039 | GK94: 0.039 | GL94: 0.039 | GM94: 0.039 | GN94: 0.039 | GO94: 0.039 | GP94: 0.039 | GQ94: 0.039 | GR94: 0.034 | GS94: 0.034 | GT94: 0.034 | GU94: 0.034 | GV94: 0.034 | GW94: 0.029 | GX94: 0.025 | GY94: 0.025 | GZ94: 0.025 | HA94: 0.025 | HB94: 0.039 | HC94: 0.039 | HD94: 0.039 | HE94: 0.039 | HF94: =C94-D94 -> 0
B95: 1.35% (premier） | FB95: 2.20% 个人 | FE95: 1.30% 个人客户（新资金） | FF95: ≥2万 | FG95: 促销 | HG95: 20k | HH95: from 19 Jan 2026
A96: CIMB | B96: 1.30% 手机银行 （个人） | C96: 0.013 | D96: 0.013 | E96: 0.013 | F96: 0.013 | G96: 0.013 | H96: 0.013 | I96: 0.012 | J96: 0.011 | K96: 0.011 | L96: 0.011 | M96: 0.011 | N96: 0.011 | O96: 0.011 | P96: 0.011 | Q96: 0.011 | R96: 0.011 | S96: 0.011 | T96: 0.011 | U96: 0.011 | V96: 0.011 | W96: 0.011 | X96: 0.011 | Y96: 0.011 | Z96: 0.011 | AA96: 0.011 | AB96: 0.011 | AC96: 0.011 | AD96: 0.011 | AE96: 0.0115 | AF96: 0.012 | AG96: 0.0135 | AH96: 0.0135 | AI96: 0.0135 | AJ96: 0.014 | AK96: 0.014 | AL96: 0.014 | AM96: 0.0145 | AN96: 0.0155 | AO96: 0.017 | AP96: 0.018 | AQ96: 0.019 | AR96: 0.019 | AS96: 0.0195 | AT96: 0.019 | AU96: 0.019 | AV96: 0.0195 | AW96: 0.0195 | AX96: 0.0205 | AY96: 0.0205 | AZ96: 0.0205 | BA96: 0.0205 | BB96: 0.0215 | BC96: 0.0215 | BD96: 0.0215 | BE96: 0.023 | BF96: 0.0245 | BG96: 0.0245 | BH96: 0.0245 | BI96: 0.0245 | BJ96: 0.026 | BK96: 0.026 | BL96: 0.026 | BM96: 0.026 | BN96: 0.026 | BO96: 0.026 | BP96: 0.026 | BQ96: 0.026 | BR96: 0.026 | BS96: 0.026 | BT96: 0.026 | BU96: 0.026 | BV96: 0.026 | BW96: 0.026 | BX96: 0.026 | BY96: 0.026 | BZ96: 0.026 | CA96: 0.026 | CB96: 0.026 | CC96: 0.027 | CD96: 0.027 | CE96: 0.027 | CF96: 0.028 | CG96: 0.028 | CH96: 0.03 | CI96: 0.03 | CJ96: 0.03 | CK96: 0.03 | CL96: 0.03 | CM96: 0.03 | CN96: 0.03 | CO96: 0.03 | CP96: 0.03 | CQ96: 0.03 | CR96: 0.03 | CS96: 0.03 | CT96: 0.03 | CU96: 0.03 | CV96: 0.03 | CW96: 0.03 | CX96: 0.03 | CY96: 0.03 | CZ96: 0.03 | DA96: 0.031 | DB96: 0.031 | DC96: 0.031 | DD96: 0.031 | DE96: 0.032 | DF96: 0.032 | DG96: 0.032 | DH96: 0.032 | DI96: 0.032 | DJ96: 0.032 | DK96: 0.032 | DL96: 0.032 | DM96: 0.032 | DN96: 0.032 | DO96: 0.032 | DP96: 0.032 | DQ96: 0.032 | DR96: 0.032 | DS96: 0.032 | DT96: 0.032 | DU96: 0.032 | DV96: 0.032 | DW96: 0.032 | DX96: 0.032 | DY96: 0.032 | DZ96: 0.032 | EA96: 0.032 | EB96: 0.032 | EC96: 0.032 | ED96: 0.032 | EE96: 0.032 | EF96: 0.032 | EG96: 0.032 | EH96: 0.032 | EI96: 0.032 | EJ96: 0.032 | EK96: 0.032 | EL96: 0.032 | EM96: 0.032 | EN96: 0.032 | EO96: 0.032 | EP96: 0.032 | EQ96: 0.032 | ER96: 0.034 | ES96: 0.034 | ET96: 0.034 | EU96: 0.034 | EV96: 0.034 | EW96: 0.035 | EX96: 0.035 | EY96: 0.035 | EZ96: ≥10,000 | FA96: 0.022 | FB96: 2.20% 财富(电子) | FC96: ≥10,000 | FE96: 1.25% 个人客户（电子渠道） | FF96: ≥1万 | FG96: 促销 | FS96: 0.019 | FU96: 0.022 | FV96: 0.022 | FW96: 0.022 | FX96: 0.022 | FY96: 0.023 | FZ96: 0.035 | GA96: 0.035 | GB96: 0.035 | GC96: 0.035 | GD96: 0.035 | GE96: 0.035 | GF96: 0.035 | GG96: 0.042 | GH96: 0.042 | GI96: 0.042 | GJ96: 0.042 | GK96: 0.042 | GL96: 0.042 | GM96: 0.042 | GN96: 0.042 | GO96: 0.042 | GP96: 0.039 | GQ96: 0.038 | GR96: 0.038 | GS96: 0.038 | GT96: 0.03 | GU96: 0.03 | GV96: 0.03 | GW96: 0.028 | GX96: 0.025 | GY96: 0.025 | GZ96: 0.025 | HA96: 0.023 | HB96: 0.035 | HC96: 0.035 | HD96: 0.035 | HE96: 0.035 | HF96: =C96-D96 -> 0 | HG96: 10k
B97: 1.35% 手机银行 （财富） | FB97: 2.15%个人(电子) | FE97: 1.30% 财富客户（电子渠道）
A98: Maybank | B98: 1.45% (branch and online) E.I.R. 1.32% 1.30% (branch and online) | C98: 0.0132 | D98: 0.0132 | E98: 0.0132 | F98: 0.0132 | G98: 0.0132 | H98: 0.0132 | I98: 0.0132 | J98: 0.0132 | K98: 0.0132 | L98: 0.0115 | M98: 0.0115 | N98: 0.0115 | O98: 0.0115 | P98: 0.0115 | Q98: 0.0115 | R98: 0.0115 | S98: 0.0115 | T98: 0.0115 | U98: 0.0115 | V98: 0.0115 | W98: 0.0115 | X98: 0.011 | Y98: 0.011 | Z98: 0.011 | AA98: 0.011 | AB98: 0.011 | AC98: 0.0115 | AD98: 0.0115 | AE98: 0.013 | AF98: 0.0135 | AG98: 0.0135 | AH98: 0.0145 | AI98: 0.0152 | AJ98: 0.0161 | AK98: 0.0161 | AL98: 0.0161 | AM98: 0.0189 | AN98: 0.0189 | AO98: 0.0189 | AP98: 0.0189 | AQ98: 0.0189 | AR98: 0.0205 | AS98: 2.25% savings bundle(EIR=2.07%) | AT98: 2.25% savings bundle(EIR=2.07%) | AU98: 2.25% savings bundle(EIR=2.07%) | AV98: 2.25% savings bundle(EIR=2.07%) | AW98: 2.25% savings bundle(EIR=2.07%) | AX98: 2.70% savings bundle(EIR=2.48%) | AY98: 2.70% savings bundle(EIR=2.48%) | AZ98: 2.70% savings bundle(EIR=2.48%) | BA98: 2.70% savings bundle(EIR=2.48%) | BB98: 2.70% savings bundle(EIR=2.48%) | BC98: 2.70% savings bundle(EIR=2.48%) | BD98: 2.70% savings bundle(EIR=2.48%) | BE98: 2.70% savings bundle(EIR=2.48%) | BF98: 2.70% savings bundle(EIR=2.48%) | BG98: 2.70% savings bundle(EIR=2.48%) | BH98: 2.70% savings bundle(EIR=2.48%) | BI98: 2.70% savings bundle(EIR=2.48%) | BJ98: 2.70% savings bundle(EIR=2.48%) | BK98: 2.80% savings bundle(EIR=2.57%) | BL98: 2.80% savings bundle(EIR=2.57%) | BM98: 2.80% savings bundle(EIR=2.57%) | BN98: 2.80% savings bundle(EIR=2.57%) | BO98: 2.80% savings bundle(EIR=2.57%) | BP98: 2.80% savings bundle(EIR=2.57%) | BQ98: 2.80% savings bundle(EIR=2.57%) | BR98: 2.80% savings bundle(EIR=2.57%) | BS98: 2.95% savings bundle(EIR=2.70%) | BT98: 2.95% savings bundle(EIR=2.70%) | BU98: 2.95% savings bundle(EIR=2.70%) | BV98: 2.95% savings bundle(EIR=2.70%) | BW98: 2.95% savings bundle(EIR=2.70%) | BX98: 2.95% savings bundle(EIR=2.70%) | BY98: 2.95% savings bundle(EIR=2.70%) | BZ98: 2.95% savings bundle(EIR=2.70%) | CA98: 2.95% savings bundle(EIR=2.70%) | CB98: 2.95% savings bundle(EIR=2.70%) | CC98: 3.30% savings bundle | CD98: 3.30% savings bundle | CE98: 3.30% savings bundle | CF98: 3.30% savings bundle | CG98: 3.30% savings bundle | CH98: 3.30% savings bundle | CI98: 3.30% savings bundle | CJ98: 3.30% savings bundle | CK98: 3.30% savings bundle | CL98: 3.30% savings bundle | CM98: 3.30% savings bundle | CN98: 3.30% savings bundle | CO98: 3.30% savings bundle | CP98: 3.30% savings bundle | CQ98: 3.30% savings bundle | CR98: 3.30% savings bundle | CS98: 3.30% savings bundle | CT98: 3.30% savings bundle | CU98: 3.30% savings bundle | CV98: 3.30% savings bundle | CW98: 3.30% savings bundle | CX98: 3.30% savings bundle | CY98: 3.30% savings bundle | CZ98: 3.30% savings bundle | DA98: 3.30% savings bundle | DB98: 3.30% savings bundle | DC98: 3.30% savings bundle | DD98: 3.30% savings bundle | DE98: 3.30% savings bundle | DF98: 3.30% savings bundle | DG98: 3.35% savings bundle | DH98: 3.35% savings bundle | DI98: 3.35% savings bundle | DJ98: 3.35% savings bundle | DK98: 3.35% savings bundle | DL98: 3.35% savings bundle | DM98: 3.35% savings bundle | DN98: 3.35% savings bundle | DO98: 3.35% savings bundle | DP98: 3.35% savings bundle | DQ98: 3.35% savings bundle | DR98: 3.35% savings bundle | DS98: 3.50% savings bundle | DT98: 3.50% savings bundle | DU98: 3.50% savings bundle | DV98: 3.50% savings bundle | DW98: 3.65% savings bundle | DX98: 3.65% savings bundle | DY98: 3.65% savings bundle | DZ98: 0.029 | EA98: 0.029 | EB98: 0.029 | EC98: 0.03 | ED98: 0.03 | EE98: 0.03 | EF98: 0.03 | EG98: 0.03 | EH98: 0.03 | EI98: 0.03 | EJ98: 0.03 | EK98: 0.03 | EL98: 0.03 | EM98: 0.03 | EN98: 0.032 | EO98: 0.032 | EP98: 0.032 | EQ98: 0.032 | ER98: 0.032 | ES98: 0.0355 | ET98: 0.0355 | EU98: 0.0355 | EV98: 0.0355 | EW98: 0.0355 | EX98: 0.0355 | EY98: 0.0355 | EZ98: ≥20,000 | FA98: 0.022 | FB98: 0.022 | FC98: ≥20,000 | FD98: 0.013 | FE98: 0.0035 | FF98: 1千-1.99万 | FG98: 挂牌 | FH98: 0.009 | FI98: 0.009 | FJ98: 0.013 | FK98: 0.009 | FL98: 0.013 | FM98: 0.013 | FN98: 0.013 | FO98: 0.013 | FP98: 0.013 | FQ98: 0.013 | FR98: 0.013 | FS98: 0.018 | FT98: 0.018 | FU98: 0.022 | FV98: 0.018 | FW98: 0.022 | FX98: 0.022 | FY98: 0.022 | FZ98: 0.039 | GA98: 0.039 | GB98: 0.039 | GC98: 0.039 | GD98: 0.039 | GE98: 0.039 | GF98: 0.039 | GG98: 0.039 | GH98: 0.039 | GI98: 0.039 | GJ98: 0.039 | GK98: 0.039 | GL98: 0.039 | GM98: 0.039 | GN98: 0.039 | GO98: 0.039 | GP98: 0.03 | GQ98: 0.03 | GR98: 0.03 | GS98: 0.03 | GT98: 0.03 | GU98: 0.03 | GV98: 0.03 | GW98: 0.03 | GX98: 0.022 | GY98: 0.022 | GZ98: 0.022 | HA98: 0.022 | HB98: 0.039 | HC98: 0.0355 | HD98: 0.039 | HE98: 0.039 | HF98: =C98-D98 -> 0
EZ99: ≥20,000 | HG99: from 20 Jan 2026
A100: SBI | B100: 1.40%（50k-200k） | C100: 0.008 | D100: 0.008 | E100: 0.008 | F100: 0.008 | G100: 0.008 | H100: 0.008 | I100: 0.008 | J100: 0.008 | K100: 0.008 | L100: 0.008 | M100: 0.008 | N100: 0.008 | O100: 0.008 | P100: 0.008 | Q100: 0.008 | R100: 0.008 | S100: 0.008 | T100: 0.008 | U100: 0.008 | V100: 0.008 | W100: - | X100: - | Y100: - | Z100: - | AA100: - | AB100: - | AC100: - | AD100: - | AE100: 0.015 | AF100: 0.015 | AG100: 0.015 | AH100: 0.015 | AI100: 0.015 | AJ100: 0.015 | AK100: - | AL100: - | AM100: - | AN100: - | AO100: - | AP100: - | AQ100: - | AR100: 0.0225 | AS100: 0.0225 | AT100: 0.0225 | AU100: 0.0225 | AV100: 0.0225 | AW100: 0.024 | AX100: 0.024 | AY100: 0.024 | AZ100: 0.024 | BA100: 0.024 | BB100: 0.024 | BC100: 0.024 | BD100: 0.0275 | BE100: 0.0275 | BF100: 0.0275 | BG100: 0.0275 | BH100: 0.025 | BI100: 0.025 | BJ100: 0.025 | BK100: 0.025 | BL100: 0.025 | BM100: 2.5%+ | BN100: - | BO100: - | BP100: - | BQ100: - | BR100: - | BS100: - | BT100: - | BU100: - | BV100: 0.025 | BW100: 0.025 | BX100: 0.025 | BY100: 0.025 | BZ100: 0.025 | CA100: 0.027 | CB100: 0.027 | CC100: 0.027 | CD100: 0.027 | CE100: 0.027 | CF100: 0.027 | CG100: 0.027 | CH100: 0.032 | CI100: 0.032 | CJ100: 0.032 | CK100: 0.032 | CL100: 0.032 | CM100: 0.032 | CN100: 0.032 | CO100: 0.0305 | CP100: 0.0305 | CQ100: 0.0305 | CR100: 0.0305 | CS100: 0.0305 | CT100: 0.0305 | CU100: 0.0305 | CV100: 0.0305 | CW100: 0.032 | CX100: 0.032 | CY100: 0.032 | CZ100: 0.032 | DA100: 0.032 | DB100: 0.032 | DC100: 0.032 | DD100: 0.032 | DE100: 0.032 | DF100: 0.032 | DG100: 0.032 | DH100: 0.033 | DI100: 0.033 | DJ100: 0.0355 | DK100: 0.0355 | DL100: 0.0355 | DM100: 0.0355 | DN100: 0.0355 | DO100: 0.0355 | DP100: 0.0355 | DQ100: 0.0355 | DR100: 0.0355 | DS100: 0.0355 | DT100: 0.0355 | DU100: 0.0355 | DV100: 0.0355 | DW100: 0.0355 | DX100: 0.0355 | DY100: 0.0355 | DZ100: 0.0355 | EA100: 0.0355 | EB100: 0.0355 | EC100: 0.0355 | ED100: 0.0355 | EE100: 0.0355 | EF100: 0.0355 | EG100: 0.032 | EH100: 0.032 | EI100: 0.032 | EJ100: 0.032 | EK100: 0.032 | EL100: 0.032 | EM100: 0.032 | EN100: 0.032 | EO100: 0.035 | EP100: 0.035 | EQ100: 0.035 | ER100: 0.035 | ES100: 0.035 | ET100: 0.0375 | EU100: 0.0375 | EV100: 0.0375 | EW100: 0.0375 | EX100: 0.0375 | EY100: 0.0375 | EZ100: 50,000-1,000,000 | FA100: 0.0225 | FB100: 0.0225 | FC100: ≥25,000 | FD100: 0.0125 | FE100: 0.009 | FF100: 1千-2.49万 | FG100: 挂牌 | FH100: 0.0125 | FI100: 0.0125 | FJ100: 0.0125 | FK100: 0.0125 | FL100: 0.0125 | FM100: 0.0125 | FN100: 0.0125 | FO100: 0.0125 | FP100: 0.016 | FQ100: 0.016 | FR100: 0.016 | FS100: 0.02 | FT100: 0.016 | FU100: 0.0225 | FV100: 0.02 | FW100: 0.0225 | FX100: 0.0225 | FY100: 0.0225 | FZ100: 0.04 | GA100: 0.04 | GB100: 0.04 | GC100: 0.04 | GD100: 0.04 | GE100: 0.04 | GF100: 0.04 | GG100: 0.04 | GH100: 0.04 | GI100: 0.04 | GJ100: 0.04 | GK100: 0.04 | GL100: 0.0375 | GM100: 0.0375 | GN100: 0.0375 | GO100: 0.0375 | GP100: 0.0375 | GQ100: 0.0375 | GR100: 0.0333 | GS100: 3.33% fresh fund | GT100: 3.33% fresh fund | GU100: 3.33% fresh fund | GV100: 3.33% fresh fund | GW100: 0.0265 | GX100: 0.0265 | GY100: 0.0265 | GZ100: 0.0265 | HA100: 0.0265 | HB100: 0.04 | HC100: 0.0375 | HD100: 0.0375 | HE100: 0.04 | HF100: =C100-D100 -> 0
B101: 0.80%（200k-1m）
...

Sheet USD促销
B1: 美元存款市场调研-促销利率
B3: Tenor: 1 month | GT3: 2022年（本周变动）
B4: 银行 | C4: 金额 | D4: ='最高报价汇总 '!F2 -> 46099 | E4: ='最高报价汇总 '!G2 -> 46092 | F4: 46085 | G4: 46078 | H4: 46071 | I4: 46057 | J4: 46050 | K4: 46043 | L4: 46036 | M4: 46029 | N4: 46022 | O4: 46015 | P4: 46008 | Q4: ='最高报价汇总 '!G2 -> 46092 | R4: 45994 | S4: 45987 | T4: 45980 | U4: 45973 | V4: 45966 | W4: 45959 | X4: 45952 | Y4: 45945 | Z4: 45938 | AA4: 45931 | AB4: 45924 | AC4: 45917 | AD4: 45910 | AE4: 45959 | AF4: 45896 | AG4: 45889 | AH4: 45882 | AI4: 45875 | AJ4: 45868 | AK4: 45861 | AL4: 45854 | AM4: 45847 | AN4: 45840 | AO4: 45833 | AP4: 45826 | AQ4: 45819 | AR4: 45812 | AS4: 45805 | AT4: 45798 | AU4: 45792 | AV4: 45785 | AW4: 45777 | AX4: 45763 | AY4: 45757 | AZ4: 45750 | BA4: 45742 | BB4: 45729 | BC4: 45722 | BD4: 45715 | BE4: 45708 | BF4: 45701 | BG4: 45694 | BH4: 45688 | BI4: 45681 | BJ4: 45673 | BK4: 45666 | BL4: 45659 | BM4: 45652 | BN4: 45645 | BO4: 45638 | BP4: 45631 | BQ4: 45625 | BR4: 45617 | BS4: 45610 | BT4: 45603 | BU4: 45595 | BV4: 45591 | BW4: 45582 | BX4: 45575 | BY4: 45568 | BZ4: 45561 | CA4: 45547 | CB4: 45540 | CC4: 45533 | CD4: 45526 | CE4: 45517 | CF4: 45511 | CG4: =#REF! -> #REF! | CH4: =#REF! -> #REF! | CI4: =#REF! -> #REF! | CJ4: =#REF! -> #REF! | CK4: =#REF! -> #REF! | CL4: =#REF! -> #REF! | CM4: =#REF! -> #REF! | CN4: =#REF! -> #REF! | ... ED4: =#REF! -> #REF! | EE4: 45141 | EF4: 45134 | EG4: 44839 | EH4: 44831 | EI4: 44826 | EJ4: 44818 | EK4: 44811 | EL4: 45070 | EM4: 45063 | EN4: 45056 | EO4: 45050 | EP4: 45042 | EQ4: 45035 | ER4: 45028 | ES4: 45020 | ET4: 45014 | EU4: 45008 | EV4: 45002 | EW4: 45000 | EX4: 44993 | EY4: 44986 | EZ4: 44979 | FA4: 44972 | FB4: 44965 | FC4: 44958 | FD4: 44951 | FE4: 44944 | FF4: 44937 | FG4: 44930 | FH4: 44923 | FI4: 44916 | FJ4: 44910 | FK4: 44902 | FL4: 44896 | FM4: 44888 | FN4: 44881 | FO4: 44874 | FP4: 44868 | FQ4: 44860 | FR4: 44853 | FS4: 44846 | FT4: 45085 | FU4: 45076 | FV4: 45127 | FW4: 45120 | FX4: 45113 | FY4: 45105 | FZ4: 45099 | GA4: 45092 | GB4: 44803 | GC4: 44797 | GD4: 44790 | GE4: 44783 | GF4: 44776 | GG4: 44769 | GH4: 44762 | GI4: 44755 | GJ4: 44748 | GK4: 44741 | GL4: 44733 | GM4: 44727 | GN4: 44720 | GO4: 44713 | GP4: 44706 | GQ4: 44699 | GR4: 44690 | GS4: 44687 | GT4: 44685 | GU4: 44678 | GV4: 44670 | GW4: 44663 | GX4: 44662 | GY4: 44659 | GZ4: 44657 | HA4: 44656 | HB4: 44655 | HC4: 44652 | HD4: 44650 | HE4: 44649 | HF4: 44648 | HG4: 44645 | HH4: 44644 | HI4: 44642 | HJ4: 44641 | HK4: 44638 | HL4: 44637 | HM4: 44636 | HN4: 当日增幅 | HO4: 其他要求
B5: ICBC | C5: 500及以上 | D5: 0.036 | E5: 0.036 | F5: 0.036 | G5: 0.036 | H5: 0.036 | I5: 0.036 | J5: 0.036 | K5: 0.036 | L5: 0.036 | M5: 0.037 | N5: 0.037 | O5: 0.037 | P5: 0.038 | Q5: 0.038 | R5: 0.038 | S5: 0.038 | T5: 0.038 | U5: 0.039 | V5: 0.039 | W5: 0.039 | X5: 0.04 | Y5: 0.04 | Z5: 0.04 | AA5: 0.04 | AB5: 0.04 | AC5: 0.04 | AD5: 0.04 | AE5: 0.04 | AF5: 0.0415 | AG5: 0.0415 | AH5: 0.0415 | AI5: 0.0415 | AJ5: 0.0415 | AK5: 0.0415 | AL5: 0.0415 | AM5: 0.0415 | AN5: 0.0415 | AO5: 0.0415 | AP5: 0.0415 | AQ5: 0.0415 | AR5: 0.0415 | AS5: 0.0415 | AT5: 0.0415 | AU5: 0.0415 | AV5: 0.0415 | AW5: 0.0415 | AX5: 0.0415 | AY5: 0.0415 | AZ5: 0.0415 | BA5: 0.0415 | BB5: 0.0415 | BC5: 0.0415 | BD5: 0.0415 | BE5: 0.0415 | BF5: 0.0415 | BG5: 0.0415 | BH5: 0.0415 | BI5: 0.043 | BJ5: 0.043 | BK5: 0.043 | BL5: 0.043 | BM5: 0.043 | BN5: 0.043 | BO5: 0.043 | BP5: 0.043 | BQ5: 0.043 | BR5: 0.043 | BS5: 0.043 | BT5: 0.043 | BU5: 0.043 | BV5: 0.043 | BW5: 0.043 | BX5: 0.043 | BY5: 0.043 | BZ5: 0.043 | CA5: 0.043 | CB5: 0.043 | CC5: 0.043 | CD5: 0.043 | CE5: 0.043 | CF5: 0.043 | CG5: 0.043 | CH5: 0.043 | CI5: 0.043 | CJ5: 0.043 | CK5: 0.043 | CL5: 0.043 | CM5: 0.043 | CN5: 0.043 | CO5: 0.043 | CP5: 0.043 | CQ5: 0.043 | CR5: 0.043 | CS5: 0.043 | CT5: 0.043 | CU5: 0.043 | CV5: 0.043 | CW5: 0.043 | CX5: 0.043 | CY5: 0.043 | CZ5: 0.043 | DA5: 0.043 | DB5: 0.043 | DC5: 0.043 | DD5: 0.043 | DE5: 0.043 | DF5: 0.043 | DG5: 0.043 | DH5: 0.043 | DI5: 0.043 | DJ5: 0.043 | DK5: 0.043 | DL5: 0.043 | DM5: 0.043 | DN5: 0.043 | DO5: 0.043 | DP5: 0.043 | DQ5: 0.043 | DR5: 0.043 | DS5: 0.043 | DT5: 0.043 | DU5: 0.043 | DV5: 0.043 | DW5: 0.043 | DX5: 0.043 | DY5: 0.043 | DZ5: 0.043 | EA5: 0.043 | EB5: 0.043 | EC5: 0.043 | ED5: 0.043 | EE5: 0.043 | EF5: 0.043 | EL5: 0.043 | EM5: 0.043 | EN5: 0.043 | EO5: 0.043 | EP5: 0.043 | EQ5: 0.043 | ER5: 0.043 | ES5: 0.043 | ET5: 0.043 | EU5: 0.043 | EV5: 0.043 | EW5: 0.043 | EX5: 0.043 | FT5: 0.043 | FU5: 0.043 | FV5: 0.043 | FW5: 0.043 | FX5: 0.043 | FY5: 0.043 | FZ5: 0.043 | GA5: 0.043 | HN5: =$D5-$E5 -> 0 | HO5: 电子银行
B6: BOC | C6: 10k以上 | D6: 0.036 | E6: 0.036 | F6: 0.0355 | G6: 0.0355 | H6: 0.0355 | I6: 0.0355 | J6: 0.0355 | K6: 0.0355 | L6: 0.0355 | M6: 0.036 | N6: 0.0385 | O6: 0.0385 | P6: 0.0385 | Q6: 0.0385 | R6: 0.0385 | S6: 0.0385 | T6: 0.0385 | U6: 0.038 | V6: 0.038 | W6: 0.039 | X6: 0.0405 | Y6: 0.0405 | Z6: 0.0405 | AA6: 0.0405 | AB6: 0.0405 | AC6: 0.0405 | AD6: 0.041 | AE6: 0.0415 | AF6: 0.0415 | AG6: 0.0415 | AH6: 0.0415 | AI6: 0.0415 | AJ6: 0.0415 | AK6: 0.0415 | AL6: 0.0415 | AM6: 0.0415 | AN6: 0.0415 | AO6: 0.0415 | AP6: 0.0415 | AQ6: 0.0415 | AR6: 0.0415 | AS6: 0.0415 | AT6: 0.0415 | AU6: 0.0415 | AV6: 0.0415 | AW6: 0.0415 | AX6: 0.0415 | AY6: 0.0415 | AZ6: 0.0415 | BA6: 0.0415 | BB6: 0.0415 | BC6: 0.0415 | BD6: 0.0415 | BE6: 0.0415 | BF6: 0.0415 | BG6: 0.0415 | BH6: 0.0415 | BI6: 0.0415 | BJ6: 0.0425 | BK6: 0.0445 | BL6: 0.0455 | BM6: 0.0455 | BN6: 0.0455 | BO6: 0.0455 | BP6: 0.0455 | BQ6: 0.0455 | BR6: 0.0455 | BS6: 0.0455 | BT6: 0.048 | BU6: 0.048 | BV6: 0.048 | BW6: 0.048 | BX6: 0.0485 | BY6: 0.049 | HN6: =$D6-$E6 -> 0 | HO6: 电子银行
B7: CIMB | C7: >10k | D7: 0.035 | E7: 0.035 | F7: 0.035 | G7: 0.035 | H7: 0.035 | I7: 0.035 | J7: 0.035 | K7: 0.035 | L7: 0.035 | M7: 0.035 | N7: 0.038 | O7: 0.038 | P7: 0.038 | Q7: 0.038 | R7: 0.038 | S7: 0.038 | T7: 0.038 | U7: 0.038 | V7: 0.038 | W7: 0.04 | X7: 0.04 | Y7: 0.04 | Z7: 0.04 | AA7: 0.04 | AB7: 0.041 | AC7: 0.041 | AD7: 0.041 | AE7: 0.041 | AF7: 0.041 | AG7: 0.041 | AH7: 0.041 | AI7: 0.041 | AJ7: 0.041 | AK7: 0.041 | AL7: 0.041 | AM7: 0.041 | AN7: 0.041 | AO7: 0.041 | AP7: 0.041 | AQ7: 0.041 | AR7: 0.041 | AS7: 0.041 | AT7: 0.041 | AU7: 0.041 | AV7: 0.041 | AW7: 0.041 | AX7: 0.041 | AY7: 0.041 | AZ7: 0.041 | BA7: 0.0425 | BB7: 0.0425 | BC7: 0.0425 | BD7: 0.0425 | BE7: 0.0425 | BF7: 0.0425 | BG7: 0.0425 | BH7: 0.043 | BI7: 0.043 | BJ7: 0.043 | BK7: 0.043 | BL7: 0.043 | BM7: 0.045 | BN7: 0.045 | BO7: 0.045 | BP7: 0.045 | BQ7: 0.047 | BR7: 0.047 | BS7: 0.047 | BT7: 0.047 | BU7: 0.047 | BV7: 0.047 | BW7: 0.047 | BX7: 0.047 | BY7: 0.047 | BZ7: 0.048 | CA7: 0.048 | CB7: 0.048 | CC7: 0.05 | CD7: 0.05 | CE7: 0.05 | CF7: 0.05 | CG7: 0.05 | CH7: 0.05 | CI7: 0.05 | CJ7: 0.05 | CK7: 0.05 | CL7: 0.05 | CM7: 0.05 | CN7: 0.05 | CO7: 0.05 | CP7: 0.05 | CQ7: 0.05 | CR7: 0.05 | CS7: 0.05 | CT7: 0.05 | CU7: 0.05 | CV7: 0.05 | CW7: 0.05 | CX7: 0.05 | CY7: 0.05 | CZ7: 0.05 | DA7: 0.05 | DB7: 0.05 | DC7: 0.05 | DD7: 0.05 | DE7: 0.05 | DF7: 0.0505 | DG7: 0.0505 | DH7: 0.0505 | DI7: 0.0505 | DJ7: 0.0505 | DK7: 0.0505 | DL7: 0.0505 | DM7: 0.0505 | DN7: 0.0505 | DO7: 0.0505 | DP7: 0.0505 | DQ7: 0.0505 | DR7: 0.0505 | DS7: 0.0505 | DT7: 0.05 | DU7: 0.05 | DV7: 0.05 | DW7: 0.05 | DX7: 0.05 | DY7: 0.05 | DZ7: 0.05 | EA7: 0.048 | EB7: 0.048 | EC7: 0.048 | ED7: 0.048 | EE7: 0.048 | EF7: 0.0475 | EG7: 0.027 | EH7: 0.022 | EI7: 0.022 | EJ7: 0.022 | EK7: 0.022 | EL7: 0.045 | EM7: 0.045 | EN7: 0.045 | EO7: 0.045 | EP7: 0.045 | EQ7: 0.045 | ER7: 0.045 | ES7: 0.045 | ET7: 0.044 | EU7: 0.044 | EV7: 0.044 | EW7: 0.044 | EX7: 0.044 | EY7: 0.044 | EZ7: 0.04 | FA7: 0.04 | FB7: 0.04 | FC7: 0.04 | FD7: 0.039 | FE7: 0.039 | FF7: 0.039 | FG7: 0.039 | FH7: 0.038 | FI7: 0.038 | FJ7: 0.038 | FK7: 0.038 | FL7: 0.038 | FM7: 0.033 | FN7: 0.033 | FO7: 0.033 | FP7: 0.033 | FQ7: 0.027 | FR7: 0.027 | FS7: 0.027 | FT7: 0.047 | FU7: 0.045 | FV7: 0.0475 | FW7: 0.0475 | FX7: 0.0475 | FY7: 0.047 | FZ7: 0.047 | GA7: 0.047 | GB7: 0.022 | GC7: 0.022 | GD7: 0.022 | GE7: 0.022 | GF7: 0.022 | GG7: 0.022 | GH7: 0.022 | GI7: 0.022 | GJ7: 0.022 | GK7: 0.022 | GL7: 0.022 | GM7: 0.022 | GN7: 0.022 | GO7: 0.022 | GP7: 0.022 | GQ7: 0.022 | GR7: 0.022 | GS7: 0.022 | GT7: 0.022 | GU7: 0.022 | GV7: 0.022 | GW7: 0.022 | GX7: 0.022 | GY7: 0.022 | GZ7: 0.022 | HA7: 0.022 | HB7: 0.022 | HC7: 0.022 | HD7: 0.022 | HE7: 0.022 | HF7: 0.022 | HG7: 0.022 | HH7: 0.022 | HI7: 0.022 | HJ7: 0.022 | HK7: 0.022 | HL7: 0.022 | HM7: 0.022 | HN7: =$D7-$E7 -> 0 | HO7: 电子银行
B8: CITI | C8: 50k-1mil | D8: 0.0325 | E8: 0.0325 | F8: 0.0325 | G8: 0.0325 | H8: 0.0325 | I8: 0.0325 | J8: 0.035 | K8: 0.035 | L8: 0.035 | M8: 0.035 | N8: 0.0375 | O8: 0.0375 | P8: 0.0375 | Q8: 0.0375 | R8: 0.0375 | S8: 0.0375 | T8: 0.0375 | U8: 0.0375 | V8: 0.0375 | W8: 0.0375 | X8: 0.0375 | Y8: 0.0375 | Z8: 0.0375 | AA8: 0.0375 | AB8: 0.0375 | AC8: 0.0375 | AD8: 0.0375 | AE8: 0.0375 | AF8: 0.04 | AG8: 0.04 | AH8: 0.04 | AI8: 0.04 | AJ8: 0.04 | AK8: 0.04 | AL8: 0.04 | AM8: 0.04 | AN8: 0.04 | AO8: 0.04 | AP8: 0.04 | AQ8: 0.04 | AR8: 0.04 | AS8: 0.04 | AT8: 0.04 | AU8: 0.04 | AV8: 0.04 | AW8: 0.04 | AX8: 0.04 | AY8: 0.04 | AZ8: 0.04 | BA8: 0.04 | BB8: 0.04 | BC8: 0.04 | BD8: 0.04 | BE8: 0.04 | BF8: 0.04 | BG8: 0.04 | BH8: 0.044 | BI8: 0.044 | BJ8: 0.044 | BK8: 0.044 | BL8: 0.046 | BM8: 0.046 | BN8: 0.046 | BO8: 0.046 | BP8: 0.046 | BQ8: 0.046 | BR8: 0.046 | BS8: 0.046 | BT8: 0.046 | BU8: 0.0475 | HN8: =$D8-$E8 -> 0 | HO8: 先做兑换
B9: BEA | C9: 100k及以上 | D9: 0.0325 | E9: 0.0325 | F9: 0.032 | G9: 0.032 | H9: 0.032 | I9: 0.032 | J9: 0.0315 | K9: 0.0315 | L9: 0.0315 | M9: 0.032 | N9: 0.034 | O9: 0.0335 | P9: 0.033 | Q9: 0.0325 | R9: 0.0335 | S9: 0.0345 | T9: 0.0327 | U9: 0.0327 | V9: 0.033 | W9: 0.0335 | X9: 0.034 | Y9: 0.034 | Z9: 0.034 | AA9: 0.0345 | AB9: 0.0345 | AC9: 0.0345 | AD9: 0.035 | AE9: 0.036 | AF9: 0.036 | AG9: 0.036 | AH9: 0.036 | AI9: 0.0365 | AJ9: 0.0365 | AK9: 0.0365 | AL9: 0.0365 | AM9: 0.0365 | AN9: 0.0365 | AO9: 0.0365 | AP9: 0.0365 | AQ9: 0.0365 | AR9: 0.0365 | AS9: 0.0365 | AT9: 0.0365 | AU9: 0.0365 | AV9: 0.0365 | HN9: =$D9-$E9 -> 0
B10: SCB | C10: >200K | D10: - | E10: - | F10: - | G10: - | H10: - | I10: - | J10: - | K10: - | L10: - | M10: - | N10: - | O10: 0.0438 | P10: 0.0438 | Q10: 0.0438 | HN10: =D10-E10 -> #VALUE! | LL10: 09/12/2025-17/12/2025
B13: Tenor: 3 months | GT13: 2022年（本周变动）
B14: 银行 | C14: 金额 | D14: =D4 -> 46099 | E14: =E4 -> 46092 | F14: =F4 -> 46085 | G14: =G4 -> 46078 | H14: 46071 | I14: =I4 -> 46057 | J14: =J4 -> 46050 | K14: =K4 -> 46043 | L14: =L4 -> 46036 | M14: =M4 -> 46029 | N14: =N4 -> 46022 | O14: =O4 -> 46015 | P14: =P4 -> 46008 | ... AF14: =AF4 -> 45896 | AG14: 45889 | AH14: 45882 | AI14: 45875 | AJ14: 45868 | AK14: 45861 | AL14: 45854 | AM14: 45847 | AN14: 45840 | AO14: =AO4 -> 45833 | AP14: 45826 | AQ14: =AQ4 -> 45819 | AR14: =AR4 -> 45812 | AS14: =AS4 -> 45805 | AT14: =AT4 -> 45798 | AU14: =AU4 -> 45792 | AV14: =AV4 -> 45785 | AW14: =AW4 -> 45777 | AX14: =AX4 -> 45763 | ... CF14: =CF4 -> 45511 | CG14: =#REF! -> #REF! | CH14: =#REF! -> #REF! | CI14: =#REF! -> #REF! | CJ14: =#REF! -> #REF! | CK14: =#REF! -> #REF! | CL14: =#REF! -> #REF! | CM14: =#REF! -> #REF! | CN14: =#REF! -> #REF! | ... ED14: =#REF! -> #REF! | EE14: 45141 | EF14: 45134 | EG14: 44839 | EH14: 44831 | EI14: 44826 | EJ14: 44818 | EK14: 44811 | EL14: 45070 | EM14: 45063 | EN14: 45056 | EO14: 45050 | EP14: 45042 | EQ14: 45035 | ER14: 45028 | ES14: 45020 | ET14: 45014 | EU14: 45008 | EV14: 45002 | EW14: 45000 | EX14: 44993 | EY14: 44986 | EZ14: 44979 | FA14: 44972 | FB14: 44965 | FC14: 44958 | FD14: 44951 | FE14: 44944 | FF14: 44937 | FG14: 44930 | FH14: 44923 | FI14: 44916 | FJ14: 44910 | FK14: 44902 | FL14: 44896 | FM14: 44888 | FN14: 44881 | FO14: 44874 | FP14: 44868 | FQ14: 44860 | FR14: 44853 | FS14: 44846 | FT14: 45085 | FU14: 45076 | FV14: 45127 | FW14: 45120 | FX14: 45113 | FY14: 45105 | FZ14: 45099 | GA14: 45092 | GB14: 44803 | GC14: 44797 | GD14: 44790 | GE14: 44783 | GF14: 44776 | GG14: 44769 | GH14: 44762 | GI14: 44755 | GJ14: 44748 | GK14: 44741 | GL14: 44733 | GM14: 44727 | GN14: 44720 | GO14: 44713 | GP14: 44706 | GQ14: 44699 | GR14: 44690 | GS14: 5月6日 | GT14: 5月4日 | GU14: 4月27日 | GV14: 4月19日 | GW14: 4月12日 | GX14: 4月11日 | GY14: 4月8日 | GZ14: 4月6日 | HA14: 4月5日 | HB14: 4月4日 | HC14: 4月1日 | HD14: 3月30日 | HE14: 3月29日 | HF14: 3月28日 | HG14: 3月25日 | HH14: 3月24日 | HI14: 3月22日 | HJ14: 3月21日 | HK14: 3月18日 | HL14: 3月17日 | HM14: 3月16日 | HN14: 当日增幅 | HO14: 其他要求
B15: BOC | C15: 10k以上 | D15: 0.036 | E15: 0.036 | F15: 0.0355 | G15: 0.0355 | H15: 0.0355 | I15: 0.0355 | J15: 0.0355 | K15: 0.0355 | L15: 0.0355 | M15: 0.036 | N15: 0.038 | O15: 0.0385 | P15: 0.0385 | Q15: 0.0385 | R15: 0.0385 | S15: 0.0385 | T15: 0.0385 | U15: 0.0375 | V15: 0.0375 | W15: 0.0385 | X15: 0.0395 | Y15: 0.0395 | Z15: 0.04 | AA15: 0.04 | AB15: 0.04 | AC15: 0.04 | AD15: 0.0405 | AE15: 0.041 | AF15: 0.041 | AG15: 0.0415 | AH15: 0.0415 | AI15: 0.0418 | AJ15: 0.0418 | AK15: 0.0418 | AL15: 0.042 | AM15: 0.0425 | AN15: 0.043 | AO15: 0.043 | AP15: 0.043 | AQ15: 0.043 | AR15: 0.043 | AS15: 0.043 | AT15: 0.043 | AU15: 0.043 | AV15: 0.043 | AW15: 0.043 | AX15: 0.043 | AY15: 0.043 | AZ15: 0.043 | BA15: 0.043 | BB15: 0.043 | BC15: 0.043 | BD15: 0.043 | BE15: 0.043 | BF15: 0.043 | BG15: 0.043 | BH15: 0.043 | BI15: 0.043 | BJ15: 0.043 | BK15: 0.045 | BL15: 0.046 | BM15: 0.046 | BN15: 0.046 | BO15: 0.046 | BP15: 0.046 | BQ15: 0.046 | BR15: 0.046 | BS15: 0.046 | BT15: 0.0475 | BU15: 0.0475 | BV15: 0.0475 | BW15: 0.0475 | BX15: 0.048 | BY15: 0.049 | BZ15: 0.051 | CA15: 0.051 | CB15: 0.0515 | CC15: 0.0515 | CD15: 0.0515 | CE15: 0.0515 | CF15: 0.0525 | CG15: 0.048 | CH15: 0.048 | CI15: 0.048 | CJ15: 0.048 | CK15: 0.048 | CL15: 0.048 | CM15: 0.048 | CN15: 0.048 | CO15: 0.048 | CP15: 0.048 | CQ15: 0.048 | CR15: 0.048 | CS15: 0.048 | CT15: 0.048 | CU15: 0.048 | CV15: 0.048 | CW15: 0.048 | CX15: 0.048 | CY15: 0.048 | CZ15: 0.048 | DA15: 0.048 | DB15: 0.048 | DC15: 0.048 | DD15: 0.048 | DE15: 0.048 | DF15: 0.048 | DG15: 0.048 | DH15: 0.048 | DI15: 0.048 | DJ15: 0.048 | DK15: 0.048 | DL15: 0.048 | DM15: 0.048 | DN15: 0.048 | DO15: 0.048 | DP15: 0.048 | DQ15: 0.048 | DR15: 0.048 | DS15: 0.048 | DT15: 0.048 | DU15: 0.048 | DV15: 0.048 | DW15: 0.048 | DX15: 0.048 | DY15: 0.048 | DZ15: 0.048 | EA15: 0.048 | EB15: 0.048 | EC15: 0.048 | ED15: 0.048 | EE15: 0.048 | EF15: 0.048 | EG15: 0.048 | EH15: 0.048 | EI15: 0.048 | EJ15: 0.048 | EK15: 0.048 | EL15: 0.048 | EM15: 0.048 | EN15: 0.048 | EO15: 0.048 | EP15: 0.048 | EQ15: 0.048 | ER15: 0.048 | ES15: 0.048 | ET15: 0.048 | EU15: 0.048 | EV15: 0.048 | EW15: 0.048 | EX15: 0.048 | EY15: 0.048 | EZ15: 0.048 | FA15: 0.048 | FB15: 0.048 | FC15: 0.048 | FD15: 0.048 | FE15: 0.048 | FF15: 0.048 | FG15: 0.048 | FH15: 0.048 | FI15: 0.048 | FJ15: 0.048 | FK15: 0.048 | FL15: 0.048 | FM15: 0.048 | FN15: 0.048 | FO15: 0.048 | FP15: 0.048 | FQ15: 0.048 | FR15: 0.048 | FS15: 0.048 | FT15: 0.048 | FU15: 0.048 | FV15: 0.048 | FW15: 0.048 | FX15: 0.048 | FY15: 0.048 | FZ15: 0.048 | GA15: 0.048 | GB15: 0.03 | GC15: 0.03 | GD15: 0.03 | GE15: 0.03 | GF15: 0.03 | GG15: 0.03 | GH15: 0.03 | GI15: 0.03 | GJ15: 0.03 | GK15: 0.03 | GL15: 0.03 | GM15: 0.03 | GN15: 0.03 | GO15: 0.03 | GP15: 0.03 | GQ15: 0.03 | GR15: 0.03 | GS15: 0.03 | GT15: 0.03 | GU15: 0.03 | GV15: 0.03 | GW15: 0.03 | GX15: 0.03 | GY15: 0.03 | GZ15: 0.03 | HA15: 0.03 | HB15: 0.03 | HC15: 0.03 | HD15: 0.03 | HE15: 0.03 | HF15: 0.03 | HG15: 0.03 | HH15: 0.03 | HI15: 0.03 | HJ15: 0.03 | HK15: 0.03 | HL15: 0.03 | HM15: 0.03 | HN15: =$D15-$E15 -> 0 | HO15: 电子银行
B16: CIMB | C16: >10k | D16: 0.036 | E16: 0.036 | F16: 0.036 | G16: 0.036 | H16: 0.036 | I16: 0.036 | J16: 0.036 | K16: 0.036 | L16: 0.036 | M16: 0.036 | N16: 0.039 | O16: 0.039 | P16: 0.039 | Q16: 0.039 | R16: 0.039 | S16: 0.039 | T16: 0.039 | U16: 0.039 | V16: 0.038 | W16: 0.039 | X16: 0.039 | Y16: 0.039 | Z16: 0.039 | AA16: 0.039 | AB16: 0.041 | AC16: 0.041 | AD16: 0.041 | AE16: 0.041 | AF16: 0.0425 | AG16: 0.0425 | AH16: 0.0425 | AI16: 0.0425 | AJ16: 0.0425 | AK16: 0.0425 | AL16: 0.0425 | AM16: 0.0425 | AN16: 0.0425 | AO16: 0.0425 | AP16: 0.0425 | AQ16: 0.0425 | AR16: 0.0425 | AS16: 0.0425 | AT16: 0.0425 | AU16: 0.0425 | AV16: 0.0425 | AW16: 0.0425 | AX16: 0.0425 | AY16: 0.0425 | AZ16: 0.0425 | BA16: 0.0425 | BB16: 0.0425 | BC16: 0.0425 | BD16: 0.0425 | BE16: 0.0425 | BF16: 0.0425 | BG16: 0.0425 | BH16: 0.044 | BI16: 0.044 | BJ16: 0.044 | BK16: 0.044 | BL16: 0.044 | BM16: 0.044 | BN16: 0.044 | BO16: 0.044 | BP16: 0.044 | BQ16: 0.047 | BR16: 0.047 | BS16: 0.047 | BT16: 0.047 | BU16: 0.047 | BV16: 0.047 | BW16: 0.047 | BX16: 0.047 | BY16: 0.047 | BZ16: 0.048 | CA16: 0.048 | CB16: 0.048 | CC16: 0.05 | CD16: 0.05 | CE16: 0.05 | CF16: 0.05 | CG16: 0.05 | CH16: 0.05 | CI16: 0.05 | CJ16: 0.05 | CK16: 0.05 | CL16: 0.05 | CM16: 0.05 | CN16: 0.05 | CO16: 0.05 | CP16: 0.05 | CQ16: 0.05 | CR16: 0.05 | CS16: 0.05 | CT16: 0.05 | CU16: 0.05 | CV16: 0.05 | CW16: 0.05 | CX16: 0.05 | CY16: 0.05 | CZ16: 0.05 | DA16: 0.05 | DB16: 0.05 | DC16: 0.05 | DD16: 0.05 | DE16: 0.05 | DF16: 0.051 | DG16: 0.051 | DH16: 0.051 | DI16: 0.051 | DJ16: 0.051 | DK16: 0.051 | DL16: 0.051 | DM16: 0.051 | DN16: 0.051 | DO16: 0.051 | DP16: 0.051 | DQ16: 0.051 | DR16: 0.051 | DS16: 0.051 | DT16: 0.051 | DU16: 0.051 | DV16: 0.051 | DW16: 0.05 | DX16: 0.05 | DY16: 0.05 | DZ16: 0.05 | EA16: 0.049 | EB16: 0.049 | EC16: 0.049 | ED16: 0.049 | EE16: 0.049 | EF16: 0.0485 | EG16: 0.032 | EH16: 0.029 | EI16: 0.029 | EJ16: 0.029 | EK16: 0.029 | EL16: 0.047 | EM16: 0.047 | EN16: 0.047 | EO16: 0.047 | EP16: 0.046 | EQ16: 0.046 | ER16: 0.046 | ES16: 0.046 | ET16: 0.047 | EU16: 0.047 | EV16: 0.047 | EW16: 0.047 | EX16: 0.047 | EY16: 0.047 | EZ16: 0.044 | FA16: 0.044 | FB16: 0.044 | FC16: 0.044 | FD16: 0.044 | FE16: 0.044 | FF16: 0.044 | FG16: 0.044 | FH16: 0.047 | FI16: 0.047 | FJ16: 0.047 | FK16: 0.047 | FL16: 0.047 | FM16: 0.042 | FN16: 0.042 | FO16: 0.042 | FP16: 0.042 | FQ16: 0.032 | FR16: 0.032 | FS16: 0.032 | FT16: 0.0475 | FU16: 0.047 | FV16: 0.0485 | FW16: 0.0485 | FX16: 0.0485 | FY16: 0.0475 | FZ16: 0.0475 | GA16: 0.0475 | GB16: 0.029 | GC16: 0.029 | GD16: 0.029 | GE16: 0.029 | GF16: 0.029 | GG16: 0.029 | GH16: 0.029 | GI16: 0.029 | GJ16: 0.029 | GK16: 0.029 | GL16: 0.029 | GM16: 0.029 | GN16: 0.029 | GO16: 0.029 | GP16: 0.029 | GQ16: 0.029 | GR16: 0.029 | GS16: 0.029 | GT16: 0.029 | GU16: 0.029 | GV16: 0.029 | GW16: 0.029 | GX16: 0.029 | GY16: 0.029 | GZ16: 0.029 | HA16: 0.029 | HB16: 0.029 | HC16: 0.029 | HD16: 0.029 | HE16: 0.029 | HF16: 0.029 | HG16: 0.029 | HH16: 0.029 | HI16: 0.029 | HJ16: 0.029 | HK16: 0.029 | HL16: 0.029 | HM16: 0.029 | HN16: =$D16-$E16 -> 0 | HO16: 电子银行
B17: ICBC | C17: 50,000及以上 | W17: 0.05 | X17: 0.05 | Y17: 0.05 | Z17: 0.05 | AA17: 0.05 | AB17: 0.05 | AC17: 0.05 | AD17: 0.05 | AE17: 0.05 | AF17: 0.05 | AG17: 0.05 | AH17: 0.05 | AI17: 0.05 | AJ17: 0.05 | AK17: 0.05 | AL17: 0.05 | AM17: 0.05 | AN17: 0.05 | AO17: 0.05 | AP17: 0.05 | AQ17: 0.05 | AR17: 0.05 | AS17: 0.05 | AT17: 0.05 | AU17: 0.05 | AV17: 0.05 | AW17: 0.05 | AX17: 0.05 | AY17: 0.05 | AZ17: 0.05 | BA17: 0.05 | BB17: 0.05 | BC17: 0.05 | BD17: 0.05 | BE17: 0.05 | BF17: 0.05 | BG17: 0.05 | BH17: 0.05 | BI17: 0.05 | BJ17: 0.05 | BK17: 0.05 | BL17: 0.05 | BM17: 0.05 | BN17: 0.05 | BO17: 0.05 | BP17: 0.05 | BQ17: 0.05 | BR17: 0.05 | BS17: 0.05 | BT17: 0.05 | BU17: 0.05 | BV17: 0.05 | BW17: 0.05 | BX17: 0.05 | BY17: 0.05 | BZ17: 0.05 | CA17: 0.05 | CB17: 0.05 | CC17: 0.05 | CD17: 0.05 | CE17: 0.05 | CF17: 0.05 | CG17: 0.05 | CH17: 0.05 | CI17: 0.05 | CJ17: 0.05 | CK17: 0.05 | CL17: 0.05 | HN17: =$D17-$E17 -> 0 | HO17: branch, new customer
C18: 500以上 | D18: 0.0365 | E18: 0.0365 | F18: 0.0365 | G18: 0.0365 | H18: 0.0365 | I18: 0.0365 | J18: 0.0365 | K18: 0.0365 | L18: 0.0365 | M18: 0.0375 | N18: 0.0375 | O18: 0.0375 | P18: 0.0385 | Q18: 0.0385 | R18: 0.0385 | S18: 0.0385 | T18: 0.0385 | U18: 0.039 | V18: 0.039 | W18: 0.039 | X18: 0.0405 | Y18: 0.0405 | Z18: 0.0405 | AA18: 0.0405 | AB18: 0.0405 | AC18: 0.0405 | AD18: 0.0405 | AE18: 0.0405 | AF18: 0.041 | AG18: 0.041 | AH18: 0.041 | AI18: 0.042 | AJ18: 0.042 | AK18: 0.042 | AL18: 0.042 | AM18: 0.042 | AN18: 0.042 | AO18: 0.042 | AP18: 0.042 | AQ18: 0.042 | AR18: 0.042 | AS18: 0.042 | AT18: 0.042 | AU18: 0.042 | AV18: 0.042 | AW18: 0.042 | AX18: 0.042 | AY18: 0.0425 | AZ18: 0.0425 | BA18: 0.0425 | BB18: 0.0425 | BC18: 0.0425 | BD18: 0.0425 | BE18: 0.0425 | BF18: 0.043 | BG18: 0.043 | BH18: 0.043 | BI18: 0.0435 | BJ18: 0.0435 | BK18: 0.045 | BL18: 0.045 | BM18: 0.045 | BN18: 0.045 | BO18: 0.045 | BP18: 0.045 | BQ18: 0.045 | BR18: 0.045 | BS18: 0.045 | BT18: 0.045 | BU18: 0.045 | BV18: 0.045 | BW18: 0.045 | BX18: 0.045 | BY18: 0.046 | BZ18: 0.0485 | CA18: 0.0485 | CB18: 0.0485 | CC18: 0.0485 | CD18: 0.0485 | CE18: 0.0485 | CF18: 0.0485 | HN18: =$D18-$E18 -> 0 | HO18: 电子银行
B19: SCB | C19: 25k以上 | W19: 0.045 | X19: 0.045 | Y19: 0.045 | Z19: 0.045 | AA19: 0.045 | AB19: 0.045 | AC19: 0.045 | AD19: 0.045 | AE19: 0.045 | AF19: 0.045 | AG19: 0.045 | AH19: 0.045 | AI19: 0.045 | AJ19: 0.045 | AK19: 0.045 | AL19: 0.045 | AM19: 0.045 | AN19: 0.045 | AO19: 0.045 | AP19: 0.045 | AQ19: 0.045 | AR19: 0.045 | AS19: 0.045 | AT19: 0.045 | AU19: 0.045 | AV19: 0.045 | AW19: 0.045 | AX19: 0.045 | AY19: 0.045 | AZ19: 0.045 | BA19: 0.045 | BB19: 0.045 | BC19: 0.045 | BD19: 0.045 | BE19: 0.045 | BF19: 0.045 | BG19: 0.045 | BH19: 0.045 | BI19: 0.045 | BJ19: 0.045 | BK19: 0.045 | BL19: 0.045 | BM19: 0.045 | BN19: 0.045 | BO19: 0.045 | BP19: 0.045 | BQ19: 0.045 | BR19: 0.045 | BS19: 0.045 | BT19: 0.045 | BU19: 0.045 | BV19: 0.045 | BW19: 0.045 | BX19: 0.045 | BY19: 0.045 | BZ19: 0.048 | CA19: 0.048 | CB19: 0.048 | CC19: 0.046 | CD19: 0.046 | CE19: 0.046 | CF19: 0.046 | CG19: 0.038834 | CH19: 0.038858 | CI19: 0.03904 | CJ19: 0.039182 | CK19: 0.039394 | CL19: 0.039436 | CM19: 0.039432 | CN19: 0.039429 | CO19: 0.039429 | CP19: 0.039267 | CQ19: 0.039224 | CR19: 0.039212 | CS19: 0.039268 | CT19: 0.039171 | CU19: 0.039171 | CV19: 0.038972 | CW19: 0.039081 | CX19: 0.039076 | CY19: 0.039052 | CZ19: 0.039052 | DA19: 0.039264 | DB19: 0.039432 | DC19: 0.03907 | DD19: 0.03907 | DE19: 0.039161 | DF19: 0.039064 | DG19: 0.039247 | DH19: 0.0382 | DI19: 0.039234 | DJ19: 0.039273 | DK19: 0.039479 | DL19: 0.039746 | DM19: 0.039861 | DN19: 0.039762 | DO19: 0.039882 | DP19: 0.039708 | DQ19: 0.039902 | DR19: 0.039657 | DS19: 0.039828 | DT19: 0.039796 | DU19: 0.039968 | DV19: 0.0402458 | DW19: 0.039998 | DX19: 0.03997 | DY19: 0.040082 | DZ19: 0.039911 | EA19: 0.040174 | EB19: 0.039773 | EC19: 0.039718 | ED19: 0.039699 | EE19: 0.039664 | EF19: 0.039574 | EG19: 0.022474 | EH19: 0.02419 | EI19: 0.023672 | EJ19: 0.018239 | EK19: 0.022469 | EL19: 0.037509 | EM19: 0.036897 | EN19: 0.036722 | EO19: 0.037114 | EP19: 0.03668 | EQ19: 0.036279 | ER19: 0.035587 | ES19: 0.035086 | ET19: 0.035012 | EU19: 0.034855 | EV19: 0.0333 | EW19: 0.0338 | EX19: 0.035417 | EY19: 0.035063 | EZ19: 0.034109 | FA19: 0.034108 | FB19: 0.033571 | FC19: 0.033317 | FD19: 0.033035 | FE19: 0.036416 | FF19: 0.03285 | FG19: 0.032375 | FH19: 0.031997 | FI19: 0.031575 | FJ19: 0.030318 | FK19: 0.030985 | FL19: 0.03049 | FM19: 0.029698 | FN19: 0.028754 | FO19: 0.028603 | FP19: 0.027909 | FQ19: 0.026955 | FR19: 0.02605 | FS19: 0.02389 | FT19: 0.038532 | FU19: 0.038637 | FV19: 0.038995 | FW19: 0.038995 | FX19: 0.038687 | FY19: 0.038387 | FZ19: 0.038203 | GA19: 0.038543 | GB19: 0.023672 | GC19: 0.023672 | GD19: 0.023672 | GE19: 0.023672 | GF19: 0.023672 | GG19: 0.023672 | GH19: 0.023672 | GI19: 0.023672 | GJ19: 0.023672 | GK19: 0.023672 | GL19: 0.023672 | GM19: 0.023672 | GN19: 0.023672 | GO19: 0.023672 | GP19: 0.023672 | GQ19: 0.023672 | GR19: 0.023672 | GS19: 0.023672 | GT19: 0.023672 | GU19: 0.023672 | GV19: 0.023672 | GW19: 0.023672 | GX19: 0.023672 | GY19: 0.023672 | GZ19: 0.023672 | HA19: 0.023672 | HB19: 0.023672 | HC19: 0.023672 | HD19: 0.023672 | HE19: 0.023672 | HF19: 0.023672 | HG19: 0.023672 | HH19: 0.023672 | HI19: 0.023672 | HJ19: 0.023672 | HK19: 0.023672 | HL19: 0.023672 | HM19: 0.023672 | HN19: =$D19-$E19 -> 0 | HO19: personal
W20: 0.046 | X20: 0.046 | Y20: 0.046 | Z20: 0.046 | AA20: 0.046 | AB20: 0.046 | AC20: 0.046 | AD20: 0.046 | AE20: 0.046 | AF20: 0.046 | AG20: 0.046 | AH20: 0.046 | AI20: 0.046 | AJ20: 0.046 | AK20: 0.046 | AL20: 0.046 | AM20: 0.046 | AN20: 0.046 | AO20: 0.046 | AP20: 0.046 | AQ20: 0.046 | AR20: 0.046 | AS20: 0.046 | AT20: 0.046 | AU20: 0.046 | AV20: 0.046 | AW20: 0.046 | AX20: 0.046 | AY20: 0.046 | AZ20: 0.046 | BA20: 0.046 | BB20: 0.046 | BC20: 0.046 | BD20: 0.046 | BE20: 0.046 | BF20: 0.046 | BG20: 0.046 | BH20: 0.046 | BI20: 0.046 | BJ20: 0.046 | BK20: 0.046 | BL20: 0.046 | BM20: 0.046 | BN20: 0.046 | BO20: 0.046 | BP20: 0.046 | BQ20: 0.046 | BR20: 0.046 | BS20: 0.046 | BT20: 0.046 | BU20: 0.046 | BV20: 0.046 | BW20: 0.046 | BX20: 0.046 | BY20: 0.046 | BZ20: 0.049 | CA20: 0.049 | CB20: 0.049 | CC20: 0.047 | CD20: 0.047 | CE20: 0.047 | CF20: 0.047 | CG20: 0.039834 | CH20: 0.039858 | CI20: 0.04004 | CJ20: 0.040182 | CK20: 0.040394 | CL20: 0.040436 | CM20: 0.040432 | CN20: 0.040429 | CO20: 0.040429 | CP20: 0.040267 | CQ20: 0.040224 | CR20: 0.040212 | CS20: 0.040269 | CT20: 0.040171 | CU20: 0.040171 | CV20: 0.039972 | CW20: 0.040081 | CX20: 0.040076 | CY20: 0.040052 | CZ20: 0.040052 | DA20: 0.040264 | DB20: 0.040432 | DC20: 0.04007 | DD20: 0.04007 | DE20: 0.040161 | DF20: 0.040064 | DG20: 0.040247 | DH20: 0.039979 | DI20: 0.040234 | DJ20: 0.040273 | DK20: 0.040479 | DL20: 0.040746 | DM20: 0.040861 | DN20: 0.040762 | DO20: 0.040882 | DP20: 0.040708 | DQ20: 0.040902 | DR20: 0.040657 | DS20: 0.040828 | DT20: 0.040796 | DU20: 0.040968 | DV20: 0.041258 | DW20: 0.040998 | DX20: 0.04097 | DY20: 0.041082 | DZ20: 0.040911 | EA20: 0.041174 | EB20: 0.040773 | EC20: 0.040718 | ED20: 0.040699 | EE20: 0.040664 | EF20: 0.040574 | EG20: 0.023474 | EH20: 0.025189 | EI20: 0.024672 | EJ20: 0.019239 | EK20: 0.024469 | EL20: 0.038509 | EM20: 0.037898 | EN20: 0.037722 | EO20: 0.038114 | EP20: 0.03768 | EQ20: 0.037279 | ER20: 0.036587 | ES20: 0.036086 | ET20: 0.036012 | EU20: 0.035855 | EV20: 0.0343 | EW20: 0.0348 | EX20: 0.036417 | EY20: 0.036063 | EZ20: 0.035109 | FA20: 0.035108 | FB20: 0.034571 | FC20: 0.034317 | FD20: 0.034035 | FE20: 0.037416 | FF20: 0.03385 | FG20: 0.033375 | FH20: 0.032997 | FI20: 0.032575 | FJ20: 0.031318 | FK20: 0.031985 | FL20: 0.03149 | FM20: 0.030698 | FN20: 0.029754 | FO20: 0.029603 | FP20: 0.028909 | FQ20: 0.027955 | FR20: 0.02705 | FS20: 0.02489 | FT20: 0.039532 | FU20: 0.039637 | FV20: 0.039995 | FW20: 0.039995 | FX20: 0.039687 | FY20: 0.039387 | FZ20: 0.039203 | GA20: 0.039543 | GB20: 0.024672 | GC20: 0.024672 | GD20: 0.024672 | GE20: 0.024672 | GF20: 0.024672 | GG20: 0.024672 | GH20: 0.024672 | GI20: 0.024672 | GJ20: 0.024672 | GK20: 0.024672 | GL20: 0.024672 | GM20: 0.024672 | GN20: 0.024672 | GO20: 0.024672 | GP20: 0.024672 | GQ20: 0.024672 | GR20: 0.024672 | GS20: 0.024672 | GT20: 0.024672 | GU20: 0.024672 | GV20: 0.024672 | GW20: 0.024672 | GX20: 0.024672 | GY20: 0.024672 | GZ20: 0.024672 | HA20: 0.024672 | HB20: 0.024672 | HC20: 0.024672 | HD20: 0.024672 | HE20: 0.024672 | HF20: 0.024672 | HG20: 0.024672 | HH20: 0.024672 | HI20: 0.024672 | HJ20: 0.024672 | HK20: 0.024672 | HL20: 0.024672 | HM20: 0.024672 | HN20: =$D20-$E20 -> 0 | HO20: priority
W21: 0.047 | X21: 0.047 | Y21: 0.047 | Z21: 0.047 | AA21: 0.047 | AB21: 0.047 | AC21: 0.047 | AD21: 0.047 | AE21: 0.047 | AF21: 0.047 | AG21: 0.047 | AH21: 0.047 | AI21: 0.047 | AJ21: 0.047 | AK21: 0.047 | AL21: 0.047 | AM21: 0.047 | AN21: 0.047 | AO21: 0.047 | AP21: 0.047 | AQ21: 0.047 | AR21: 0.047 | AS21: 0.047 | AT21: 0.047 | AU21: 0.047 | AV21: 0.047 | AW21: 0.047 | AX21: 0.047 | AY21: 0.047 | AZ21: 0.047 | BA21: 0.047 | BB21: 0.047 | BC21: 0.047 | BD21: 0.047 | BE21: 0.047 | BF21: 0.047 | BG21: 0.047 | BH21: 0.047 | BI21: 0.047 | BJ21: 0.047 | BK21: 0.047 | BL21: 0.047 | BM21: 0.047 | BN21: 0.047 | BO21: 0.047 | BP21: 0.047 | BQ21: 0.047 | BR21: 0.047 | BS21: 0.047 | BT21: 0.047 | BU21: 0.047 | BV21: 0.047 | BW21: 0.047 | BX21: 0.047 | BY21: 0.047 | BZ21: 0.05 | CA21: 0.05 | CB21: 0.05 | CC21: 0.048 | CD21: 0.048 | CE21: 0.048 | CF21: 0.048 | CG21: 0.040834 | CH21: 0.040858 | CI21: 0.04104 | CJ21: 0.041182 | CK21: 0.041394 | CL21: 0.041436 | CM21: 0.041432 | CN21: 0.041429 | CO21: 0.041429 | CP21: 0.041267 | CQ21: 0.041224 | CR21: 0.041212 | CS21: 0.041268 | CT21: 0.041171 | CU21: 0.041171 | CV21: 0.040972 | CW21: 0.041081 | CX21: 0.041076 | CY21: 0.041052 | CZ21: 0.041052 | DA21: 0.041264 | DB21: 0.041432 | DC21: 0.04107 | DD21: 0.04107 | DE21: 0.041161 | DF21: 0.041064 | DG21: 0.041247 | DH21: 0.040979 | DI21: 0.041234 | DJ21: 0.041273 | DK21: 0.041479 | DL21: 0.041746 | DM21: 0.041861 | DN21: 0.041762 | DO21: 0.041882 | DP21: 0.041708 | DQ21: 0.041902 | DR21: 0.041657 | DS21: 0.041828 | DT21: 0.041796 | DU21: 0.041968 | DV21: 0.042258 | DW21: 0.041998 | DX21: 0.04197 | DY21: 0.042082 | DZ21: 0.041911 | EA21: 0.042174 | EB21: 0.041773 | EC21: 0.041718 | ED21: 0.041699 | EE21: 0.041664 | EF21: 0.041574 | EG21: 0.024474 | EH21: 0.02619 | EI21: 0.025672 | EJ21: 0.020239 | EK21: 0.025469 | EL21: 0.039509 | EM21: 0.038897 | EN21: 0.038722 | EO21: 0.039114 | EP21: 0.03868 | EQ21: 0.038279 | ER21: 0.037587 | ES21: 0.037086 | ET21: 0.037012 | EU21: 0.036855 | EV21: 0.0353 | EW21: 0.0358 | EX21: 0.037417 | EY21: 0.037063 | EZ21: 0.036109 | FA21: 0.036108 | FB21: 0.035571 | FC21: 0.035317 | FD21: 0.035035 | FE21: 0.038416 | FF21: 0.03485 | FG21: 0.034375 | FH21: 0.033997 | FI21: 0.033575 | FJ21: 0.032318 | FK21: 0.032985 | FL21: 0.03249 | FM21: 0.031698 | FN21: 0.030754 | FO21: 0.030603 | FP21: 0.029909 | FQ21: 0.028955 | FR21: 0.02805 | FS21: 0.02589 | FT21: 0.040532 | FU21: 0.040637 | FV21: 0.040995 | FW21: 0.040995 | FX21: 0.040687 | FY21: 0.040387 | FZ21: 0.040203 | GA21: 0.040543 | GB21: 0.025672 | GC21: 0.025672 | GD21: 0.025672 | GE21: 0.025672 | GF21: 0.025672 | GG21: 0.025672 | GH21: 0.025672 | GI21: 0.025672 | GJ21: 0.025672 | GK21: 0.025672 | GL21: 0.025672 | GM21: 0.025672 | GN21: 0.025672 | GO21: 0.025672 | GP21: 0.025672 | GQ21: 0.025672 | GR21: 0.025672 | GS21: 0.025672 | GT21: 0.025672 | GU21: 0.025672 | GV21: 0.025672 | GW21: 0.025672 | GX21: 0.025672 | GY21: 0.025672 | GZ21: 0.025672 | HA21: 0.025672 | HB21: 0.025672 | HC21: 0.025672 | HD21: 0.025672 | HE21: 0.025672 | HF21: 0.025672 | HG21: 0.025672 | HH21: 0.025672 | HI21: 0.025672 | HJ21: 0.025672 | HK21: 0.025672 | HL21: 0.025672 | HM21: 0.025672 | HN21: =$D21-$E21 -> 0 | HO21: private
B22: HLB | C22: 50k | D22: 0.0365 | E22: 0.0365 | F22: 0.0365 | G22: 0.0365 | H22: 0.0365 | HN22: =$D22-$E22 -> 0 | HO22: branch exclusive
B23: HSBC | C23: 100K | W23: 0.042 | X23: 0.042 | Y23: 0.042 | Z23: 0.042 | AA23: 0.042 | AB23: 0.042 | AC23: 0.042 | AD23: 0.042 | AE23: 0.042 | AF23: 0.042 | AG23: 0.042 | AH23: 0.042 | AI23: 0.042 | AJ23: 0.042 | AK23: 0.042 | AL23: 0.042 | AM23: 0.042 | AN23: 0.042 | AO23: 0.042 | AP23: 0.042 | AQ23: 0.042 | AR23: 0.042 | AS23: 0.042 | AT23: 0.042 | AU23: 0.042 | AV23: 0.042 | AW23: 0.042 | AX23: 0.042 | AY23: 0.042 | AZ23: 0.042 | BA23: 0.042 | BB23: 0.042 | BC23: 0.042 | BD23: 0.042 | BE23: 0.042 | BF23: 0.042 | BG23: 0.042 | BH23: 0.042 | BI23: 0.042 | BJ23: 0.042 | BK23: 0.042 | BL23: 0.042 | BM23: 0.042 | BN23: 0.042 | BO23: 0.042 | BP23: 0.042 | BQ23: 0.042 | BR23: 0.042 | BS23: 0.042 | BT23: 0.042 | BU23: 0.042 | BV23: 0.042 | BW23: 0.044 | BX23: 0.044 | BY23: 0.044 | BZ23: 0.047 | CA23: 0.0465 | CB23: 0.0465 | CC23: 0.0485 | CD23: 0.0485 | CE23: 0.0485 | CF23: 0.0485 | HN23: =$D23-$E23 -> 0
C24: USD30K | D24: 0.03 | E24: 0.03 | F24: 0.03 | G24: 0.03 | H24: 0.03 | I24: 0.03 | J24: 0.03 | K24: 0.03 | L24: 0.03 | M24: 0.03 | N24: 0.03 | O24: 0.03 | P24: 0.03 | Q24: 0.03 | R24: 0.03 | S24: 0.031 | T24: 0.031 | U24: 0.031 | V24: 0.031 | W24: 0.031 | X24: 0.031 | Y24: 0.031 | Z24: 0.031 | AA24: 0.033 | AB24: 0.033 | AC24: 0.033 | AD24: 0.033 | AE24: 0.033 | AF24: 0.033 | AG24: 0.033 | AH24: 0.033 | AI24: 0.033 | AJ24: 0.033 | AK24: 0.032 | AL24: 0.032 | AM24: 0.032 | AN24: 0.032 | AO24: 0.0325 | AP24: 0.0325 | AQ24: 0.0325 | AR24: 0.0325 | AS24: 0.0335 | AT24: 0.0335 | AU24: 0.0335 | AV24: 0.0335 | AW24: 0.0345 | AX24: 0.036 | AY24: 0.036 | AZ24: 0.036 | BA24: 0.0395 | BB24: 0.0395 | BC24: 0.04 | BD24: 0.04 | BE24: 0.04 | BF24: 0.04 | BG24: 0.037 | BH24: 0.0408 | BI24: 0.0408 | BJ24: 0.0408 | BK24: 0.0408 | BL24: 0.041 | BM24: 0.041 | BN24: 0.041 | BO24: 0.041 | BP24: 0.041 | BQ24: 0.041 | BR24: 0.041 | BS24: 0.041 | BT24: 0.041 | BU24: 0.041 | BV24: 0.041 | BW24: 0.043 | BX24: 0.043 | BY24: 0.043 | BZ24: - | HN24: =$D24-$E24 -> 0 | HO24: personal
B25: SBI | C25: ≥25,000 | V25: - | W25: - | X25: - | Y25: - | Z25: - | AA25: - | AB25: - | AC25: - | AD25: - | AE25: - | AF25: - | AG25: - | AH25: - | AI25: - | AJ25: - | AK25: - | AL25: - | AM25: - | AN25: - | AO25: - | AP25: - | AQ25: - | AR25: - | AS25: - | AT25: - | AU25: - | AV25: - | AW25: - | AX25: - | AY25: - | AZ25: - | BA25: - | BB25: - | BC25: - | BD25: - | BE25: - | BF25: - | BG25: - | BH25: - | BI25: - | BJ25: - | BK25: - | BL25: - | BM25: - | BN25: - | BO25: - | BP25: - | BQ25: - | BR25: - | BS25: - | BT25: - | BU25: - | BV25: - | BW25: - | BX25: - | BY25: - | BZ25: - | CA25: - | CB25: - | CC25: - | CD25: - | CE25: - | CF25: - | CG25: - | CH25: - | CI25: - | CJ25: - | CK25: - | CL25: - | CM25: - | CN25: - | CO25: - | CP25: - | CQ25: - | CR25: - | CS25: - | CT25: - | CU25: - | CV25: - | CW25: - | CX25: - | CY25: - | CZ25: - | DA25: - | DB25: - | DC25: - | DD25: - | DE25: - | DF25: - | DG25: - | DH25: - | DI25: - | DJ25: - | DK25: - | DL25: - | DM25: - | DN25: - | DO25: - | DP25: - | DQ25: - | DR25: - | DS25: - | DT25: - | DU25: - | DV25: - | DW25: - | DX25: - | DY25: - | DZ25: - | EA25: - | EB25: - | EC25: - | ED25: - | EE25: - | EF25: - | EG25: - | EH25: - | EI25: - | EJ25: - | EK25: - | EL25: - | EM25: - | EN25: - | EO25: - | EP25: - | EQ25: - | ER25: - | ES25: - | ET25: - | EU25: - | EV25: - | EW25: - | EX25: - | EY25: - | EZ25: - | FA25: - | FB25: - | FC25: - | FD25: - | FE25: - | FF25: - | FG25: - | FH25: - | FI25: - | FJ25: - | FK25: - | FL25: - | FM25: - | FN25: - | FO25: - | FP25: - | FQ25: - | FR25: - | FS25: - | FT25: - | FU25: - | FV25: - | FW25: - | FX25: - | FY25: - | FZ25: - | GA25: - | GB25: - | GC25: - | GD25: - | GE25: - | GF25: - | GG25: - | GH25: - | GI25: - | GJ25: - | GK25: - | GL25: - | GM25: - | GN25: - | GO25: - | GP25: - | GQ25: - | GR25: - | GS25: - | GT25: - | GU25: - | GV25: - | GW25: - | GX25: - | GY25: - | GZ25: - | HA25: - | HB25: - | HC25: - | HD25: - | HE25: - | HF25: - | HG25: - | HH25: - | HI25: - | HJ25: - | HK25: - | HL25: - | HM25: - | HO25: branch
B26: BEA | C26: 100k及以上 | D26: 0.0345 | E26: 0.0345 | F26: 0.0335 | G26: 0.0335 | H26: 0.0335 | I26: 0.0335 | J26: 0.0335 | K26: 0.033 | L26: 0.0325 | M26: 0.0335 | N26: 0.034 | O26: 0.034 | P26: 0.034 | Q26: 0.0345 | R26: 0.0345 | S26: 0.0355 | T26: 0.0342 | U26: 0.0332 | V26: 0.0345 | W26: 0.035 | X26: 0.0355 | Y26: 0.0355 | Z26: 0.0355 | AA26: 0.036 | AB26: 0.036 | AC26: 0.037 | AD26: 0.0375 | AE26: 0.0385 | AF26: 0.039 | AG26: 0.039 | AH26: 0.039 | AI26: 0.0395 | AJ26: 0.0395 | AK26: 0.0395 | AL26: 0.0395 | AM26: 0.0395 | AN26: 0.0395 | AO26: 0.0395 | AP26: 0.0395 | AQ26: 0.0395 | AR26: 0.0395 | AS26: 0.0395 | AT26: 0.0395 | AU26: 0.0395 | AV26: 0.0395 | HN26: =$D26-$E26 -> 0 | HO26: New Fund
B27: RHB | C27: ≥USD5,000 | D27: 0.034 | E27: 0.034 | F27: 0.034 | G27: 0.034 | HN27: =$D27-$E27 -> 0
B28: SCB | C28: Personal Banking (USD 25K) | I28: 0.0395 | J28: 0.0395 | L28: 0.036 | M28: 0.037 | N28: 0.037 | O28: 0.038 | P28: 0.038 | Q28: 0.038 | R28: 0.038 | S28: 0.035 | T28: 0.035 | U28: 0.035 | V28: 0.035 | W28: 0.035 | X28: 0.036 | Y28: 0.037 | Z28: 0.038 | AA28: 0.038 | AB28: 0.038 | AC28: 0.039 | AD28: 0.039 | AE28: 0.039 | AF28: 0.039 | AG28: 0.039 | AH28: 0.039 | AI28: 0.04 | AJ28: 0.04 | AK28: 0.04 | AL28: 0.04 | AM28: 0.04 | AN28: 0.04 | AO28: 0.04 | AP28: 0.04 | AQ28: 0.04 | AR28: 0.04 | AS28: 0.04 | AT28: 0.04 | AU28: 0.04 | AV28: 0.04 | AW28: 0.04 | AX28: 0.039 | AY28: 0.039 | AZ28: 0.039 | BA28: 0.039 | BB28: 0.039 | BC28: 0.042 | BD28: 0.042 | BE28: 0.042 | BF28: 0.041 | BG28: 0.041 | BH28: 0.041 | BI28: 0.041 | BJ28: 0.041 | BK28: 0.041 | BL28: 0.041 | BM28: 0.043 | BN28: 0.043 | BO28: 0.043 | BP28: 0.043 | BQ28: 0.043 | BR28: 0.043 | BS28: 0.043 | BT28: 0.043 | BV28: 0.045 | BW28: 0.045 | BX28: 0.045 | BY28: 0.045 | BZ28: 0.048 | CA28: 0.048 | CB28: 0.048 | CC28: 0.046 | CD28: 0.046 | CE28: 0.046 | CF28: 0.046 | CG28: 0.038834 | CH28: 0.038858 | CI28: 0.03904 | CJ28: 0.039182 | CK28: 0.039394 | CL28: 0.039436 | CM28: 0.039432 | CN28: 0.039429 | CO28: 0.039429 | CP28: 0.039267 | CQ28: 0.039224 | CR28: 0.039212 | CS28: 0.039268 | CT28: 0.039171 | CU28: 0.039171 | CV28: 0.038972 | CW28: 0.039081 | CX28: 0.039076 | CY28: 0.039052 | CZ28: 0.039052 | DA28: 0.039264 | DB28: 0.039432 | DC28: 0.03907 | DD28: 0.03907 | DE28: 0.039161 | DF28: 0.039064 | DG28: 0.039247 | DH28: 0.0382 | DI28: 0.039234 | DJ28: 0.039273 | DK28: 0.039479 | DL28: 0.039746 | DM28: 0.039861 | DN28: 0.039762 | DO28: 0.039882 | DP28: 0.039708 | DQ28: 0.039902 | DR28: 0.039657 | DS28: 0.039828 | DT28: 0.039796 | DU28: 0.039968 | DV28: 0.0402458 | DW28: 0.039998 | DX28: 0.03997 | DY28: 0.040082 | DZ28: 0.039911 | EA28: 0.040174 | EB28: 0.039773 | EC28: 0.039718 | ED28: 0.039699 | EE28: 0.039664 | EF28: 0.039574 | EG28: 0.022474 | EH28: 0.02419 | EI28: 0.023672 | EJ28: 0.018239 | EK28: 0.022469 | EL28: 0.037509 | EM28: 0.036897 | EN28: 0.036722 | EO28: 0.037114 | EP28: 0.03668 | EQ28: 0.036279 | ER28: 0.035587 | ES28: 0.035086 | ET28: 0.035012 | EU28: 0.034855 | EV28: 0.0333 | EW28: 0.0338 | EX28: 0.035417 | EY28: 0.035063 | EZ28: 0.034109 | FA28: 0.034108 | FB28: 0.033571 | FC28: 0.033317 | FD28: 0.033035 | FE28: 0.036416 | FF28: 0.03285 | FG28: 0.032375 | FH28: 0.031997 | FI28: 0.031575 | FJ28: 0.030318 | FK28: 0.030985 | FL28: 0.03049 | FM28: 0.029698 | FN28: 0.028754 | FO28: 0.028603 | FP28: 0.027909 | FQ28: 0.026955 | FR28: 0.02605 | FS28: 0.02389 | FT28: 0.038532 | FU28: 0.038637 | FV28: 0.038995 | FW28: 0.038995 | FX28: 0.038687 | FY28: 0.038387 | FZ28: 0.038203 | GA28: 0.038543 | GB28: 0.023672 | GC28: 0.023672 | GD28: 0.023672 | GE28: 0.023672 | GF28: 0.023672 | GG28: 0.023672 | GH28: 0.023672 | GI28: 0.023672 | GJ28: 0.023672 | GK28: 0.023672 | GL28: 0.023672 | GM28: 0.023672 | GN28: 0.023672 | GO28: 0.023672 | GP28: 0.023672 | GQ28: 0.023672 | GR28: 0.023672 | GS28: 0.023672 | GT28: 0.023672 | GU28: 0.023672 | GV28: 0.023672 | GW28: 0.023672 | GX28: 0.023672 | GY28: 0.023672 | GZ28: 0.023672 | HA28: 0.023672 | HB28: 0.023672 | HC28: 0.023672 | HD28: 0.023672 | HE28: 0.023672 | HF28: 0.023672 | HG28: 0.023672 | HH28: 0.023672 | HI28: 0.023672 | HJ28: 0.023672 | HK28: 0.023672 | HL28: 0.023672 | HM28: 0.023672 | HN28: =$D28-$E28 -> 0 | HO28: personal
C29: Priority Banking (USD 25K) | I29: 0.04 | J29: 0.04 | L29: 0.037 | M29: 0.038 | N29: 0.038 | O29: 0.039 | P29: 0.039 | Q29: 0.039 | R29: 0.039 | S29: 0.036 | T29: 0.036 | U29: 0.036 | V29: 0.036 | W29: 0.036 | X29: 0.037 | Y29: 0.038 | Z29: 0.039 | AA29: 0.039 | AB29: 0.039 | AC29: 0.04 | AD29: 0.04 | AE29: 0.04 | AF29: 0.04 | AG29: 0.04 | AH29: 0.04 | AI29: 0.041 | AJ29: 0.041 | AK29: 0.041 | AL29: 0.041 | AM29: 0.041 | AN29: 0.041 | AO29: 0.041 | AP29: 0.041 | AQ29: 0.041 | AR29: 0.041 | AS29: 0.041 | AT29: 0.041 | AU29: 0.041 | AV29: 0.041 | AW29: 0.041 | AX29: 0.04 | AY29: 0.04 | AZ29: 0.04 | BA29: 0.04 | BB29: 0.04 | BC29: 0.043 | BD29: 0.043 | BE29: 0.043 | BF29: 0.042 | BG29: 0.042 | BH29: 0.042 | BI29: 0.042 | BJ29: 0.042 | BK29: 0.042 | BL29: 0.042 | BM29: 0.044 | BN29: 0.044 | BO29: 0.044 | BP29: 0.044 | BQ29: 0.044 | BR29: 0.044 | BS29: 0.044 | BT29: 0.044 | BV29: 0.046 | BW29: 0.046 | BX29: 0.046 | BY29: 0.046 | BZ29: 0.049 | CA29: 0.049 | CB29: 0.049 | CC29: 0.047 | CD29: 0.047 | CE29: 0.047 | CF29: 0.047 | CG29: 0.039834 | CH29: 0.039858 | CI29: 0.04004 | CJ29: 0.040182 | CK29: 0.040394 | CL29: 0.040436 | CM29: 0.040432 | CN29: 0.040429 | CO29: 0.040429 | CP29: 0.040267 | CQ29: 0.040224 | CR29: 0.040212 | CS29: 0.040269 | CT29: 0.040171 | CU29: 0.040171 | CV29: 0.039972 | CW29: 0.040081 | CX29: 0.040076 | CY29: 0.040052 | CZ29: 0.040052 | DA29: 0.040264 | DB29: 0.040432 | DC29: 0.04007 | DD29: 0.04007 | DE29: 0.040161 | DF29: 0.040064 | DG29: 0.040247 | DH29: 0.039979 | DI29: 0.040234 | DJ29: 0.040273 | DK29: 0.040479 | DL29: 0.040746 | DM29: 0.040861 | DN29: 0.040762 | DO29: 0.040882 | DP29: 0.040708 | DQ29: 0.040902 | DR29: 0.040657 | DS29: 0.040828 | DT29: 0.040796 | DU29: 0.040968 | DV29: 0.041258 | DW29: 0.040998 | DX29: 0.04097 | DY29: 0.041082 | DZ29: 0.040911 | EA29: 0.041174 | EB29: 0.040773 | EC29: 0.040718 | ED29: 0.040699 | EE29: 0.040664 | EF29: 0.040574 | EG29: 0.023474 | EH29: 0.025189 | EI29: 0.024672 | EJ29: 0.019239 | EK29: 0.024469 | EL29: 0.038509 | EM29: 0.037898 | EN29: 0.037722 | EO29: 0.038114 | EP29: 0.03768 | EQ29: 0.037279 | ER29: 0.036587 | ES29: 0.036086 | ET29: 0.036012 | EU29: 0.035855 | EV29: 0.0343 | EW29: 0.0348 | EX29: 0.036417 | EY29: 0.036063 | EZ29: 0.035109 | FA29: 0.035108 | FB29: 0.034571 | FC29: 0.034317 | FD29: 0.034035 | FE29: 0.037416 | FF29: 0.03385 | FG29: 0.033375 | FH29: 0.032997 | FI29: 0.032575 | FJ29: 0.031318 | FK29: 0.031985 | FL29: 0.03149 | FM29: 0.030698 | FN29: 0.029754 | FO29: 0.029603 | FP29: 0.028909 | FQ29: 0.027955 | FR29: 0.02705 | FS29: 0.02489 | FT29: 0.039532 | FU29: 0.039637 | FV29: 0.039995 | FW29: 0.039995 | FX29: 0.039687 | FY29: 0.039387 | FZ29: 0.039203 | GA29: 0.039543 | GB29: 0.024672 | GC29: 0.024672 | GD29: 0.024672 | GE29: 0.024672 | GF29: 0.024672 | GG29: 0.024672 | GH29: 0.024672 | GI29: 0.024672 | GJ29: 0.024672 | GK29: 0.024672 | GL29: 0.024672 | GM29: 0.024672 | GN29: 0.024672 | GO29: 0.024672 | GP29: 0.024672 | GQ29: 0.024672 | GR29: 0.024672 | GS29: 0.024672 | GT29: 0.024672 | GU29: 0.024672 | GV29: 0.024672 | GW29: 0.024672 | GX29: 0.024672 | GY29: 0.024672 | GZ29: 0.024672 | HA29: 0.024672 | HB29: 0.024672 | HC29: 0.024672 | HD29: 0.024672 | HE29: 0.024672 | HF29: 0.024672 | HG29: 0.024672 | HH29: 0.024672 | HI29: 0.024672 | HJ29: 0.024672 | HK29: 0.024672 | HL29: 0.024672 | HM29: 0.024672 | HN29: =$D29-$E29 -> 0 | HO29: priority
C30: Priority Private Banking (USD 25K) | I30: 0.0405 | J30: 0.0405 | L30: 0.038 | M30: 0.039 | N30: 0.039 | O30: 0.04 | P30: 0.04 | Q30: 0.04 | R30: 0.04 | S30: 0.037 | T30: 0.037 | U30: 0.037 | V30: 0.037 | W30: 0.037 | X30: 0.038 | Y30: 0.039 | Z30: 0.04 | AA30: 0.04 | AB30: 0.04 | AC30: 0.041 | AD30: 0.041 | AE30: 0.041 | AF30: 0.041 | AG30: 0.041 | AH30: 0.041 | AI30: 0.042 | AJ30: 0.042 | AK30: 0.042 | AL30: 0.042 | AM30: 0.042 | AN30: 0.042 | AO30: 0.042 | AP30: 0.042 | AQ30: 0.042 | AR30: 0.042 | AS30: 0.042 | AT30: 0.042 | AU30: 0.042 | AV30: 0.042 | AW30: 0.042 | AX30: 0.041 | AY30: 0.041 | AZ30: 0.041 | BA30: 0.041 | BB30: 0.041 | BC30: 0.044 | BD30: 0.044 | BE30: 0.044 | BF30: 0.043 | BG30: 0.043 | BH30: 0.043 | BI30: 0.043 | BJ30: 0.043 | BK30: 0.043 | BL30: 0.043 | BM30: 0.045 | BN30: 0.045 | BO30: 0.045 | BP30: 0.045 | BQ30: 0.045 | BR30: 0.045 | BS30: 0.045 | BT30: 0.045 | BV30: 0.047 | BW30: 0.047 | BX30: 0.047 | BY30: 0.047 | BZ30: 0.05 | CA30: 0.05 | CB30: 0.05 | CC30: 0.048 | CD30: 0.048 | CE30: 0.048 | CF30: 0.048 | CG30: 0.040834 | CH30: 0.040858 | CI30: 0.04104 | CJ30: 0.041182 | CK30: 0.041394 | CL30: 0.041436 | CM30: 0.041432 | CN30: 0.041429 | CO30: 0.041429 | CP30: 0.041267 | CQ30: 0.041224 | CR30: 0.041212 | CS30: 0.041268 | CT30: 0.041171 | CU30: 0.041171 | CV30: 0.040972 | CW30: 0.041081 | CX30: 0.041076 | CY30: 0.041052 | CZ30: 0.041052 | DA30: 0.041264 | DB30: 0.041432 | DC30: 0.04107 | DD30: 0.04107 | DE30: 0.041161 | DF30: 0.041064 | DG30: 0.041247 | DH30: 0.040979 | DI30: 0.041234 | DJ30: 0.041273 | DK30: 0.041479 | DL30: 0.041746 | DM30: 0.041861 | DN30: 0.041762 | DO30: 0.041882 | DP30: 0.041708 | DQ30: 0.041902 | DR30: 0.041657 | DS30: 0.041828 | DT30: 0.041796 | DU30: 0.041968 | DV30: 0.042258 | DW30: 0.041998 | DX30: 0.04197 | DY30: 0.042082 | DZ30: 0.041911 | EA30: 0.042174 | EB30: 0.041773 | EC30: 0.041718 | ED30: 0.041699 | EE30: 0.041664 | EF30: 0.041574 | EG30: 0.024474 | EH30: 0.02619 | EI30: 0.025672 | EJ30: 0.020239 | EK30: 0.025469 | EL30: 0.039509 | EM30: 0.038897 | EN30: 0.038722 | EO30: 0.039114 | EP30: 0.03868 | EQ30: 0.038279 | ER30: 0.037587 | ES30: 0.037086 | ET30: 0.037012 | EU30: 0.036855 | EV30: 0.0353 | EW30: 0.0358 | EX30: 0.037417 | EY30: 0.037063 | EZ30: 0.036109 | FA30: 0.036108 | FB30: 0.035571 | FC30: 0.035317 | FD30: 0.035035 | FE30: 0.038416 | FF30: 0.03485 | FG30: 0.034375 | FH30: 0.033997 | FI30: 0.033575 | FJ30: 0.032318 | FK30: 0.032985 | FL30: 0.03249 | FM30: 0.031698 | FN30: 0.030754 | FO30: 0.030603 | FP30: 0.029909 | FQ30: 0.028955 | FR30: 0.02805 | FS30: 0.02589 | FT30: 0.040532 | FU30: 0.040637 | FV30: 0.040995 | FW30: 0.040995 | FX30: 0.040687 | FY30: 0.040387 | FZ30: 0.040203 | GA30: 0.040543 | GB30: 0.025672 | GC30: 0.025672 | GD30: 0.025672 | GE30: 0.025672 | GF30: 0.025672 | GG30: 0.025672 | GH30: 0.025672 | GI30: 0.025672 | GJ30: 0.025672 | GK30: 0.025672 | GL30: 0.025672 | GM30: 0.025672 | GN30: 0.025672 | GO30: 0.025672 | GP30: 0.025672 | GQ30: 0.025672 | GR30: 0.025672 | GS30: 0.025672 | GT30: 0.025672 | GU30: 0.025672 | GV30: 0.025672 | GW30: 0.025672 | GX30: 0.025672 | GY30: 0.025672 | GZ30: 0.025672 | HA30: 0.025672 | HB30: 0.025672 | HC30: 0.025672 | HD30: 0.025672 | HE30: 0.025672 | HF30: 0.025672 | HG30: 0.025672 | HH30: 0.025672 | HI30: 0.025672 | HJ30: 0.025672 | HK30: 0.025672 | HL30: 0.025672 | HM30: 0.025672 | HN30: =$D30-$E30 -> 0 | HO30: private
B33: Tenor: 6 months
B34: 银行 | C34: 金额 | D34: =D4 -> 46099 | E34: =E4 -> 46092 | F34: =F4 -> 46085 | G34: =G4 -> 46078 | H34: 46071 | I34: =I4 -> 46057 | J34: =J4 -> 46050 | K34: =K4 -> 46043 | L34: =L4 -> 46036 | M34: =M4 -> 46029 | N34: =N4 -> 46022 | O34: =O4 -> 46015 | P34: =P4 -> 46008 | ... AF34: =AF4 -> 45896 | AG34: 45889 | AH34: 45882 | AI34: 45875 | AJ34: 45868 | AK34: 45861 | AL34: 45854 | AM34: 45847 | AN34: 45840 | AO34: =AO4 -> 45833 | AP34: 45826 | AQ34: =AQ4 -> 45819 | AR34: =AR4 -> 45812 | AS34: =AS4 -> 45805 | AT34: =AT4 -> 45798 | AU34: =AU4 -> 45792 | AV34: =AV4 -> 45785 | AW34: =AW4 -> 45777 | AX34: =AX4 -> 45763 | ... CF34: =CF4 -> 45511 | CG34: =#REF! -> #REF! | CH34: =#REF! -> #REF! | CI34: =#REF! -> #REF! | CJ34: =#REF! -> #REF! | CK34: =#REF! -> #REF! | CL34: =#REF! -> #REF! | CM34: =#REF! -> #REF! | CN34: =#REF! -> #REF! | ... DL34: =#REF! -> #REF! | DM34: 45274 | DN34: 45148 | DO34: 45148 | DP34: 45148 | DQ34: 45148 | DR34: 45148 | DS34: 45148 | DT34: 45148 | DU34: 45148 | DV34: 45148 | DW34: 45148 | DX34: =#REF! -> #REF! | DY34: 45148 | DZ34: 45148 | EA34: 45148 | EB34: 45148 | EC34: 45148 | ED34: 45148 | EE34: 45141 | EF34: 45134 | EG34: 44839 | EH34: 44831 | EI34: 44826 | EJ34: 44818 | EK34: 44811 | EL34: 45070 | EM34: 45063 | EN34: 45056 | EO34: 45050 | EP34: 45042 | EQ34: 45035 | ER34: 45028 | ES34: 45020 | ET34: 45014 | EU34: 45008 | EV34: 45002 | EW34: 45000 | EX34: 44993 | EY34: 44986 | EZ34: 44979 | FA34: 44972 | FB34: 44965 | FC34: 44958 | FD34: 44951 | FE34: 44944 | FF34: 44937 | FG34: 44930 | FH34: 44923 | FI34: 44916 | FJ34: 44910 | FK34: 44902 | FL34: 44896 | FM34: 44888 | FN34: 44881 | FO34: 44874 | FP34: 44868 | FQ34: 44860 | FR34: 44853 | FS34: 44846 | FT34: 45085 | FU34: 45076 | FV34: 45127 | FW34: 45120 | FX34: 45113 | FY34: 45105 | FZ34: 45099 | GA34: 45092 | GB34: 44803 | GC34: 44797 | GD34: 44790 | GE34: 44783 | GF34: 44776 | GG34: 44769 | GH34: 44762 | GI34: 44755 | GJ34: 44748 | GK34: 44741 | GL34: 44733 | GM34: 44727 | GN34: 44720 | GO34: 44713 | GP34: 44706 | GQ34: 44699 | GR34: 44690 | GS34: 5月6日 | GT34: 5月4日 | GU34: 4月27日 | GV34: 4月19日 | GW34: 4月12日 | GX34: 4月11日 | GY34: 4月8日 | GZ34: 4月6日 | HA34: 4月5日 | HB34: 4月4日 | HC34: 4月1日 | HD34: 3月30日 | HE34: 3月29日 | HF34: 3月28日 | HG34: 3月25日 | HH34: 3月24日 | HI34: 3月22日 | HJ34: 3月21日 | HK34: 3月18日 | HL34: 3月17日 | HM34: 3月16日 | HN34: 当日增幅 | HO34: 其他要求
B35: BOC | C35: ≥10,000 | D35: 0.036 | E35: 0.036 | F35: 0.0355 | G35: 0.0355 | H35: 0.0355 | I35: 0.0355 | J35: 0.0355 | K35: 0.0355 | L35: 0.0355 | M35: 0.036 | N35: 0.0375 | O35: 0.0375 | P35: 0.0375 | Q35: 0.0375 | R35: 0.0375 | S35: 0.0375 | T35: 0.0375 | U35: 0.0375 | V35: 0.0375 | W35: 0.038 | X35: 0.039 | Y35: 0.039 | Z35: 0.039 | AA35: 0.039 | AB35: 0.039 | AC35: 0.0395 | AD35: 0.04 | AE35: 0.0405 | AF35: 0.0405 | AG35: 0.041 | AH35: 0.041 | AI35: 0.0418 | AJ35: 0.0418 | AK35: 0.0418 | AL35: 0.0418 | AM35: 0.042 | AN35: 0.042 | AO35: 0.042 | AP35: 0.042 | AQ35: 0.042 | AR35: 0.042 | AS35: 0.042 | AT35: 0.042 | AU35: 0.042 | AV35: 0.042 | AW35: 0.042 | AX35: 0.042 | AY35: 0.042 | AZ35: 0.042 | BA35: 0.042 | BB35: 0.042 | BC35: 0.042 | BD35: 0.042 | BE35: 0.042 | BF35: 0.042 | BG35: 0.042 | BH35: 0.042 | BI35: 0.042 | BJ35: 0.042 | BK35: 0.043 | BL35: 0.044 | BM35: 0.044 | BN35: 0.044 | BO35: 0.044 | BP35: 0.044 | BQ35: 0.044 | BR35: 0.044 | BS35: 0.044 | BT35: 0.045 | BU35: 0.045 | BV35: 0.045 | BW35: 0.045 | BX35: 0.045 | BY35: 0.046 | BZ35: - | GB35: 0.025 | GC35: 0.025 | GD35: 0.025 | GE35: 0.025 | GF35: 0.025 | GG35: 0.025 | GH35: 0.025 | GI35: 0.025 | GJ35: 0.025 | GK35: 0.025 | GL35: 0.025 | GM35: 0.025 | GN35: 0.025 | GO35: 0.025 | GP35: 0.025 | GQ35: 0.025 | GR35: 0.025 | GS35: 0.025 | GT35: 0.025 | GU35: 0.025 | GV35: 0.025 | GW35: 0.025 | GX35: 0.025 | GY35: 0.025 | GZ35: 0.025 | HA35: 0.025 | HB35: 0.025 | HC35: 0.025 | HD35: 0.025 | HE35: 0.025 | HF35: 0.025 | HG35: 0.025 | HH35: 0.025 | HI35: 0.025 | HJ35: 0.025 | HK35: 0.025 | HL35: 0.025 | HM35: 0.025 | HN35: =$D35-$E35 -> 0 | HO35: 电子银行
